Workbook

Sheet DG_quarterly_balance-sheet
A1: name | B1: 45138 | C1: 45046 | D1: 44957 | E1: 44865 | F1: 44773 | G1: 44681 | H1: 44592 | I1: 44500 | J1: 44408 | K1: 44316 | L1: 44227 | M1: 44135 | N1: 44043 | O1: 43951 | P1: 43861 | Q1: 43769 | R1: 43677 | S1: 43585 | T1: 43496 | U1: 43404 | V1: 43312 | W1: 43220 | X1: 43131 | Y1: 43039 | Z1: 42947 | AA1: 42855 | AB1: 42766 | AC1: 42674 | AD1: 42582 | AE1: 42490 | AF1: 42400 | AG1: 42308 | AH1: 42216 | AI1: 42124 | AJ1: 42035 | AK1: 41943 | AL1: 41851 | AM1: 41759 | AN1: 41670 | AO1: 41578 | AP1: 41486 | AQ1: 41394 | AR1: 41305 | AS1: 41213 | AT1: 41121 | AU1: 41029 | AV1: 40939 | AW1: 40847 | AX1: 40755 | AY1: 40663 | AZ1: 40574 | BA1: 40482 | BB1: 40390 | BC1: 40298 | BD1: 40209 | BE1: 40117 | BF1: 40025 | BG1: 39933 | BH1: 39844 | BI1: 39752 | BJ1: 39660 | BK1: 39568 | BL1: 39478 | BM1: 39202 | BN1: 39113 | BO1: 39021 | BP1: 38929 | BQ1: 38837 | BR1: 38748 | BS1: 38656 | BT1: 38564 | BU1: 38472 | BV1: 38383 | BW1: 38291 | BX1: 38199 | BY1: 38107 | BZ1: 38017 | CA1: 37925 | CB1: 37833 | CC1: 37741 | CD1: 37652 | CE1: 37560 | CF1: 37468 | CG1: 37376 | CH1: 37287 | CI1: 37195 | CJ1: 37103 | CK1: 37011 | CL1: 36922 | CM1: 36830 | CN1: 36738 | CO1: 36646 | CP1: 36556 | CQ1: 36464 | CR1: 36372 | CS1: 36280 | CT1: 36191 | CU1: 36099 | CV1: 36007 | CW1: 35915 | CX1: 35826 | CY1: 35734 | CZ1: 35642 | DA1: 35550 | DB1: 35461 | DC1: 35369 | DD1: 35277 | DE1: 35185 | DF1: 35095 | DG1: 35003 | DH1: 34911 | DI1: 34819 | DJ1: 34730 | DK1: 34638 | DL1: 34546 | DM1: 34454 | DN1: 34365 | DO1: 34273 | DP1: 34181 | DQ1: 34089 | DR1: 34000 | DS1: 33908 | DT1: 33816 | DU1: 33724 | DV1: 33634 | DW1: 33542 | DX1: 33450 | DY1: 33358 | DZ1: 33269 | EA1: 33177 | EB1: 33085 | EC1: 32993 | ED1: 32904 | EE1: 32812 | EF1: 32720 | EG1: 32539 | EH1: 32142 | EI1: 31777 | EJ1: 31412
A2: TotalAssets | B2: 30395557000 | C2: 29803933000 | D2: 29083367000 | E2: 29007158000 | F2: 28239256000 | G2: 26956308000 | H2: 26327371000 | I2: 25925302000 | J2: 25487808000 | K2: 25236698000 | L2: 25862624000 | M2: 26153442000 | N2: 25847433000 | O2: 24848313000 | P2: 22825084000 | Q2: 22412790000 | R2: 21917529000 | S2: 21304284000 | T2: 13204038000 | U2: 13121021000 | V2: 12943949000 | W2: 12493230000 | X2: 12516911000 | Y2: 12374756000 | Z2: 12120824000 | AA2: 11796355000 | AB2: 11672298000 | AC2: 11917076000 | AD2: 11617370000 | AE2: 11316384000 | AF2: 11257885000 | AG2: 11288293000 | AH2: 11195195000 | AI2: 10956550000 | AJ2: 11224104000 | AK2: 10877372000 | AL2: 10825794000 | AM2: 10601884000 | AN2: 10867524000 | AO2: 10775974000 | AP2: 10699630000 | AQ2: 10493697000 | AR2: 10367682000 | AS2: 10273677000 | AT2: 10103474000 | AU2: 9770208000 | AV2: 9688520000 | AW2: 9735882000 | AX2: 9529103000 | AY2: 9714864000 | AZ2: 9546222000 | BA2: 9349574000 | BB2: 9179474000 | BC2: 8977076000 | BD2: 8863519000 | BE2: 9132532000 | BF2: 9139944000 | BG2: 8978801000 | BH2: 8889199000 | BI2: 8940101000 | BJ2: 8909790000 | BK2: 8662999000 | BL2: 8656431000 | BM2: 3074309000 | BN2: 3040514000 | BO2: 3206303000 | BP2: 3245197000 | BQ2: 3063467000 | BR2: 2992187000 | BS2: 2930781000 | BT2: 2840366000 | BU2: 2904538000 | BV2: 2841004000 | BW2: 2828017000 | BX2: 2655005000 | BY2: 2673769000 | BZ2: 2652709000 | CA2: 2589194000 | CB2: 2365381000 | CC2: 2355967000 | CD2: 2333153000 | CE2: 2411164000 | CF2: 2265229000 | CG2: 2588732000 | CH2: 2552385000 | CI2: 2469266000 | CJ2: 2330324000 | CK2: 2301594000 | CL2: 2282462000 | CM2: 1768009000 | CN2: 1626962000 | CO2: 1518270000 | CP2: 1450941000 | CQ2: 1549100000 | CR2: 1342100000 | CS2: 1325400000 | CT2: 1211784000 | CU2: 1299000000 | CV2: 1151200000 | CW2: 1016500000 | CX2: 914838000 | CY2: 1019600000 | CZ2: 864600000 | DA2: 796000000 | DB2: 718147000 | DC2: 845000000 | DD2: 719900000 | DE2: 732600000 | DF2: 679996000 | DG2: 769000000 | DH2: 647000000 | DI2: 622000000 | DJ2: 540868000 | DK2: 554900000 | DL2: 481000000 | DM2: 439800000 | DN2: 397200000 | DO2: 454400000 | DP2: 376200000 | DQ2: 374000000 | DR2: 316400000 | DS2: 357500000 | DT2: 297900000 | DU2: 292800000 | DV2: 237300000 | DW2: 297000000 | DX2: 260000000 | DY2: 244100000 | DZ2: 207700000 | EA2: 269900000 | EB2: 245500000 | EC2: 248800000 | ED2: 193800000 | EE2: 249900000 | EF2: 229900000 | EG2: 210300000 | EH2: 224900000 | EI2: 232400000 | EJ2: 227600000
A3: CurrentAssets | B3: 8413979000 | C3: 8055460000 | D3: 7581009000 | E3: 8017016000 | F3: 7682892000 | G3: 6736870000 | H3: 6303843000 | I3: 6181834000 | J3: 5992718000 | K3: 6041745000 | L3: 6914219000 | M3: 7533432000 | N3: 7597408000 | O3: 6992483000 | P3: 5177868000 | Q3: 5068542000 | R3: 4919138000 | S3: 4583769000 | T3: 4663020000 | U3: 4630344000 | V3: 4517826000 | W3: 4166036000 | X3: 4247852000 | Y3: 4153334000 | Z3: 3979991000 | AA3: 3748949000 | AB3: 3677771000 | AC3: 3968512000 | AD3: 3708051000 | AE3: 3477346000 | AF3: 3432410000 | AG3: 3488775000 | AH3: 3424847000 | AI3: 3244900000 | AJ3: 3532609000 | AK3: 3179132000 | AL3: 3140631000 | AM3: 2943346000 | AN3: 3205607000 | AO3: 2904302000 | AP3: 2864743000 | AQ3: 2724476000 | AR3: 2677113000 | AS3: 2618192000 | AT3: 2514444000 | AU3: 2273735000 | AV3: 2275074000 | AW3: 2392855000 | AX3: 2272781000 | AY3: 2506897000 | AZ3: 2367825000 | BA3: 2272758000 | BB3: 2134684000 | BC3: 1938578000 | BD3: 1845449000 | BE3: 2117314000 | BF3: 2145779000 | BG3: 1962148000 | BH3: 1870125000 | BI3: 1886297000 | BJ3: 1852801000 | BK3: 1595140000 | BL3: 1517744000 | BM3: 1786157000 | BN3: 1742748000 | BO3: 1917991000 | BP3: 1953880000 | BQ3: 1808755000 | BR3: 1762925000 | BS3: 1744650000 | BT3: 1698663000 | BU3: 1783195000 | BV3: 1730902000 | BW3: 1722234000 | BX3: 1586642000 | BY3: 1629658000 | BZ3: 1652215000 | CA3: 1598700000 | CB3: 1367308000 | CC3: 1355391000 | CD3: 1323908000 | CE3: 1390393000 | CF3: 1244105000 | CG3: 1588266000 | CH3: 1556047000 | CI3: 1346941000 | CJ3: 1140679000 | CK3: 1126236000 | CL3: 1124927000 | CM3: 1257107000 | CN3: 1164356000 | CO3: 1137045000 | CP3: 1095535000 | CQ3: 1213700000 | CR3: 1028800000 | CS3: 999100000 | CT3: 878917000 | CU3: 1003400000 | CV3: 874200000 | CW3: 756600000 | CX3: 666709000 | CY3: 775900000 | CZ3: 638400000 | DA3: 596800000 | DB3: 504599000 | DC3: 660500000 | DD3: 552200000 | DE3: 570500000 | DF3: 516243000 | DG3: 609500000 | DH3: 501600000 | DI3: 486900000 | DJ3: 410153000 | DK3: 442300000 | DL3: 383100000 | DM3: 353600000 | DN3: 315000000 | DO3: 377100000 | DP3: 305100000 | DQ3: 309700000 | DR3: 255700000 | DS3: 301300000 | DT3: 246600000 | DU3: 244900000 | DV3: 192400000 | DW3: 254400000 | DX3: 218900000 | DY3: 204100000 | DZ3: 168200000 | EA3: 229700000 | EB3: 206400000 | EC3: 210000000 | ED3: 155200000 | EE3: 212400000 | EF3: 196500000 | EG3: 182600000 | EH3: 190400000 | EI3: 194200000 | EJ3: 189400000
A4: CashCashEquivalentsAndShortTermInvestments | B4: 353018000 | C4: 313064000 | D4: 381576000 | E4: 362731000 | F4: 326263000 | G4: 335613000 | H4: 344829000 | I4: 488662000 | J4: 313666000 | K4: 688055000 | L4: 1376577000 | M4: 2199443000 | N4: 2959604000 | O4: 2673912000 | P4: 240320000 | Q4: 276076000 | R4: 259568000 | S4: 271111000 | T4: 235487000 | U4: 260688000 | V4: 265288000 | W4: 283970000 | X4: 267441000 | Y4: 226192000 | Z4: 214173000 | AA4: 205977000 | AB4: 187915000 | AC4: 200236000 | AD4: 185033000 | AE4: 187687000 | AF4: 157947000 | AG4: 182514000 | AH4: 180525000 | AI4: 225116000 | AJ4: 579823000 | AK4: 216155000 | AL4: 172474000 | AM4: 166330000 | AN4: 505566000 | AO4: 165717000 | AP4: 169220000 | AQ4: 155526000 | AR4: 140809000 | AS4: 142580000 | AT4: 134157000 | AU4: 132530000 | AV4: 126126000 | AW4: 118580000 | AX4: 113050000 | AY4: 602463000 | AZ4: 497446000 | BA4: 237906000 | BB4: 281421000 | BC4: 222709000 | BD4: 222076000 | BE4: 337019000 | BF4: 515375000 | BG4: 434584000 | BH4: 377995000 | BI4: 150590000 | BJ4: 264227000 | BK4: 164475000 | BL4: 119820000 | BM4: 231788000 | BN4: 219238000 | BO4: 120314000 | BP4: 107882000 | BQ4: 90701000 | BR4: 209459000 | BS4: 94186000 | BT4: 145950000 | BU4: 236523000 | BV4: 275755000 | BW4: 45832000 | BX4: 101465000 | BY4: 256883000 | BZ4: 398278000 | CA4: 138470000 | CB4: 102276000 | CC4: 75946000 | CD4: 121318000 | CE4: 37101000 | CF4: 39517000 | CG4: 287424000 | CH4: 261525000 | CI4: 74819000 | CJ4: 81630000 | CK4: 160894000 | CL4: 162310000 | CM4: 13080000 | CN4: 14040000 | CO4: 28397000 | CP4: 58789000 | CQ4: 35700000 | CR4: 25300000 | CS4: 25600000 | CT4: 22294000 | CU4: 18300000 | CV4: 33200000 | CW4: 37200000 | CX4: 7128000 | CY4: 13200000 | CZ4: 24900000 | DA4: 33400000 | DB4: 6563000 | DC4: 8800000 | DD4: 13000000 | DE4: 19400000 | DF4: 4344000 | DG4: 4100000 | DH4: 14000000 | DI4: 41100000 | DJ4: 33045000 | DK4: 25600000 | DL4: 26800000 | DM4: 30300000 | DN4: 35400000 | DO4: 33200000 | DP4: 22600000 | DQ4: 17400000 | DR4: 25000000 | DS4: 29300000 | DT4: 18100000 | DU4: 13900000 | DV4: 7900000 | DW4: 7600000 | DX4: 8800000 | DY4: 5900000 | DZ4: 3900000 | EA4: 12600000 | EB4: 7300000 | EC4: 8400000 | ED4: 6500000 | EE4: 2700000 | EF4: 3500000 | EG4: 5700000 | EH4: 7300000 | EI4: 5200000 | EJ4: 6800000
A5: CashAndCashEquivalents | B5: 353018000 | C5: 313064000 | D5: 381576000 | E5: 362731000 | F5: 326263000 | G5: 335613000 | H5: 344829000 | I5: 488662000 | J5: 313666000 | K5: 688055000 | L5: 1376577000 | M5: 2199443000 | N5: 2959604000 | O5: 2673912000 | P5: 240320000 | Q5: 276076000 | R5: 259568000 | S5: 271111000 | T5: 235487000 | U5: 260688000 | V5: 265288000 | W5: 283970000 | X5: 267441000 | Y5: 226192000 | Z5: 214173000 | AA5: 205977000 | AB5: 187915000 | AC5: 200236000 | AD5: 185033000 | AE5: 187687000 | AF5: 157947000 | AG5: 182514000 | AH5: 180525000 | AI5: 225116000 | AJ5: 579823000 | AK5: 216155000 | AL5: 172474000 | AM5: 166330000 | AN5: 505566000 | AO5: 165717000 | AP5: 169220000 | AQ5: 155526000 | AR5: 140809000 | AS5: 142580000 | AT5: 134157000 | AU5: 132530000 | AV5: 126126000 | AW5: 118580000 | AX5: 113050000 | AY5: 602463000 | AZ5: 497446000 | BA5: 237906000 | BB5: 281421000 | BC5: 222709000 | BD5: 222076000 | BE5: 337019000 | BF5: 515375000 | BG5: 434584000 | BH5: 377995000 | BI5: 150590000 | BJ5: 261630000 | BK5: 115904000 | BL5: 100209000 | BM5: 204417000 | BN5: 189288000 | BO5: 90914000 | BP5: 86352000 | BQ5: 71876000 | BR5: 200609000 | BS5: 92769000 | BT5: 145950000 | BU5: 236523000 | BV5: 232830000 | BW5: 45832000 | BX5: 101465000 | BY5: 256883000 | BZ5: 398278000 | CA5: 138470000 | CB5: 102276000 | CC5: 75946000 | CD5: 121318000 | CE5: 37101000 | CF5: 39517000 | CG5: 287424000 | CH5: 261525000 | CI5: 74819000 | CJ5: 81630000 | CK5: 160894000 | CL5: 162310000 | CM5: 13080000 | CN5: 14040000 | CO5: 28397000 | CP5: 58789000 | CQ5: 35700000 | CR5: 25300000 | CS5: 25600000 | CT5: 22294000 | CU5: 18300000 | CV5: 33200000 | CW5: 37200000 | CX5: 7128000 | CY5: 13200000 | CZ5: 24900000 | DA5: 33400000 | DB5: 6563000 | DC5: 8800000 | DD5: 13000000 | DE5: 19400000 | DF5: 4344000 | DG5: 4100000 | DH5: 14000000 | DI5: 41100000 | DJ5: 33045000 | DK5: 25600000 | DL5: 26800000 | DM5: 30300000 | DN5: 35400000 | DO5: 33200000 | DP5: 22600000 | DQ5: 17400000 | DR5: 25000000 | DS5: 29300000 | DT5: 18100000 | DU5: 13900000 | DV5: 7900000 | DW5: 7600000 | DX5: 8800000 | DY5: 5900000 | DZ5: 3900000 | EA5: 12600000 | EB5: 7300000 | EC5: 8400000 | ED5: 6500000 | EE5: 2700000 | EF5: 3500000 | EG5: 5700000 | EH5: 7300000 | EI5: 5200000 | EJ5: 6800000
A6: OtherShortTermInvestments | BH6: 0 | BI6: 0 | BJ6: 2597000 | BK6: 48571000 | BL6: 19611000 | BM6: 27371000 | BN6: 29950000 | BO6: 29400000 | BP6: 21530000 | BQ6: 18825000 | BR6: 8850000 | BS6: 1417000 | BT6: 0 | BU6: 0 | BV6: 42925000
A7: Receivables | B7: 151730000 | C7: 50863000 | D7: 135775000 | E7: 188082000 | F7: 93283000 | G7: 33576000 | H7: 97394000 | I7: 120374000 | J7: 127011000 | K7: 16637000 | L7: 90760000 | M7: 111139000 | N7: 36176000 | O7: 17191000 | P7: 76537000 | Q7: 103188000 | R7: 61692000 | S7: 25164000 | T7: 57804000 | U7: 114647000 | V7: 68353000 | W7: 28637000 | X7: 108265000 | Y7: 99678000 | Z7: 44255000 | AA7: 10492000 | AB7: 11050000 | AC7: 54586000 | AD7: 22985000 | AE7: 6827000 | AF7: 6843000 | AG7: 11877000 | AH7: 14646000 | AL7: 4237000 | AO7: 9786000 | AP7: 7894000 | AS7: 13554000 | AT7: 89473000 | AU7: 5210000 | AW7: 48807000 | AX7: 43435000 | AZ7: 0 | BA7: 27677000 | BB7: 0 | BC7: 0 | BD7: 7543000 | BE7: 31268000 | BF7: 5450000 | BG7: 3479000 | BH7: 6392000 | BI7: 42986000 | BJ7: 12829000 | BK7: 33813000 | BL7: 32501000 | BM7: 14624000 | BN7: 9833000 | BP7: 38753000 | CF7: 55573000 | EE7: 202400000
A8: TaxesReceivable | B8: 151730000 | C8: 50863000 | D8: 135775000 | E8: 188082000 | F8: 93283000 | G8: 33576000 | H8: 97394000 | I8: 120374000 | J8: 127011000 | K8: 16637000 | L8: 90760000 | M8: 111139000 | N8: 36176000 | O8: 17191000 | P8: 76537000 | Q8: 103188000 | R8: 61692000 | S8: 25164000 | T8: 57804000 | U8: 114647000 | V8: 68353000 | W8: 28637000 | X8: 108265000 | Y8: 99678000 | Z8: 44255000 | AA8: 10492000 | AB8: 11050000 | AC8: 54586000 | AD8: 22985000 | AE8: 6827000 | AF8: 6843000 | AG8: 11877000 | AH8: 14646000 | AL8: 4237000 | AO8: 9786000 | AP8: 7894000 | AS8: 13554000 | AT8: 89473000 | AU8: 5210000 | AW8: 48807000 | AX8: 43435000 | AZ8: 0 | BA8: 27677000 | BB8: 0 | BC8: 0 | BD8: 7543000 | BE8: 31268000 | BF8: 5450000 | BG8: 3479000 | BH8: 6392000 | BI8: 42986000 | BJ8: 12829000 | BK8: 33813000 | BL8: 32501000 | BM8: 14624000 | BN8: 9833000 | BP8: 38753000 | CF8: 55573000
A9: Inventory | B9: 7531459000 | C9: 7335845000 | D9: 6760733000 | E9: 7144722000 | F9: 6935856000 | G9: 6087399000 | H9: 5614325000 | I9: 5298859000 | J9: 5279273000 | K9: 5099465000 | L9: 5247477000 | M9: 5025810000 | N9: 4391157000 | O9: 4107331000 | P9: 4676848000 | Q9: 4496377000 | R9: 4419628000 | S9: 4109759000 | T9: 4097004000 | U9: 3979105000 | V9: 3896432000 | W9: 3594529000 | X9: 3609025000 | Y9: 3597195000 | Z9: 3463004000 | AA9: 3300082000 | AB9: 3258785000 | AC9: 3488247000 | AD9: 3270685000 | AE9: 3072063000 | AF9: 3074153000 | AG9: 3101908000 | AH9: 3029731000 | AI9: 2839198000 | AJ9: 2782521000 | AK9: 2788996000 | AL9: 2788872000 | AM9: 2605356000 | AN9: 2552993000 | AO9: 2591552000 | AP9: 2533766000 | AQ9: 2414411000 | AR9: 2397175000 | AS9: 2330436000 | AT9: 2147837000 | AU9: 2000864000 | AV9: 2009206000 | AW9: 2089722000 | AX9: 1973863000 | AY9: 1767121000 | AZ9: 1765433000 | BA9: 1885753000 | BB9: 1738439000 | BC9: 1604754000 | BD9: 1519578000 | BE9: 1680273000 | BF9: 1552586000 | BG9: 1454692000 | BH9: 1414955000 | BI9: 1619922000 | BJ9: 1490063000 | BK9: 1317097000 | BL9: 1288661000 | BM9: 1444313000 | BN9: 1432336000 | BO9: 1676057000 | BP9: 1735031000 | BQ9: 1636118000 | BR9: 1474414000 | BS9: 1574567000 | BT9: 1460700000 | BU9: 1465981000 | BV9: 1376537000 | BW9: 1558574000 | BX9: 1379543000 | BY9: 1277185000 | BZ9: 1157141000 | CA9: 1373200000 | CB9: 1184709000 | CC9: 1200701000 | CD9: 1123031000 | CE9: 1249120000 | CF9: 1058200000 | CG9: 1134449000 | CH9: 1131023000 | CI9: 1133215000 | CJ9: 980856000 | CK9: 905534000 | CL9: 896235000 | CM9: 1173328000 | CN9: 1062175000 | CO9: 995495000 | CP9: 985715000 | CQ9: 1105500000 | CR9: 951100000 | CS9: 939200000 | CT9: 811722000 | CU9: 944300000 | CV9: 797300000 | CW9: 692700000 | CX9: 631954000 | CY9: 737300000 | CZ9: 589700000 | DA9: 541000000 | DB9: 476103000 | DC9: 623400000 | DD9: 513700000 | DE9: 526100000 | DF9: 488362000 | DG9: 580900000 | DH9: 462600000 | DI9: 420000000 | DJ9: 356111000 | DK9: 392600000 | DL9: 332600000 | DM9: 304200000 | DN9: 260000000 | DO9: 322600000 | DP9: 263700000 | DQ9: 276900000 | DR9: 216800000 | DS9: 258100000 | DT9: 215200000 | DU9: 217400000 | DV9: 172800000 | DW9: 235200000 | DX9: 197600000 | DY9: 187600000 | DZ9: 154800000 | EA9: 208500000 | EB9: 191000000 | EC9: 192400000 | ED9: 140400000 | EF9: 186000000 | EG9: 171000000 | EH9: 177100000 | EI9: 183900000 | EJ9: 178200000
A10: FinishedGoods | B10: 7531459000 | C10: 7335845000 | D10: 6760733000 | E10: 7144722000 | F10: 6935856000 | G10: 6087399000 | H10: 5614325000 | I10: 5298859000 | J10: 5279273000 | K10: 5099465000 | L10: 5247477000 | M10: 5025810000 | N10: 4391157000 | O10: 4107331000 | P10: 4676848000 | Q10: 4496377000 | R10: 4419628000 | S10: 4109759000 | T10: 4097004000 | U10: 3979105000 | V10: 3896432000 | W10: 3594529000 | X10: 3609025000 | Y10: 3597195000 | Z10: 3463004000 | AA10: 3300082000 | AB10: 3258785000 | AC10: 3488247000 | AD10: 3270685000 | AE10: 3072063000 | AF10: 3074153000 | AG10: 3101908000 | AH10: 3029731000 | AI10: 2839198000 | AJ10: 2782521000 | AK10: 2788996000 | AL10: 2788872000 | AM10: 2605356000 | AN10: 2552993000 | AO10: 2591552000 | AP10: 2533766000 | AQ10: 2414411000 | AR10: 2397175000
A11: PrepaidAssets | E11: 321481000 | F11: 327490000 | G11: 280282000 | H11: 247295000 | I11: 273939000 | J11: 272768000 | K11: 237588000 | L11: 199405000 | M11: 197040000 | N11: 210471000 | O11: 194049000 | P11: 184163000 | Q11: 192901000 | R11: 178250000 | S11: 177735000 | T11: 272725000 | U11: 275904000 | V11: 287753000 | W11: 258900000 | X11: 263121000 | Y11: 230269000 | Z11: 258559000 | AA11: 232398000 | AB11: 220021000 | AC11: 225443000 | AD11: 229348000 | AE11: 210769000 | AF11: 193467000 | AG11: 192476000 | AH11: 199945000 | AI11: 180586000 | AJ11: 170265000 | AK11: 173981000 | AL11: 175048000 | AM11: 171660000 | AN11: 147048000 | AO11: 137247000 | AP11: 153863000 | AQ11: 154539000 | AR11: 139129000 | AS11: 131622000 | AT11: 142977000 | AU11: 135131000 | AV11: 139742000 | AW11: 135746000 | AX11: 142433000 | AY11: 137313000 | AZ11: 104946000 | BA11: 121422000 | BB11: 114824000 | BC11: 111115000 | BD11: 96252000 | BE11: 68754000 | BF11: 72368000 | BG11: 69393000 | BH11: 66183000 | BI11: 72799000 | BJ11: 68287000 | BK11: 64508000 | BL11: 59465000 | BM11: 57572000 | BN11: 57020000 | BO11: 71993000 | BP11: 71212000 | BQ11: 79569000 | BR11: 67140000 | BS11: 61549000 | BT11: 58305000 | BU11: 59166000 | BV11: 53702000
A12: CurrentDeferredAssets | BD12: 0 | BE12: 0 | BF12: 0 | BG12: 0 | BH12: 4600000 | BI12: 0 | BJ12: 17395000 | BK12: 15247000 | BL12: 17297000 | BM12: 37860000 | BN12: 24321000 | BO12: 49627000 | BP12: 1002000 | BQ12: 2367000 | BR12: 11912000 | BS12: 14348000 | BT12: 33708000 | BU12: 21525000 | BV12: 24908000 | BW12: 17305000 | BX12: 10997000 | BY12: 21852000 | BZ12: 30413000 | CA12: 21729000 | CB12: 22829000 | CC12: 26664000 | CD12: 33860000 | CE12: 43095000 | CF12: 25552000 | CG12: 80974000 | CH12: 105091000 | CI12: 90307000 | CJ12: 24962000 | CK12: 21912000 | CL12: 21514000 | CM12: 7743000 | CN12: 6936000 | CO12: 6682000 | CP12: 5995000 | CT12: 2523000 | CX12: 5743000 | DB12: 3689000 | DF12: 11989000 | DJ12: 11785000
A13: CurrentDeferredTaxesAssets | BD13: 0 | BE13: 0 | BF13: 0 | BG13: 0 | BH13: 4600000 | BI13: 0 | BJ13: 17395000 | BK13: 15247000 | BL13: 17297000 | BM13: 37860000 | BN13: 24321000 | BO13: 49627000 | BP13: 1002000 | BQ13: 2367000 | BR13: 11912000 | BS13: 14348000 | BT13: 33708000 | BU13: 21525000 | BV13: 24908000 | BW13: 17305000 | BX13: 10997000 | BY13: 21852000 | BZ13: 30413000 | CA13: 21729000 | CB13: 22829000 | CC13: 26664000 | CD13: 33860000 | CE13: 43095000 | CF13: 25552000 | CG13: 80974000 | CH13: 105091000 | CI13: 90307000 | CJ13: 24962000 | CK13: 21912000 | CL13: 21514000 | CM13: 7743000 | CN13: 6936000 | CO13: 6682000 | CP13: 5995000 | CT13: 2523000 | CX13: 5743000 | DB13: 3689000 | DF13: 11989000 | DJ13: 11785000
A14: OtherCurrentAssets | B14: 377772000 | C14: 355688000 | D14: 302925000 | E14: 321481000 | F14: 327490000 | G14: 280282000 | H14: 247295000 | I14: 273939000 | J14: 272768000 | K14: 237588000 | L14: 199405000 | M14: 197040000 | N14: 210471000 | O14: 194049000 | P14: 184163000 | Q14: 192901000 | R14: 178250000 | S14: 177735000 | T14: 272725000 | U14: 275904000 | V14: 287753000 | W14: 258900000 | X14: 263121000 | Y14: 230269000 | Z14: 258559000 | AA14: 232398000 | AB14: 220021000 | AC14: 225443000 | AD14: 229348000 | AE14: 210769000 | AF14: 193467000 | AG14: 192476000 | AH14: 199945000 | AI14: 180586000 | AJ14: 170265000 | AK14: 173981000 | AL14: 175048000 | AM14: 171660000 | AN14: 147048000 | AO14: 137247000 | AP14: 153863000 | AQ14: 154539000 | AR14: 139129000 | BW14: 100523000 | BX14: 94637000 | BY14: 73738000 | BZ14: 66383000 | CA14: 65301000 | CB14: 57494000 | CC14: 52080000 | CD14: 45699000 | CE14: 61077000 | CF14: 65263000 | CG14: 85419000 | CH14: 58408000 | CI14: 48600000 | CJ14: 53231000 | CK14: 37896000 | CL14: 44868000 | CM14: 62956000 | CN14: 81205000 | CO14: 106471000 | CP14: 45036000 | CQ14: 72500000 | CR14: 52400000 | CS14: 34300000 | CT14: 42378000 | CU14: 40800000 | CV14: 43700000 | CW14: 26700000 | CX14: 21884000 | CY14: 25400000 | CZ14: 23800000 | DA14: 22400000 | DB14: 18244000 | DC14: 28300000 | DD14: 25500000 | DE14: 25000000 | DF14: 11548000 | DG14: 24500000 | DH14: 25000000 | DI14: 25800000 | DJ14: 9212000 | DK14: 24100000 | DL14: 23700000 | DM14: 19100000 | DN14: 19600000 | DO14: 21300000 | DP14: 18800000 | DQ14: 15400000 | DR14: 13900000 | DS14: 13900000 | DT14: 13300000 | DU14: 13600000 | DV14: 11700000 | DW14: 11600000 | DX14: 12500000 | DY14: 10600000 | DZ14: 9500000 | EA14: 8600000 | EB14: 8100000 | EC14: 9200000 | ED14: 8300000 | EE14: 7300000 | EF14: 7000000 | EG14: 5900000 | EH14: 6000000 | EI14: 5100000 | EJ14: 4400000
A15: TotalNonCurrentAssets | B15: 21981578000 | C15: 21748473000 | D15: 21502358000 | E15: 20990142000 | F15: 20556364000 | G15: 20219438000 | H15: 20023528000 | I15: 19743468000 | J15: 19495090000 | K15: 19194953000 | L15: 18948405000 | M15: 18620010000 | N15: 18250025000 | O15: 17855830000 | P15: 17647216000 | Q15: 17344248000 | R15: 16998391000 | S15: 16720515000 | T15: 8541018000 | U15: 8490677000 | V15: 8426123000 | W15: 8327194000 | X15: 8269059000 | Y15: 8221422000 | Z15: 8140833000 | AA15: 8047406000 | AB15: 7994527000 | AC15: 7948564000 | AD15: 7909319000 | AE15: 7839038000 | AF15: 7825475000 | AG15: 7799518000 | AH15: 7770348000 | AI15: 7711650000 | AJ15: 7691495000 | AK15: 7698240000 | AL15: 7685163000 | AM15: 7658538000 | AN15: 7661917000 | AO15: 7871672000 | AP15: 7834887000 | AQ15: 7769221000 | AR15: 7690569000 | AS15: 7655485000 | AT15: 7589030000 | AU15: 7496473000 | AV15: 7413446000 | AW15: 7343027000 | AX15: 7256322000 | AY15: 7207967000 | AZ15: 7178397000 | BA15: 7076816000 | BB15: 7044790000 | BC15: 7038498000 | BD15: 7018070000 | BE15: 7015218000 | BF15: 6994165000 | BG15: 7016653000 | BH15: 7019074000 | BI15: 7053804000 | BJ15: 7056989000 | BK15: 7067859000 | BL15: 7138687000 | BM15: 1288152000 | BN15: 1297766000 | BO15: 1288312000 | BP15: 1291317000 | BQ15: 1254712000 | BR15: 1229262000 | BS15: 1186131000 | BT15: 1141703000 | BU15: 1121343000 | BV15: 1110102000 | BW15: 1105783000 | BX15: 1068363000 | BY15: 1044111000 | BZ15: 1000494000 | CA15: 990494000 | CB15: 998073000 | CC15: 1000576000 | CD15: 1009245000 | CE15: 1020771000 | CF15: 1021124000 | CG15: 1000466000 | CH15: 996338000 | CI15: 1122325000 | CJ15: 1189645000 | CK15: 1175358000 | CL15: 1157535000 | CM15: 510902000 | CN15: 462606000 | CO15: 381225000 | CP15: 355406000 | CQ15: 335400000 | CR15: 313300000 | CS15: 326300000 | CT15: 332867000 | CU15: 295600000 | CV15: 277000000 | CW15: 259900000 | CX15: 248129000 | CY15: 243700000 | CZ15: 226200000 | DA15: 199200000 | DB15: 213548000 | DC15: 184500000 | DD15: 167700000 | DE15: 162100000 | DF15: 163753000 | DG15: 159500000 | DH15: 145400000 | DI15: 135100000 | DJ15: 130715000 | DK15: 112600000 | DL15: 97900000 | DM15: 86200000 | DN15: 82200000 | DO15: 77300000 | DP15: 71100000 | DQ15: 64300000 | DR15: 60700000 | DS15: 56200000 | DT15: 51300000 | DU15: 47900000 | DV15: 44900000 | DW15: 42600000 | DX15: 41100000 | DY15: 40000000 | DZ15: 39500000 | EA15: 40200000 | EB15: 39100000 | EC15: 38800000 | ED15: 38600000 | EE15: 37500000 | EF15: 33400000 | EG15: 27700000 | EH15: 34500000 | EI15: 38200000 | EJ15: 38200000
A16: NetPPE | B16: 16379301000 | C16: 16146657000 | D16: 15906323000 | E16: 15396824000 | F16: 14967412000 | G16: 14634180000 | H16: 14439057000 | I16: 14160537000 | J16: 13909274000 | K16: 13614144000 | L16: 13373327000 | M16: 13045157000 | N16: 12675787000 | O16: 12280946000 | P16: 12074542000 | Q16: 11770451000 | R16: 11425752000 | S16: 11148751000 | T16: 2970806000 | U16: 2921943000 | V16: 2857274000 | W16: 2758369000 | X16: 2701282000 | Y16: 2654936000 | Z16: 2574816000 | AA16: 2487292000 | AB16: 2434456000 | AC16: 2388463000 | AD16: 2349119000 | AE16: 2278081000 | AF16: 2264062000 | AG16: 2237068000 | AH16: 2195857000 | AI16: 2135436000 | AJ16: 2116075000 | AK16: 2120572000 | AL16: 2106963000 | AM16: 2079832000 | AN16: 2080305000 | AO16: 2287410000 | AP16: 2244651000 | AQ16: 2177264000 | AR16: 2088665000 | AS16: 2047434000 | AT16: 1972205000 | AU16: 1878172000 | AV16: 1794960000 | AW16: 1716797000 | AX16: 1622991000 | AY16: 1562596000 | AZ16: 1524575000 | BA16: 1414700000 | BB16: 1377630000 | BC16: 1360868000 | BD16: 1328386000 | BE16: 1305858000 | BF16: 1273452000 | BG16: 1280835000 | BH16: 1268960000 | BI16: 1288848000 | BJ16: 1266722000 | BK16: 1250570000 | BL16: 1274245000 | BM16: 1212198000 | BN16: 1236874000 | BO16: 1246890000 | BP16: 1241219000 | BQ16: 1212386000 | BR16: 1192172000 | BS16: 1155281000 | BT16: 1121697000 | BU16: 1091997000 | BV16: 1080838000 | BW16: 1076627000 | BX16: 1039046000 | BY16: 1017647000 | BZ16: 989224000 | CA16: 979487000 | CB16: 986463000 | CC16: 988111000 | CD16: 993822000 | CE16: 1000265000 | CF16: 999273000 | CG16: 991477000 | CH16: 988915000 | CI16: 997790000 | CJ16: 1003224000 | CK16: 991039000 | CL16: 973094000 | CM16: 494943000 | CN16: 449670000 | CO16: 372200000 | CP16: 346473000 | CQ16: 324900000 | CR16: 303600000 | CS16: 316600000 | CT16: 326408000 | CU16: 289000000 | CV16: 270500000 | CW16: 253300000 | CX16: 241445000 | CY16: 238100000 | CZ16: 220900000 | DA16: 193800000 | DB16: 208536000 | DC16: 179400000 | DD16: 162600000 | DE16: 157000000 | DF16: 158587000 | DG16: 154000000 | DH16: 139700000 | DI16: 129600000 | DJ16: 125252000 | DK16: 107800000 | DL16: 93200000 | DM16: 81600000 | DN16: 77500000 | DO16: 71900000 | DP16: 66400000 | DQ16: 58500000 | DR16: 56100000 | DS16: 51700000 | DT16: 46800000 | DU16: 43400000 | DV16: 40400000 | DW16: 38000000 | DX16: 36300000 | DY16: 35200000 | DZ16: 34700000 | EA16: 34600000 | EB16: 33500000 | EC16: 33200000 | ED16: 32900000 | EE16: 32400000 | EF16: 28200000 | EG16: 22600000 | EH16: 25400000 | EI16: 29100000 | EJ16: 23500000
A17: GrossPPE | B17: 16379301000 | C17: 16146657000 | D17: 15906323000 | E17: 15396824000 | F17: 14967412000 | G17: 14634180000 | H17: 14439057000 | I17: 14160537000 | J17: 13909274000 | K17: 13614144000 | L17: 13373327000 | M17: 13045157000 | N17: 12675787000 | O17: 12280946000 | P17: 12074542000 | Q17: 11770451000 | R17: 11425752000 | S17: 11148751000 | T17: 5518977000 | X17: 5175292000 | AB17: 4595002000 | AF17: 4170486000 | AJ17: 3753557000 | AN17: 3452916000 | AR17: 3226898000 | AV17: 2680985000 | AZ17: 2177269000 | BD17: 1792373000 | BH17: 1561008000 | BW17: 1905578000 | BX17: 1833447000 | BY17: 1775496000 | CA17: 1667438000 | CB17: 1639164000 | CC17: 1606447000 | CE17: 1581427000 | CF17: 1547346000 | CG17: 1507414000 | CH17: 1473693000 | CI17: 1454268000 | CJ17: 1429373000 | CK17: 1386885000 | CL17: 1339554000 | CM17: 801837000 | CN17: 736444000 | CO17: 641158000 | CP17: 597537000 | CQ17: 560300000 | CR17: 523600000 | CS17: 533000000 | CT17: 528238000 | CU17: 477200000 | CV17: 445400000 | CW17: 416000000 | CX17: 391911000 | CY17: 378500000 | CZ17: 351800000 | DA17: 315700000 | DB17: 321917000 | DC17: 285100000 | DD17: 260700000 | DE17: 247800000 | DF17: 242628000 | DG17: 231500000 | DH17: 212300000 | DI17: 196700000 | DJ17: 187360000 | DK17: 165300000 | DL17: 147800000 | DM17: 132500000 | DN17: 124800000 | DO17: 116000000 | DP17: 108300000 | DQ17: 98300000 | DR17: 93500000 | DS17: 92400000 | DT17: 86300000 | DU17: 81000000 | DV17: 76600000 | DW17: 74100000 | DX17: 72800000 | DY17: 70100000 | DZ17: 68100000 | EA17: 69900000 | EB17: 67200000 | EC17: 65300000 | ED17: 63500000 | EE17: 65800000 | EF17: 60100000 | EG17: 52000000 | EH17: 49900000 | EI17: 49400000 | EJ17: 38600000
A18: Properties | D18: 0 | H18: 0 | L18: 0 | P18: 0 | T18: 0 | X18: 0 | AB18: 0 | AF18: 0 | AJ18: 0 | AN18: 0 | AR18: 0 | AV18: 0 | AZ18: 0 | BD18: 0 | BH18: 0 | CH18: 0 | CL18: 0
A19: LandAndImprovements | D19: 329381000 | H19: 323487000 | L19: 317797000 | P19: 306864000 | T19: 299725000 | X19: 291630000 | AB19: 273380000 | AF19: 255487000 | AJ19: 227704000 | AN19: 212014000 | AR19: 257695000 | AV19: 204562000 | AZ19: 174439000 | BD19: 137903000 | BH19: 137779000 | CH19: 144490000 | CL19: 119410000
A20: BuildingsAndImprovements | D20: 1561440000 | H20: 1446126000 | L20: 1329309000 | P20: 1290673000 | T20: 1219852000 | X20: 1116872000 | AB20: 1013227000 | AF20: 834884000 | AJ20: 800346000 | AN20: 765555000 | AR20: 773835000 | AV20: 622849000 | AZ20: 575305000 | BD20: 520867000 | BH20: 518933000 | CH20: 331795000 | CL20: 286476000
A21: MachineryFurnitureEquipment | D21: 5714456000 | H21: 4984534000 | L21: 4487665000 | P21: 3782016000 | T21: 3298594000 | X21: 3186406000 | AB21: 2797144000 | AF21: 2526843000 | AJ21: 2295590000 | AN21: 2078893000 | AR21: 1828573000 | AV21: 1500268000 | AZ21: 1235756000 | BD21: 992423000 | BH21: 781425000 | CH21: 988074000 | CL21: 823234000
A22: OtherProperties | B22: 16379301000 | C22: 16146657000 | D22: 15906323000 | E22: 15396824000 | F22: 14967412000 | G22: 14634180000 | H22: 14439057000 | I22: 14160537000 | J22: 13909274000 | K22: 13614144000 | L22: 13373327000 | M22: 13045157000 | N22: 12675787000 | O22: 12280946000 | P22: 12074542000 | Q22: 11770451000 | R22: 11425752000 | S22: 11148751000
A23: ConstructionInProgress | D23: 313615000 | H23: 131073000 | L23: 183593000 | P23: 62183000 | T23: 117275000 | X23: 72490000 | AB23: 72540000 | AF23: 150275000 | AJ23: 68360000 | AN23: 70332000 | AR23: 87444000 | AV23: 139454000 | AZ23: 17933000 | BD23: 10406000 | BH23: 5025000 | CH23: 9334000 | CL23: 110434000
A24: Leases | D24: 1011788000 | H24: 889782000 | L24: 782858000 | P24: 656234000 | T24: 583531000 | X24: 507894000 | AB24: 438711000 | AF24: 402997000 | AJ24: 361557000 | AN24: 326122000 | AR24: 279351000 | AV24: 213852000 | AZ24: 173836000 | BD24: 130774000 | BH24: 117846000
A25: AccumulatedDepreciation | D25: -3909423000 | H25: -3591647000 | L25: -3364333000 | P25: -2819611000 | T25: -2548171000 | X25: -2474010000 | AB25: -2160546000 | AF25: -1906424000 | AJ25: -1637482000 | AN25: -1372611000 | AR25: -1138233000 | AV25: -886025000 | AZ25: -652694000 | BD25: -463987000 | BH25: -292048000 | BW25: -828951000 | BX25: -794401000 | BY25: -757849000 | CA25: -687951000 | CB25: -652701000 | CC25: -618336000 | CE25: -581162000 | CF25: -548073000 | CG25: -515937000 | CH25: -484778000 | CI25: -456478000 | CJ25: -426149000 | CK25: -395846000 | CL25: -366460000 | CM25: -306894000 | CN25: -286774000 | CO25: -268958000 | CP25: -251064000 | CQ25: -235400000 | CR25: -220000000 | CS25: -216400000 | CT25: -201830000 | CU25: -188200000 | CV25: -174900000 | CW25: -162700000 | CX25: -150466000 | CY25: -140400000 | CZ25: -130900000 | DA25: -121900000 | DB25: -113381000 | DC25: -105700000 | DD25: -98100000 | DE25: -90800000 | DF25: -84041000 | DG25: -77500000 | DH25: -72600000 | DI25: -67100000 | DJ25: -62108000 | DK25: -57500000 | DL25: -54600000 | DM25: -50900000 | DN25: -47300000 | DO25: -44100000 | DP25: -41900000 | DQ25: -39800000 | DR25: -37400000 | DS25: -40700000 | DT25: -39500000 | DU25: -37600000 | DV25: -36200000 | DW25: -36100000 | DX25: -36500000 | DY25: -34900000 | DZ25: -33400000 | EA25: -35300000 | EB25: -33700000 | EC25: -32100000 | ED25: -30600000 | EE25: -33400000 | EF25: -31900000 | EG25: -29400000 | EH25: -24500000 | EI25: -20300000 | EJ25: -15100000
A26: GoodwillAndOtherIntangibleAssets | B26: 5538289000 | C26: 5538289000 | D26: 5538289000 | E26: 5538289000 | F26: 5538289000 | G26: 5538309000 | H26: 5538339000 | I26: 5538369000 | J26: 5538399000 | K26: 5538429000 | L26: 5538459000 | M26: 5538489000 | N26: 5538520000 | O26: 5538550000 | P26: 5538595000 | Q26: 5538648000 | R26: 5538700000 | S26: 5538753000 | T26: 5538806000 | U26: 5538859000 | V26: 5538911000 | W26: 5538964000 | X26: 5539017000 | Y26: 5539070000 | Z26: 5539126000 | AA26: 5539186000 | AB26: 5539248000 | AC26: 5539323000 | AD26: 5539405000 | AE26: 5539493000 | AF26: 5539583000 | AG26: 5539699000 | AH26: 5539830000 | AI26: 5540017000 | AJ26: 5540459000 | AK26: 5541240000 | AL26: 5542493000 | AM26: 5544187000 | AN26: 5546234000 | AO26: 5548666000 | AP26: 5551410000 | AQ26: 5554588000 | AR26: 5558132000 | AS26: 5561996000 | AT26: 5566088000 | AU26: 5570455000 | AV26: 5574543000 | AW26: 5579322000 | AX26: 5584362000 | AY26: 5589878000 | AZ26: 5595511000 | BA26: 5601423000 | BB26: 5607579000 | BC26: 5614762000 | BD26: 5622872000 | BE26: 5631869000 | BF26: 5641785000 | BG26: 5653014000 | BH26: 5664147000 | BI26: 5673926000 | BJ26: 5692878000 | BK26: 5704020000 | BL26: 5715487000
A27: Goodwill | B27: 4338589000 | C27: 4338589000 | D27: 4338589000 | E27: 4338589000 | F27: 4338589000 | G27: 4338589000 | H27: 4338589000 | I27: 4338589000 | J27: 4338589000 | K27: 4338589000 | L27: 4338589000 | M27: 4338589000 | N27: 4338589000 | O27: 4338589000 | P27: 4338589000 | Q27: 4338589000 | R27: 4338589000 | S27: 4338589000 | T27: 4338589000 | U27: 4338589000 | V27: 4338589000 | W27: 4338589000 | X27: 4338589000 | Y27: 4338589000 | Z27: 4338589000 | AA27: 4338589000 | AB27: 4338589000 | AC27: 4338589000 | AD27: 4338589000 | AE27: 4338589000 | AF27: 4338589000 | AG27: 4338589000 | AH27: 4338589000 | AI27: 4338589000 | AJ27: 4338589000 | AK27: 4338589000 | AL27: 4338589000 | AM27: 4338589000 | AN27: 4338589000 | AO27: 4338589000 | AP27: 4338589000 | AQ27: 4338589000 | AR27: 4338589000 | AS27: 4338589000 | AT27: 4338589000 | AU27: 4338589000 | AV27: 4338589000 | AW27: 4338589000 | AX27: 4338589000 | AY27: 4338589000 | AZ27: 4338589000 | BA27: 4338589000 | BB27: 4338589000 | BC27: 4338589000 | BD27: 4338589000 | BE27: 4338589000 | BF27: 4338589000 | BG27: 4338589000 | BH27: 4338589000 | BI27: 4337152000 | BJ27: 4344930000 | BK27: 4344930000 | BL27: 4344930000
A28: OtherIntangibleAssets | B28: 1199700000 | C28: 1199700000 | D28: 1199700000 | E28: 1199700000 | F28: 1199700000 | G28: 1199720000 | H28: 1199750000 | I28: 1199780000 | J28: 1199810000 | K28: 1199840000 | L28: 1199870000 | M28: 1199900000 | N28: 1199931000 | O28: 1199961000 | P28: 1200006000 | Q28: 1200059000 | R28: 1200111000 | S28: 1200164000 | T28: 1200217000 | U28: 1200270000 | V28: 1200322000 | W28: 1200375000 | X28: 1200428000 | Y28: 1200481000 | Z28: 1200537000 | AA28: 1200597000 | AB28: 1200659000 | AC28: 1200734000 | AD28: 1200816000 | AE28: 1200904000 | AF28: 1200994000 | AG28: 1201110000 | AH28: 1201241000 | AI28: 1201428000 | AJ28: 1201870000 | AK28: 1202651000 | AL28: 1203904000 | AM28: 1205598000 | AN28: 1207645000 | AO28: 1210077000 | AP28: 1212821000 | AQ28: 1215999000 | AR28: 1219543000 | AS28: 1223407000 | AT28: 1227499000 | AU28: 1231866000 | AV28: 1235954000 | AW28: 1240733000 | AX28: 1245773000 | AY28: 1251289000 | AZ28: 1256922000 | BA28: 1262834000 | BB28: 1268990000 | BC28: 1276173000 | BD28: 1284283000 | BE28: 1293280000 | BF28: 1303196000 | BG28: 1314425000 | BH28: 1325558000 | BI28: 1336774000 | BJ28: 1347948000 | BK28: 1359090000 | BL28: 1370557000
A29: NonCurrentDeferredAssets | BM29: 12418000 | CH29: 0 | CL29: 52708000
A30: NonCurrentDeferredTaxesAssets | BM30: 12418000 | CH30: 0 | CL30: 52708000
A31: OtherNonCurrentAssets | B31: 63988000 | C31: 63527000 | D31: 57746000 | E31: 55029000 | F31: 50663000 | G31: 46949000 | H31: 46132000 | I31: 44562000 | J31: 47417000 | K31: 42380000 | L31: 36619000 | M31: 36364000 | N31: 35718000 | O31: 36334000 | P31: 34079000 | Q31: 35149000 | R31: 33939000 | S31: 33011000 | T31: 31406000 | U31: 29875000 | V31: 29938000 | W31: 29861000 | X31: 28760000 | Y31: 27416000 | Z31: 26891000 | AA31: 20928000 | AB31: 20823000 | AC31: 20778000 | AD31: 20795000 | AE31: 21464000 | AF31: 21830000 | AG31: 22751000 | AH31: 34661000 | AI31: 36197000 | AJ31: 34961000 | AK31: 36428000 | AL31: 35707000 | AM31: 34519000 | AN31: 35378000 | AO31: 35596000 | AP31: 38826000 | AQ31: 37369000 | AR31: 43772000 | AS31: 46055000 | AT31: 50737000 | AU31: 47846000 | AV31: 43943000 | AW31: 46908000 | AX31: 48969000 | AY31: 55493000 | AZ31: 58311000 | BA31: 60693000 | BB31: 59581000 | BC31: 62868000 | BD31: 66812000 | BE31: 77491000 | BF31: 78928000 | BG31: 82804000 | BH31: 85967000 | BI31: 91030000 | BJ31: 97389000 | BK31: 113269000 | BL31: 148955000 | BM31: 63536000 | BN31: 60892000 | BO31: 41422000 | BP31: 50098000 | BQ31: 42326000 | BR31: 37090000 | BS31: 30850000 | BT31: 20006000 | BU31: 29346000 | BV31: 29264000 | BW31: 29156000 | BX31: 29317000 | BY31: 26464000 | BZ31: 11270000 | CA31: 11007000 | CB31: 11610000 | CC31: 12465000 | CD31: 15423000 | CE31: 20506000 | CF31: 21851000 | CG31: 8989000 | CH31: 7423000 | CI31: 124535000 | CJ31: 186421000 | CK31: 184319000 | CL31: 131733000 | CM31: 15959000 | CN31: 12936000 | CO31: 9025000 | CP31: 8933000 | CT31: 6459000 | CX31: 6684000 | DB31: 5012000 | DF31: 5166000 | DJ31: 5463000
A32: TotalLiabilitiesNetMinorityInterest | B32: 24097852000 | C32: 23868682000 | D32: 23541595000 | E32: 22913352000 | F32: 22050765000 | G32: 20994684000 | H32: 20065385000 | I32: 19735501000 | J32: 19350673000 | K32: 18986773000 | L32: 19201386000 | M32: 19167923000 | N32: 18491362000 | O32: 17638859000 | P32: 16122584000 | Q32: 15764495000 | R32: 15168369000 | S32: 14731615000 | T32: 6786645000 | U32: 6765133000 | V32: 6565007000 | W32: 6256912000 | X32: 6391137000 | Y32: 6630601000 | Z32: 6433729000 | AA32: 6267474000 | AB32: 6266004000 | AC32: 6555224000 | AD32: 6204009000 | AE32: 5928001000 | AF32: 5880009000 | AG32: 5944700000 | AH32: 5776261000 | AI32: 5570692000 | AJ32: 5514066000 | AK32: 5533735000 | AL32: 5729801000 | AM32: 5769657000 | AN32: 5465331000 | AO32: 5501020000 | AP32: 5468154000 | AQ32: 5314798000 | AR32: 5382352000 | AS32: 5538815000 | AT32: 5293064000 | AU32: 5178776000 | AV32: 5020025000 | AW32: 5181870000 | AX32: 5155539000 | AY32: 5495208000 | AZ32: 5491743000 | BA32: 5532184000 | BB32: 5496630000 | BC32: 5440550000 | BD32: 5473221000 | BE32: 6277118000 | BF32: 6123406000 | BG32: 6062216000 | BH32: 6057504000 | BI32: 6176637000 | BJ32: 6142987000 | BK32: 5932392000 | BL32: 5952558000 | BM32: 1277532000 | BN32: 1294767000 | BO32: 1503362000 | BP32: 1523720000 | BQ32: 1376653000 | BR32: 1271392000 | BS32: 1316494000 | BT32: 1192549000 | BU32: 1176572000 | BV32: 1156539000 | BW32: 1250527000 | BX32: 1116129000 | BY32: 1185686000 | BZ32: 1075789000 | CA32: 1087534000 | CB32: 963236000 | CC32: 1018220000 | CD32: 1045085000 | CE32: 1220813000 | CF32: 1133875000 | CG32: 1500072000 | CH32: 1510667000 | CI32: 1516106000 | CJ32: 1414294000 | CK32: 1405974000 | CL32: 1420699000 | CM32: 762620000 | CN32: 680603000 | CO32: 610764000 | CP32: 525020000 | CQ32: 687000000 | CR32: 504900000 | CS32: 537900000 | CT32: 486023000 | CU32: 647000000 | CV32: 507400000 | CW32: 419800000 | CX32: 330942000 | CY32: 502700000 | CZ32: 305100000 | DA32: 276600000 | DB32: 232618000 | DC32: 410600000 | DD32: 270300000 | DE32: 297200000 | DF32: 259985000 | DG32: 385900000 | DH32: 283100000 | DI32: 287400000 | DJ32: 217112000 | DK32: 268500000 | DL32: 211500000 | DM32: 183300000 | DN32: 156500000 | DO32: 235000000 | DP32: 169700000 | DQ32: 179400000 | DR32: 126600000 | DS32: 188600000 | DT32: 137600000 | DU32: 139100000 | DV32: 86300000 | DW32: 158900000 | DX32: 125600000 | DY32: 112200000 | DZ32: 76000000 | EA32: 146300000 | EB32: 123700000 | EC32: 128700000 | ED32: 73200000 | EE32: 135600000 | EF32: 117600000 | EG32: 98700000 | EH32: 115400000 | EI32: 123600000 | EJ32: 119600000
A33: CurrentLiabilities | B33: 6033922000 | C33: 6100679000 | D33: 5887768000 | E33: 6502647000 | F33: 7566786000 | G33: 6951841000 | H33: 5979357000 | I33: 5740499000 | J33: 5479084000 | K33: 5315398000 | L33: 5710783000 | M33: 5886211000 | N33: 5411188000 | O33: 4843228000 | P33: 4543560000 | Q33: 4506038000 | R33: 4312270000 | S33: 3956716000 | T33: 3015857000 | U33: 2982182000 | V33: 2915544000 | W33: 2525332000 | X33: 2964878000 | Y33: 2937806000 | Z33: 2806755000 | AA33: 2692041000 | AB33: 2622805000 | AC33: 2959739000 | AD33: 2719406000 | AE33: 2011594000 | AF33: 1995596000 | AG33: 1991583000 | AH33: 2154763000 | AI33: 2072939000 | AJ33: 1987740000 | AK33: 2010846000 | AL33: 1969418000 | AM33: 1863318000 | AN33: 1811971000 | AO33: 1753049000 | AP33: 1740190000 | AQ33: 1600402000 | AR33: 1738547000 | AS33: 1633839000 | AT33: 1526683000 | AU33: 1411253000 | AV33: 1509902000 | AW33: 1572221000 | AX33: 1526951000 | AY33: 1387230000 | AZ33: 1365373000 | BA33: 1410315000 | BB33: 1319160000 | BC33: 1206040000 | BD33: 1206500000 | BE33: 1310933000 | BF33: 1165825000 | BG33: 1092662000 | BH33: 1075235000 | BI33: 1192657000 | BJ33: 1164717000 | BK33: 954740000 | BL33: 858241000 | BM33: 750273000 | BN33: 832871000 | BO33: 948503000 | BP33: 944652000 | BQ33: 979492000 | BR33: 933797000 | BS33: 909940000 | BT33: 869368000 | BU33: 847778000 | BV33: 825692000 | BW33: 848659000 | BX33: 780869000 | BY33: 853417000 | BZ33: 743802000 | CA33: 760077000 | CB33: 633883000 | CC33: 640608000 | CD33: 664501000 | CE33: 673275000 | CF33: 581138000 | CG33: 1110601000 | CH33: 1133551000 | CI33: 1168932000 | CJ33: 516859000 | CK33: 510448000 | CL33: 537935000 | CM33: 500896000 | CN33: 423561000 | CO33: 553079000 | CP33: 472297000 | CQ33: 673500000 | CR33: 485300000 | CS33: 512700000 | CT33: 455134000 | CU33: 634500000 | CV33: 485500000 | CW33: 397800000 | CX33: 307711000 | CY33: 495900000 | CZ33: 298200000 | DA33: 267000000 | DB33: 224465000 | DC33: 404300000 | DD33: 264600000 | DE33: 291400000 | DF33: 253714000 | DG33: 379200000 | DH33: 276100000 | DI33: 280200000 | DJ33: 208963000 | DK33: 261400000 | DL33: 204200000 | DM33: 175900000 | DN33: 148200000 | DO33: 226600000 | DP33: 161200000 | DQ33: 170700000 | DR33: 117000000 | DS33: 178700000 | DT33: 97500000 | DU33: 112900000 | DV33: 62400000 | DW33: 111500000 | DX33: 85600000 | DY33: 86300000 | DZ33: 55100000 | EA33: 84700000 | EB33: 64800000 | EC33: 80700000 | ED33: 45100000 | EE33: 73600000 | EF33: 54500000 | EG33: 52400000 | EH33: 61400000 | EI33: 65200000 | EJ33: 50200000
A34: PayablesAndAccruedExpenses | B34: 4702489000 | C34: 4538926000 | D34: 4598829000 | E34: 5245587000 | F34: 5435087000 | G34: 4846163000 | H34: 4795798000 | I34: 4583254000 | J34: 4351243000 | K34: 4214029000 | L34: 4636704000 | M34: 4841843000 | N34: 4395455000 | O34: 3851594000 | P34: 3578200000 | Q34: 3564979000 | R34: 3396640000 | S34: 3061692000 | T34: 3013907000 | U34: 2980253000 | V34: 2913635000 | W34: 2523443000 | X34: 2563533000 | Y34: 2536274000 | Z34: 2405353000 | AA34: 2290853000 | AB34: 2121855000 | AC34: 2458259000 | AD34: 2217858000 | AE34: 2010068000 | AF34: 1994217000 | AG34: 1974097000 | AH34: 2021122000 | AI34: 1937822000 | AJ34: 1861314000 | AK34: 1870947000 | AL34: 1846971000 | AM34: 1738784000 | AN34: 1714210000 | AO34: 1666914000 | AP34: 1685690000 | AQ34: 1567973000 | AR34: 1637451000 | AS34: 1593163000 | AT34: 1510793000 | AU34: 1396628000 | AV34: 1428601000 | AW34: 1548632000 | AX34: 1490382000 | AY34: 1346349000 | AZ34: 1327362000 | BA34: 1364356000 | BB34: 1278278000 | BC34: 1156211000 | BD34: 1177768000 | BE34: 1237993000 | BF34: 1123996000 | BG34: 1061194000 | BH34: 1061077000 | BI34: 1161533000 | BJ34: 1161718000 | BK34: 951910000 | BL34: 854995000 | BM34: 743087000 | BN34: 824791000 | BO34: 940030000 | BP34: 935485000 | BQ34: 970692000 | BR34: 925012000 | BS34: 901076000 | BT34: 859807000 | BU34: 837041000 | BV34: 812832000 | BW34: 833955000 | BX34: 764913000 | BY34: 836537000 | BZ34: 727132000 | CA34: 742782000 | CB34: 616926000 | CC34: 624048000 | CD34: 648292000 | CE34: 657441000 | CF34: 566006000 | CG34: 714724000 | CH34: 737876000 | CI34: 777843000 | CJ34: 508917000 | CK34: 503365000 | CL34: 528900000 | CM34: 435905000 | CN34: 399235000 | CO34: 370125000 | CP34: 471064000 | CQ34: 347600000 | CR34: 209900000 | CS34: 246700000 | CT34: 454409000 | CU34: 280800000 | CV34: 214500000 | CW34: 179100000 | CX34: 284328000 | CY34: 210800000 | CZ34: 163100000 | DA34: 152700000 | DB34: 183966000 | DC34: 144700000 | DD34: 121200000 | DE34: 120400000 | DF34: 180032000 | DG34: 111900000 | DH34: 93600000 | DI34: 122700000 | DJ34: 177922000 | DK34: 88800000 | DL34: 91500000 | DM34: 101100000 | DN34: 81000000 | DO34: 112000000 | DP34: 83300000 | DQ34: 101300000 | DR34: 64000000 | DS34: 85400000 | DT34: 65700000 | DU34: 86300000 | DV34: 37800000 | DW34: 79300000 | DX34: 63500000 | DY34: 67300000 | DZ34: 31500000 | EA34: 56500000 | EB34: 40500000 | EC34: 57900000 | ED34: 22100000 | EE34: 51300000 | EF34: 37000000
A35: Payables | B35: 3688895000 | C35: 3690169000 | D35: 3561910000 | E35: 4135082000 | F35: 4365161000 | G35: 3915903000 | H35: 3746659000 | I35: 3544032000 | J35: 3378218000 | K35: 3352376000 | L35: 3630152000 | M35: 3781241000 | N35: 3416888000 | O35: 3060226000 | P35: 2869044000 | Q35: 2847512000 | R35: 2730389000 | S35: 2501685000 | T35: 2395502000 | U35: 2341609000 | V35: 2302246000 | W35: 2028072000 | X35: 2013875000 | Y35: 1982678000 | Z35: 1884326000 | AA35: 1831748000 | AB35: 1620989000 | AC35: 1953832000 | AD35: 1743432000 | AE35: 1569371000 | AF35: 1527095000 | AG35: 1500569000 | AH35: 1577958000 | AI35: 1544315000 | AJ35: 1447554000 | AK35: 1428088000 | AL35: 1419702000 | AM35: 1343957000 | AN35: 1345632000 | AO35: 1252033000 | AP35: 1272836000 | AQ35: 1208935000 | AR35: 1446323000 | AS35: 1200724000 | AT35: 1144522000 | AU35: 1036279000 | AV35: 1216468000 | AW35: 1133655000 | AX35: 1123759000 | AY35: 965927000 | AZ35: 979621000 | BA35: 985606000 | BB35: 956606000 | BC35: 823960000 | BD35: 835478000 | BE35: 856647000 | BF35: 819612000 | BG35: 728472000 | BH35: 686032000 | BI35: 721950000 | BJ35: 819990000 | BK35: 594995000 | BL35: 554039000 | BM35: 484997000 | BN35: 571233000 | BO35: 533269000 | BP35: 547616000 | BQ35: 591474000 | BR35: 552092000 | BS35: 528539000 | BT35: 512201000 | BU35: 514299000 | BV35: 478943000 | BW35: 497547000 | BX35: 459951000 | BY35: 548509000 | BZ35: 429516000 | CA35: 455058000 | CB35: 361899000 | CC35: 393760000 | CD35: 408394000 | CE35: 410626000 | CF35: 346786000 | CG35: 502134000 | CH35: 495096000 | CI35: 554335000 | CJ35: 294784000 | CK35: 302682000 | CL35: 314708000 | CM35: 313454000 | CN35: 277815000 | CO35: 255471000 | CP35: 349689000 | CQ35: 347600000 | CR35: 209900000 | CS35: 246700000 | CT35: 281584000 | CU35: 280800000 | CV35: 214500000 | CW35: 179100000 | CX35: 192301000 | CY35: 210800000 | CZ35: 163100000 | DA35: 152700000 | DB35: 113525000 | DC35: 144700000 | DD35: 121200000 | DE35: 120400000 | DF35: 117933000 | DG35: 111900000 | DH35: 93600000 | DI35: 122700000 | DJ35: 116885000 | DK35: 88800000 | DL35: 91500000 | DM35: 101100000 | DN35: 81000000 | DO35: 112000000 | DP35: 83300000 | DQ35: 101300000 | DR35: 64000000 | DS35: 85400000 | DT35: 65700000 | DU35: 86300000 | DV35: 37800000 | DW35: 79300000 | DX35: 63500000 | DY35: 67300000 | DZ35: 31500000 | EA35: 56500000 | EB35: 40500000 | EC35: 57900000 | ED35: 22100000 | EE35: 51300000 | EF35: 37000000
A36: AccountsPayable | B36: 3681634000 | C36: 3679170000 | D36: 3552991000 | E36: 4127076000 | F36: 4358388000 | G36: 3906852000 | H36: 3738604000 | I36: 3532639000 | J36: 3369984000 | K36: 3294423000 | L36: 3614089000 | M36: 3770528000 | N36: 3400642000 | O36: 2954361000 | P36: 2860682000 | Q36: 2844171000 | R36: 2727079000 | S36: 2452898000 | T36: 2385469000 | U36: 2336772000 | V36: 2294996000 | W36: 2018320000 | X36: 2009771000 | Y36: 1978032000 | Z36: 1880668000 | AA36: 1622776000 | AB36: 1557596000 | AC36: 1948111000 | AD36: 1720772000 | AE36: 1447223000 | AF36: 1494225000 | AG36: 1470107000 | AH36: 1536610000 | AI36: 1435367000 | AJ36: 1388154000 | AK36: 1394873000 | AL36: 1395780000 | AM36: 1222680000 | AN36: 1286484000 | AO36: 1251394000 | AP36: 1254856000 | AQ36: 1138395000 | AR36: 1261607000 | AS36: 1199727000 | AT36: 1143857000 | AU36: 985924000 | AV36: 1064087000 | AW36: 1132544000 | AX36: 1122949000 | AY36: 933710000 | AZ36: 953641000 | BA36: 971538000 | BB36: 941742000 | BC36: 789274000 | BD36: 830953000 | BE36: 852988000 | BF36: 800308000 | BG36: 700438000 | BH36: 678421000 | BI36: 720126000 | BJ36: 818246000 | BK36: 592071000 | BL36: 551040000 | BM36: 484949000 | BN36: 555274000 | BO36: 517443000 | BP36: 538046000 | BQ36: 569447000 | BR36: 508386000 | BS36: 521087000 | BT36: 462697000 | BU36: 459742000 | BV36: 409327000 | BW36: 475841000 | BX36: 440485000 | BY36: 510187000 | BZ36: 383791000 | CA36: 440505000 | CB36: 352717000 | CC36: 357224000 | CD36: 341303000 | CE36: 410426000 | CF36: 346786000 | CG36: 341134000 | CH36: 322463000 | CI36: 381843000 | CJ36: 294784000 | CK36: 282560000 | CL36: 297262000 | CM36: 309508000 | CN36: 277815000 | CO36: 242361000 | CP36: 334554000 | CQ36: 347600000 | CR36: 209900000 | CS36: 246700000 | CT36: 257759000 | CU36: 280800000 | CV36: 214500000 | CW36: 179100000 | CX36: 179958000 | CY36: 210800000 | CZ36: 163100000 | DA36: 152700000 | DB36: 103523000 | DC36: 144700000 | DD36: 121200000 | DE36: 120400000 | DF36: 103176000 | DG36: 111900000 | DH36: 93600000 | DI36: 122700000 | DJ36: 111675000 | DK36: 88800000 | DL36: 91500000 | DM36: 101100000 | DN36: 81000000 | DO36: 112000000 | DP36: 83300000 | DQ36: 101300000 | DR36: 64000000 | DS36: 85400000 | DT36: 65700000 | DU36: 86300000 | DV36: 37800000 | DW36: 79300000 | DX36: 63500000 | DY36: 67300000 | DZ36: 31500000 | EA36: 56500000 | EB36: 40500000 | EC36: 57900000 | ED36: 22100000 | EE36: 51300000 | EF36: 37000000
A37: TotalTaxPayable | B37: 7261000 | C37: 10999000 | D37: 8919000 | E37: 8006000 | F37: 6773000 | G37: 9051000 | H37: 8055000 | I37: 11393000 | J37: 8234000 | K37: 57953000 | L37: 16063000 | M37: 10713000 | N37: 16246000 | O37: 105865000 | P37: 8362000 | Q37: 3341000 | R37: 3310000 | S37: 48787000 | T37: 10033000 | U37: 4837000 | V37: 7250000 | W37: 9752000 | X37: 4104000 | Y37: 4646000 | Z37: 3658000 | AA37: 208972000 | AB37: 63393000 | AC37: 5721000 | AD37: 22660000 | AE37: 122148000 | AF37: 32870000 | AG37: 30462000 | AH37: 41348000 | AI37: 108948000 | AJ37: 59400000 | AK37: 33215000 | AL37: 23922000 | AM37: 121277000 | AN37: 59148000 | AO37: 639000 | AP37: 17980000 | AQ37: 70540000 | AR37: 184716000 | AS37: 997000 | AT37: 665000 | AU37: 50355000 | AV37: 152381000 | AW37: 1111000 | AX37: 810000 | AY37: 32217000 | AZ37: 25980000 | BA37: 14068000 | BB37: 14864000 | BC37: 34686000 | BD37: 4525000 | BE37: 3659000 | BF37: 19304000 | BG37: 28034000 | BH37: 7611000 | BI37: 1824000 | BJ37: 1744000 | BK37: 2924000 | BL37: 2999000 | BM37: 48000 | BN37: 15959000 | BO37: 15826000 | BP37: 9570000 | BQ37: 22027000 | BR37: 43706000 | BS37: 7452000 | BT37: 49504000 | BU37: 54557000 | BV37: 69616000 | BW37: 21706000 | BX37: 19466000 | BY37: 38322000 | BZ37: 45725000 | CA37: 14553000 | CB37: 9182000 | CC37: 36536000 | CD37: 67091000 | CH37: 10633000 | CI37: 10492000 | CJ37: 0 | CK37: 20122000 | CL37: 17446000 | CM37: 3946000 | CN37: 0 | CO37: 13110000 | CP37: 15135000 | CT37: 23825000 | CX37: 12343000 | DB37: 10002000 | DF37: 14757000 | DJ37: 5210000
A38: IncomeTaxPayable | B38: 7261000 | C38: 10999000 | D38: 8919000 | E38: 8006000 | F38: 6773000 | G38: 9051000 | H38: 8055000 | I38: 11393000 | J38: 8234000 | K38: 57953000 | L38: 16063000 | M38: 10713000 | N38: 16246000 | O38: 105865000 | P38: 8362000 | Q38: 3341000 | R38: 3310000 | S38: 48787000 | T38: 10033000 | U38: 4837000 | V38: 7250000 | W38: 9752000 | X38: 4104000 | Y38: 4646000 | Z38: 3658000 | AA38: 208972000 | AB38: 63393000 | AC38: 5721000 | AD38: 22660000 | AE38: 122148000 | AF38: 32870000 | AG38: 30462000 | AH38: 41348000 | AI38: 108948000 | AJ38: 59400000 | AK38: 33215000 | AL38: 23922000 | AM38: 121277000 | AN38: 59148000 | AO38: 639000 | AP38: 17980000 | AQ38: 70540000 | AR38: 95387000 | AS38: 997000 | AT38: 665000 | AU38: 50355000 | AV38: 44428000 | AW38: 1111000 | AX38: 810000 | AY38: 32217000 | AZ38: 25980000 | BA38: 14068000 | BB38: 14864000 | BC38: 34686000 | BD38: 4525000 | BE38: 3659000 | BF38: 19304000 | BG38: 28034000 | BH38: 7611000 | BI38: 1824000 | BJ38: 1744000 | BK38: 2924000 | BL38: 2999000 | BM38: 48000 | BN38: 15959000 | BO38: 15826000 | BP38: 9570000 | BQ38: 22027000 | BR38: 43706000 | BS38: 7452000 | BT38: 49504000 | BU38: 54557000 | BV38: 69616000 | BW38: 21706000 | BX38: 19466000 | BY38: 38322000 | BZ38: 45725000 | CA38: 14553000 | CB38: 9182000 | CC38: 36536000 | CD38: 67091000 | CH38: 10633000 | CI38: 10492000 | CJ38: 0 | CK38: 20122000 | CL38: 17446000 | CM38: 3946000 | CN38: 0 | CO38: 13110000 | CP38: 15135000 | CT38: 23825000 | CX38: 12343000 | DB38: 10002000 | DF38: 14757000 | DJ38: 5210000
A39: OtherPayable | CE39: 200000 | CG39: 161000000 | CH39: 162000000 | CI39: 162000000
A40: CurrentAccruedExpenses | B40: 1013594000 | C40: 848757000 | D40: 1036919000 | E40: 1110505000 | F40: 1069926000 | G40: 930260000 | H40: 1049139000 | I40: 1039222000 | J40: 973025000 | K40: 861653000 | L40: 1006552000 | M40: 1060602000 | N40: 978567000 | O40: 791368000 | P40: 709156000 | Q40: 717467000 | R40: 666251000 | S40: 560007000 | T40: 618405000 | U40: 638644000 | V40: 611389000 | W40: 495371000 | X40: 549658000 | Y40: 553596000 | Z40: 521027000 | AA40: 459105000 | AB40: 500866000 | AC40: 504427000 | AD40: 474426000 | AE40: 440697000 | AF40: 467122000 | AG40: 473528000 | AH40: 443164000 | AI40: 393507000 | AJ40: 413760000 | AK40: 442859000 | AL40: 427269000 | AM40: 394827000 | AN40: 368578000 | AO40: 414881000 | AP40: 412854000 | AQ40: 359038000 | AR40: 191128000 | AS40: 392439000 | AT40: 366271000 | AU40: 360349000 | AV40: 212133000 | AW40: 414977000 | AX40: 366623000 | AY40: 380422000 | AZ40: 347741000 | BA40: 378750000 | BB40: 321672000 | BC40: 332251000 | BD40: 342290000 | BE40: 381346000 | BF40: 304384000 | BG40: 332722000 | BH40: 375045000 | BI40: 439583000 | BJ40: 341728000 | BK40: 356915000 | BL40: 300956000 | BM40: 258090000 | BN40: 253558000 | BO40: 406761000 | BP40: 387869000 | BQ40: 379218000 | BR40: 372920000 | BS40: 372537000 | BT40: 347606000 | BU40: 322742000 | BV40: 333889000 | BW40: 336408000 | BX40: 304962000 | BY40: 288028000 | BZ40: 297616000 | CA40: 287724000 | CB40: 255027000 | CC40: 230288000 | CD40: 239898000 | CE40: 246815000 | CF40: 219220000 | CG40: 212590000 | CH40: 242780000 | CI40: 223508000 | CJ40: 214133000 | CK40: 200683000 | CL40: 214192000 | CM40: 122451000 | CN40: 121420000 | CO40: 114654000 | CP40: 121375000 | CT40: 172825000 | CX40: 92027000 | DB40: 70441000 | DF40: 62099000 | DJ40: 61037000
A41: CurrentProvisions | D41: 136911000 | H41: 127719000 | L41: 110321000 | P41: 109291000 | T41: 107380000
A42: PensionandOtherPostRetirementBenefitPlansCurrent | D42: 214472000 | H42: 215355000 | L42: 269032000 | P42: 135492000 | T42: 121375000 | X42: 118755000 | AB42: 91243000 | AF42: 111191000 | AJ42: 78645000 | AN42: 47909000 | AR42: 76981000 | AV42: 76989000
A43: CurrentDebtAndCapitalLeaseObligation | B43: 1331433000 | C43: 1561753000 | D43: 1288939000 | E43: 1257060000 | F43: 2131699000 | G43: 2105678000 | H43: 1183559000 | I43: 1157245000 | J43: 1127841000 | K43: 1101369000 | L43: 1074079000 | M43: 1044368000 | N43: 1015733000 | O43: 991634000 | P43: 965360000 | Q43: 941059000 | R43: 915630000 | S43: 895024000 | T43: 1950000 | U43: 1929000 | V43: 1909000 | W43: 1889000 | X43: 401345000 | Y43: 401532000 | Z43: 401402000 | AA43: 401188000 | AB43: 500950000 | AC43: 501480000 | AD43: 501548000 | AE43: 1526000 | AF43: 1379000 | AG43: 1358000 | AH43: 101335000 | AI43: 101309000 | AJ43: 101158000 | AK43: 101041000 | AL43: 101013000 | AM43: 100989000 | AN43: 75966000 | AO43: 50945000 | AP43: 25927000 | AQ43: 909000 | AR43: 892000 | AS43: 891000 | AT43: 344000 | AU43: 459000 | AV43: 590000 | AW43: 763000 | AX43: 963000 | AY43: 1039000 | AZ43: 1157000 | BA43: 1358000 | BB43: 1595000 | BC43: 3547000 | BD43: 3671000 | BE43: 26762000 | BF43: 26797000 | BG43: 19526000 | BH43: 14158000 | BI43: 8455000 | BJ43: 2999000 | BK43: 2830000 | BL43: 3246000 | BM43: 7186000 | BN43: 8080000 | BO43: 8473000 | BP43: 9167000 | BQ43: 8800000 | BR43: 8785000 | BS43: 8864000 | BT43: 9561000 | BU43: 10737000 | BV43: 12860000 | BW43: 14704000 | BX43: 15956000 | BY43: 16880000 | BZ43: 16670000 | CA43: 17295000 | CB43: 16957000 | CC43: 16560000 | CD43: 16209000 | CE43: 15834000 | CF43: 15132000 | CG43: 395877000 | CH43: 395675000 | CI43: 391089000 | CJ43: 7942000 | CK43: 7083000 | CL43: 9035000 | CM43: 64991000 | CN43: 24326000 | CO43: 182954000 | CP43: 1233000 | CQ43: 181300000 | CR43: 149900000 | CS43: 114300000 | CT43: 725000 | CU43: 260300000 | CV43: 161600000 | CW43: 120400000 | CX43: 23383000 | CY43: 195200000 | CZ43: 59600000 | DA43: 51900000 | DB43: 40499000 | DC43: 186800000 | DD43: 76600000 | DE43: 106500000 | DF43: 73682000 | DG43: 201600000 | DH43: 126000000 | DI43: 97900000 | DJ43: 31041000 | DK43: 114000000 | DL43: 63300000 | DM43: 28300000 | DN43: 19300000 | DO43: 69100000 | DP43: 35300000 | DQ43: 26300000 | DR43: 11300000 | DS43: 58300000 | DT43: 1300000 | DU43: 1300000 | DV43: 1300000 | DW43: 10300000 | DX43: 1300000 | DY43: 1600000 | DZ43: 1600000 | EA43: 10400000 | EB43: 7800000 | EC43: 7800000 | ED43: 7800000 | EE43: 7800000 | EF43: 3800000 | EG43: 800000 | EH43: 16300000 | EI43: 6500000 | EJ43: 6500000
A44: CurrentDebt | C44: 250000000 | F44: 900635000 | G44: 900635000 | O44: 580000 | P44: 555000 | Q44: 555000 | R44: 555000 | S44: 555000 | T44: 1950000 | U44: 1929000 | V44: 1909000 | W44: 1889000 | X44: 401345000 | Y44: 401532000 | Z44: 401402000 | AA44: 401188000 | AB44: 500950000 | AC44: 501480000 | AD44: 501548000 | AE44: 1526000 | AF44: 1379000 | AG44: 1358000 | AH44: 101335000 | AI44: 101309000 | AJ44: 101158000 | AK44: 101041000 | AL44: 101013000 | AM44: 100989000 | AN44: 75966000 | AO44: 50945000 | AP44: 25927000 | AQ44: 909000 | AR44: 892000 | AS44: 891000 | AT44: 344000 | AU44: 459000 | AV44: 590000 | AW44: 763000 | AX44: 963000 | AY44: 1039000 | AZ44: 1157000 | BA44: 1358000 | BB44: 1595000 | BC44: 3547000 | BD44: 3671000 | BE44: 26762000 | BF44: 26797000 | BG44: 19526000 | BH44: 14158000 | BI44: 8455000 | BJ44: 2999000 | BK44: 2830000 | BL44: 3246000 | BM44: 7186000 | BN44: 8080000 | BO44: 8473000 | BP44: 9167000 | BQ44: 8800000 | BR44: 8785000 | BS44: 8864000 | BT44: 9561000 | BU44: 10737000 | BV44: 12860000 | BW44: 14704000 | BX44: 15956000 | BY44: 16880000 | BZ44: 16670000 | CA44: 17295000 | CB44: 16957000 | CC44: 16560000 | CD44: 16209000 | CE44: 15834000 | CF44: 15132000 | CG44: 395877000 | CH44: 395675000 | CI44: 391089000 | CJ44: 7942000 | CK44: 7083000 | CL44: 9035000 | CM44: 64991000 | CN44: 24326000 | CO44: 182954000 | CP44: 1233000 | CQ44: 181300000 | CR44: 149900000 | CS44: 114300000 | CT44: 725000 | CU44: 260300000 | CV44: 161600000 | CW44: 120400000 | CX44: 23383000 | CY44: 195200000 | CZ44: 59600000 | DA44: 51900000 | DB44: 40499000 | DC44: 186800000 | DD44: 76600000 | DE44: 106500000 | DF44: 73682000 | DG44: 201600000 | DH44: 126000000 | DI44: 97900000 | DJ44: 31041000 | DK44: 114000000 | DL44: 63300000 | DM44: 28300000 | DN44: 19300000 | DO44: 69100000 | DP44: 35300000 | DQ44: 26300000 | DR44: 11300000 | DS44: 58300000 | DT44: 1300000 | DU44: 1300000 | DV44: 1300000 | DW44: 10300000 | DX44: 1300000 | DY44: 1600000 | DZ44: 1600000 | EA44: 10400000 | EB44: 7800000 | EC44: 7800000 | ED44: 7800000 | EE44: 7800000 | EF44: 3800000 | EG44: 800000 | EH44: 16300000 | EI44: 6500000 | EJ44: 6500000
A45: OtherCurrentBorrowings | C45: 250000000 | F45: 900635000 | G45: 900635000 | O45: 580000 | P45: 555000 | Q45: 555000 | R45: 555000 | S45: 555000
A46: CurrentCapitalLeaseObligation | B46: 1331433000 | C46: 1311753000 | D46: 1288939000 | E46: 1257060000 | F46: 1231064000 | G46: 1205043000 | H46: 1183559000 | I46: 1157245000 | J46: 1127841000 | K46: 1101369000 | L46: 1074079000 | M46: 1044368000 | N46: 1015733000 | O46: 991054000 | P46: 964805000 | Q46: 940504000 | R46: 915075000 | S46: 894469000
A47: CurrentDeferredLiabilities | AG47: 16128000 | AH47: 32306000 | AI47: 33808000 | AJ47: 25268000 | AK47: 38858000 | AL47: 21434000 | AM47: 23545000 | AN47: 21795000 | AO47: 35190000 | AP47: 28573000 | AQ47: 31520000 | AR47: 23223000 | AS47: 39785000 | AT47: 15546000 | AU47: 14166000 | AV47: 3722000 | AW47: 22826000 | AX47: 35606000 | AY47: 39842000 | AZ47: 36854000 | BA47: 44601000 | BB47: 39287000 | BC47: 46282000 | BD47: 25061000 | BE47: 46178000 | BF47: 15032000 | BG47: 11942000 | BI47: 22669000 | BN47: 0
A48: CurrentDeferredTaxesLiabilities | AG48: 16128000 | AH48: 32306000 | AI48: 33808000 | AJ48: 25268000 | AK48: 38858000 | AL48: 21434000 | AM48: 23545000 | AN48: 21795000 | AO48: 35190000 | AP48: 28573000 | AQ48: 31520000 | AR48: 23223000 | AS48: 39785000 | AT48: 15546000 | AU48: 14166000 | AV48: 3722000 | AW48: 22826000 | AX48: 35606000 | AY48: 39842000 | AZ48: 36854000 | BA48: 44601000 | BB48: 39287000 | BC48: 46282000 | BD48: 25061000 | BE48: 46178000 | BF48: 15032000 | BG48: 11942000 | BI48: 22669000 | BN48: 0
A49: OtherCurrentLiabilities | CQ49: 144600000 | CR49: 125500000 | CS49: 151700000 | CU49: 93400000 | CV49: 109400000 | CW49: 98300000 | CY49: 89900000 | CZ49: 75500000 | DA49: 62400000 | DC49: 72800000 | DD49: 66800000 | DE49: 64500000 | DG49: 65700000 | DH49: 56500000 | DI49: 59600000 | DK49: 58600000 | DL49: 49400000 | DM49: 46500000 | DN49: 47900000 | DO49: 45500000 | DP49: 42600000 | DQ49: 43100000 | DR49: 41700000 | DS49: 35000000 | DT49: 30500000 | DU49: 25300000 | DV49: 23300000 | DW49: 21900000 | DX49: 20800000 | DY49: 17400000 | DZ49: 22000000 | EA49: 17800000 | EB49: 16500000 | EC49: 15000000 | ED49: 15200000 | EE49: 14500000 | EF49: 13700000 | EG49: 51600000 | EH49: 45100000 | EI49: 58700000 | EJ49: 43700000
A50: TotalNonCurrentLiabilitiesNetMinorityInterest | B50: 18063930000 | C50: 17768003000 | D50: 17653827000 | E50: 16410705000 | F50: 14483979000 | G50: 14042843000 | H50: 14086028000 | I50: 13995002000 | J50: 13871589000 | K50: 13671375000 | L50: 13490603000 | M50: 13281712000 | N50: 13080174000 | O50: 12795631000 | P50: 11579024000 | Q50: 11258457000 | R50: 10856099000 | S50: 10774899000 | T50: 3770788000 | U50: 3782951000 | V50: 3649463000 | W50: 3731580000 | X50: 3426259000 | Y50: 3692795000 | Z50: 3626974000 | AA50: 3575433000 | AB50: 3643199000 | AC50: 3595485000 | AD50: 3484603000 | AE50: 3916407000 | AF50: 3884413000 | AG50: 3953117000 | AH50: 3621498000 | AI50: 3497753000 | AJ50: 3526326000 | AK50: 3522889000 | AL50: 3760383000 | AM50: 3906339000 | AN50: 3653360000 | AO50: 3747971000 | AP50: 3727964000 | AQ50: 3714396000 | AR50: 3643805000 | AS50: 3904976000 | AT50: 3766381000 | AU50: 3767523000 | AV50: 3510123000 | AW50: 3609649000 | AX50: 3628588000 | AY50: 4107978000 | AZ50: 4126370000 | BA50: 4121869000 | BB50: 4177470000 | BC50: 4234510000 | BD50: 4266721000 | BE50: 4966185000 | BF50: 4957581000 | BG50: 4969554000 | BH50: 4982269000 | BI50: 4983980000 | BJ50: 4978270000 | BK50: 4977652000 | BL50: 5094317000 | BM50: 527259000 | BN50: 461896000 | BO50: 554859000 | BP50: 579068000 | BQ50: 397161000 | BR50: 337595000 | BS50: 406554000 | BT50: 323181000 | BU50: 328794000 | BV50: 330847000 | BW50: 401868000 | BX50: 335260000 | BY50: 332269000 | BZ50: 331987000 | CA50: 327457000 | CB50: 329353000 | CC50: 377612000 | CD50: 380584000 | CE50: 547538000 | CF50: 552737000 | CG50: 389471000 | CH50: 377116000 | CI50: 347174000 | CJ50: 897435000 | CK50: 895526000 | CL50: 882764000 | CM50: 261724000 | CN50: 257042000 | CO50: 57685000 | CP50: 52723000 | CT50: 30889000 | CX50: 23231000 | DB50: 8153000 | DF50: 6271000 | DJ50: 8149000
A51: LongTermProvisions | H51: 129692000 | L51: 134765000 | P51: 131281000 | T51: 130022000
A52: LongTermDebtAndCapitalLeaseObligation | B52: 16704408000 | C52: 16428600000 | D52: 16372160000 | E52: 15180770000 | F52: 13361028000 | G52: 12906636000 | H52: 13062777000 | I52: 12935940000 | J52: 12818481000 | K52: 12630152000 | L52: 12516363000 | M52: 12416600000 | N52: 12213885000 | O52: 11923980000 | P52: 10731121000 | Q52: 10451413000 | R52: 10054354000 | S52: 9971050000 | T52: 2862740000 | U52: 2902439000 | V52: 2776811000 | W52: 2862497000 | X52: 2604613000 | Y52: 2719568000 | Z52: 2683105000 | AA52: 2632090000 | AB52: 2710576000 | AC52: 2673210000 | AD52: 2556464000 | AE52: 2989663000 | AF52: 2969175000 | AG52: 3105332000 | AH52: 2761794000 | AI52: 2614005000 | AJ52: 2639427000 | AK52: 2666022000 | AL52: 2881217000 | AM52: 3006404000 | AN52: 2742788000 | AO52: 2873967000 | AP52: 2845138000 | AQ52: 2835303000 | AR52: 2771336000 | AS52: 3023367000 | AT52: 2887251000 | AU52: 2880920000 | AV52: 2617891000 | AW52: 2721061000 | AX52: 2779408000 | AY52: 3262597000 | AZ52: 3287070000 | BA52: 3286907000 | BB52: 3350807000 | BC52: 3399887000 | BD52: 3399715000 | BE52: 4105252000 | BF52: 4111023000 | BG52: 4117190000 | BH52: 4122956000 | BI52: 4172467000 | BJ52: 4177610000 | BK52: 4176121000 | BL52: 4278756000 | BM52: 260373000 | BN52: 261958000 | BO52: 495339000 | BP52: 516537000 | BQ52: 333471000 | BR52: 269962000 | BS52: 344436000 | BT52: 255445000 | BU52: 256452000 | BV52: 258462000 | BW52: 321194000 | BX52: 259009000 | BY52: 261621000 | BZ52: 265337000 | CA52: 268357000 | CB52: 272420000 | CC52: 326028000 | CD52: 330337000 | CE52: 502498000 | CF52: 506707000 | CG52: 336083000 | CH52: 339470000 | CI52: 347174000 | CJ52: 735435000 | CK52: 733526000 | CL52: 720764000 | CM52: 210907000 | CN52: 205369000 | CO52: 2240000 | CP52: 1200000 | CQ52: 1500000 | CR52: 1500000 | CS52: 600000 | CT52: 786000 | CU52: 200000 | CV52: 200000 | CW52: 400000 | CX52: 1294000 | CY52: 1400000 | CZ52: 1600000 | DA52: 1800000 | DB52: 2582000 | DC52: 2700000 | DD52: 2100000 | DE52: 2300000 | DF52: 3278000 | DG52: 3400000 | DH52: 3600000 | DI52: 3900000 | DJ52: 4767000 | DK52: 4500000 | DL52: 4700000 | DM52: 4800000 | DN52: 5700000 | DO52: 5800000 | DP52: 6000000 | DQ52: 6100000 | DR52: 7000000 | DS52: 7100000 | DT52: 37300000 | DU52: 23500000 | DV52: 21200000 | DW52: 45700000 | DX52: 38300000 | DY52: 24100000 | DZ52: 19100000 | EA52: 60200000 | EB52: 57600000 | EC52: 46700000 | ED52: 26800000 | EE52: 60900000 | EF52: 62500000 | EG52: 45600000 | EH52: 48900000 | EI52: 52300000 | EJ52: 64300000
A53: LongTermDebt | B53: 7295215000 | C53: 7028767000 | D53: 7009399000 | E53: 5985728000 | F53: 4290700000 | G53: 3947462000 | H53: 4172068000 | I53: 4127426000 | J53: 4156765000 | K53: 4130710000 | L53: 4130975000 | M53: 4131573000 | N53: 4089001000 | O53: 3967221000 | P53: 2911438000 | Q53: 2762490000 | R53: 2573483000 | S53: 2732105000 | T53: 2862740000 | U53: 2902439000 | V53: 2776811000 | W53: 2862497000 | X53: 2604613000 | Y53: 2719568000 | Z53: 2683105000 | AA53: 2632090000 | AB53: 2710576000 | AC53: 2673210000 | AD53: 2556464000 | AE53: 2989663000 | AF53: 2969175000 | AG53: 3105332000 | AH53: 2761794000 | AI53: 2614005000 | AJ53: 2639427000 | AK53: 2666022000 | AL53: 2881217000 | AM53: 3006404000 | AN53: 2742788000 | AO53: 2873967000 | AP53: 2845138000 | AQ53: 2835303000 | AR53: 2771336000 | AS53: 3023367000 | AT53: 2887251000 | AU53: 2880920000 | AV53: 2617891000 | AW53: 2721061000 | AX53: 2779408000 | AY53: 3262597000 | AZ53: 3287070000 | BA53: 3286907000 | BB53: 3350807000 | BC53: 3399887000 | BD53: 3399715000 | BE53: 4105252000 | BF53: 4111023000 | BG53: 4117190000 | BH53: 4122956000 | BI53: 4172467000 | BJ53: 4177610000 | BK53: 4176121000 | BL53: 4278756000 | BM53: 260373000 | BN53: 261958000 | BO53: 495339000 | BP53: 516537000 | BQ53: 333471000 | BR53: 269962000 | BS53: 344436000 | BT53: 255445000 | BU53: 256452000 | BV53: 258462000 | BW53: 321194000 | BX53: 259009000 | BY53: 261621000 | BZ53: 265337000 | CA53: 268357000 | CB53: 272420000 | CC53: 326028000 | CD53: 330337000 | CE53: 502498000 | CF53: 506707000 | CG53: 336083000 | CH53: 339470000 | CI53: 347174000 | CJ53: 735435000 | CK53: 733526000 | CL53: 720764000 | CM53: 210907000 | CN53: 205369000 | CO53: 2240000 | CP53: 1200000 | CQ53: 1500000 | CR53: 1500000 | CS53: 600000 | CT53: 786000 | CU53: 200000 | CV53: 200000 | CW53: 400000 | CX53: 1294000 | CY53: 1400000 | CZ53: 1600000 | DA53: 1800000 | DB53: 2582000 | DC53: 2700000 | DD53: 2100000 | DE53: 2300000 | DF53: 3278000 | DG53: 3400000 | DH53: 3600000 | DI53: 3900000 | DJ53: 4767000 | DK53: 4500000 | DL53: 4700000 | DM53: 4800000 | DN53: 5700000 | DO53: 5800000 | DP53: 6000000 | DQ53: 6100000 | DR53: 7000000 | DS53: 7100000 | DT53: 37300000 | DU53: 23500000 | DV53: 21200000 | DW53: 45700000 | DX53: 38300000 | DY53: 24100000 | DZ53: 19100000 | EA53: 60200000 | EB53: 57600000 | EC53: 46700000 | ED53: 26800000 | EE53: 60900000 | EF53: 62500000 | EG53: 45600000 | EH53: 48900000 | EI53: 52300000 | EJ53: 64300000
A54: LongTermCapitalLeaseObligation | B54: 9409193000 | C54: 9399833000 | D54: 9362761000 | E54: 9195042000 | F54: 9070328000 | G54: 8959174000 | H54: 8890709000 | I54: 8808514000 | J54: 8661716000 | K54: 8499442000 | L54: 8385388000 | M54: 8285027000 | N54: 8124884000 | O54: 7956759000 | P54: 7819683000 | Q54: 7688923000 | R54: 7480871000 | S54: 7238945000
A55: NonCurrentDeferredLiabilities | B55: 1119114000 | C55: 1111434000 | D55: 1060906000 | E55: 992479000 | F55: 906846000 | G55: 907020000 | H55: 825254000 | I55: 781231000 | J55: 781477000 | K55: 769430000 | L55: 710549000 | M55: 686694000 | N55: 689893000 | O55: 700098000 | P55: 675227000 | Q55: 634041000 | R55: 627765000 | S55: 629864000 | T55: 609687000 | U55: 583066000 | V55: 569690000 | W55: 565150000 | X55: 515702000 | Y55: 690795000 | Z55: 659844000 | AA55: 662485000 | AB55: 652841000 | AC55: 637135000 | AD55: 647372000 | AE55: 647626000 | AF55: 639955000 | AG55: 568238000 | AH55: 578084000 | AI55: 598248000 | AJ55: 601590000 | AK55: 569055000 | AL55: 582883000 | AM55: 600239000 | AN55: 614026000 | AO55: 643206000 | AP55: 647780000 | AQ55: 646462000 | AR55: 670453000 | AS55: 655910000 | AT55: 651521000 | AU55: 649532000 | AV55: 656996000 | AW55: 647329000 | AX55: 624034000 | AY55: 606071000 | AZ55: 598565000 | BA55: 565510000 | BB55: 532313000 | BC55: 540010000 | BD55: 546172000 | BE55: 547180000 | BF55: 550551000 | BG55: 554098000 | BH55: 556101000 | BI55: 542260000 | BJ55: 483867000 | BK55: 490035000 | BL55: 486725000 | BM55: 0 | BN55: 41597000 | BO55: 59520000 | BP55: 62531000 | BQ55: 63690000 | BR55: 67633000 | BS55: 62118000 | BT55: 67736000 | BU55: 72342000 | BV55: 72385000 | BW55: 80674000 | BX55: 76251000 | BY55: 70648000 | BZ55: 66650000 | CA55: 59100000 | CB55: 56933000 | CC55: 51584000 | CD55: 50247000 | CE55: 45040000 | CF55: 46030000 | CG55: 53388000 | CH55: 37646000 | CL55: 0 | CM55: 50817000 | CN55: 51673000 | CO55: 55445000 | CP55: 51523000 | CQ55: 12100000 | CR55: 18100000 | CS55: 24600000 | CT55: 30103000 | CU55: 12300000 | CV55: 21700000 | CW55: 21700000 | CX55: 21937000 | CY55: 5400000 | CZ55: 5300000 | DA55: 7800000 | DB55: 5571000 | DC55: 3600000 | DD55: 3600000 | DE55: 3600000 | DF55: 2993000 | DG55: 3400000 | DH55: 3400000 | DI55: 3400000 | DJ55: 3382000 | DK55: 2600000 | DL55: 2600000 | DM55: 2600000 | DN55: 2600000 | DO55: 2600000 | DP55: 2600000 | DQ55: 2600000 | DR55: 2600000 | DS55: 2900000 | DT55: 2900000 | DU55: 2800000 | DV55: 2800000 | DW55: 1800000 | DX55: 1600000 | DY55: 1800000 | DZ55: 1800000 | EA55: 1400000 | EB55: 1300000 | EC55: 1300000 | ED55: 1300000 | EE55: 1100000 | EF55: 700000 | EG55: 700000 | EH55: 5100000 | EI55: 6100000 | EJ55: 5200000
A56: NonCurrentDeferredTaxesLiabilities | B56: 1119114000 | C56: 1111434000 | D56: 1060906000 | E56: 992479000 | F56: 906846000 | G56: 907020000 | H56: 825254000 | I56: 781231000 | J56: 781477000 | K56: 769430000 | L56: 710549000 | M56: 686694000 | N56: 689893000 | O56: 700098000 | P56: 675227000 | Q56: 634041000 | R56: 627765000 | S56: 629864000 | T56: 609687000 | U56: 583066000 | V56: 569690000 | W56: 565150000 | X56: 515702000 | Y56: 690795000 | Z56: 659844000 | AA56: 662485000 | AB56: 652841000 | AC56: 637135000 | AD56: 647372000 | AE56: 647626000 | AF56: 639955000 | AG56: 568238000 | AH56: 578084000 | AI56: 598248000 | AJ56: 601590000 | AK56: 569055000 | AL56: 582883000 | AM56: 600239000 | AN56: 614026000 | AO56: 643206000 | AP56: 647780000 | AQ56: 646462000 | AR56: 670453000 | AS56: 655910000 | AT56: 651521000 | AU56: 649532000 | AV56: 656996000 | AW56: 647329000 | AX56: 624034000 | AY56: 606071000 | AZ56: 598565000 | BA56: 565510000 | BB56: 532313000 | BC56: 540010000 | BD56: 546172000 | BE56: 547180000 | BF56: 550551000 | BG56: 554098000 | BH56: 556101000 | BI56: 542260000 | BJ56: 483867000 | BK56: 490035000 | BL56: 486725000 | BM56: 0 | BN56: 41597000 | BO56: 59520000 | BP56: 62531000 | BQ56: 63690000 | BR56: 67633000 | BS56: 62118000 | BT56: 67736000 | BU56: 72342000 | BV56: 72385000 | BW56: 80674000 | BX56: 76251000 | BY56: 70648000 | BZ56: 66650000 | CA56: 59100000 | CB56: 56933000 | CC56: 51584000 | CD56: 50247000 | CE56: 45040000 | CF56: 46030000 | CG56: 53388000 | CH56: 37646000 | CL56: 0 | CM56: 50817000 | CN56: 51673000 | CO56: 55445000 | CP56: 51523000 | CQ56: 12100000 | CR56: 18100000 | CS56: 24600000 | CT56: 30103000 | CU56: 12300000 | CV56: 21700000 | CW56: 21700000 | CX56: 21937000 | CY56: 5400000 | CZ56: 5300000 | DA56: 7800000 | DB56: 5571000 | DC56: 3600000 | DD56: 3600000 | DE56: 3600000 | DF56: 2993000 | DG56: 3400000 | DH56: 3400000 | DI56: 3400000 | DJ56: 3382000 | DK56: 2600000 | DL56: 2600000 | DM56: 2600000 | DN56: 2600000 | DO56: 2600000 | DP56: 2600000 | DQ56: 2600000 | DR56: 2600000 | DS56: 2900000 | DT56: 2900000 | DU56: 2800000 | DV56: 2800000 | DW56: 1800000 | DX56: 1600000 | DY56: 1800000 | DZ56: 1800000 | EA56: 1400000 | EB56: 1300000 | EC56: 1300000 | ED56: 1300000 | EE56: 1100000 | EF56: 700000 | EG56: 700000 | EH56: 5100000 | EI56: 6100000 | EJ56: 5200000
A57: NonCurrentDeferredRevenue | P57: 0 | T57: 40303000 | X57: 44781000 | AB57: 49259000 | AF57: 53737000 | AJ57: 58215000 | AN57: 62693000
A58: TradeandOtherPayablesNonCurrent | H58: 0 | L58: 81488000 | CJ58: 162000000 | CK58: 162000000 | CL58: 162000000
A59: NonCurrentAccruedExpenses | X59: 134256000 | AB59: 137743000 | AF59: 137798000 | AJ59: 140916000 | AN59: 145162000 | AR59: 137451000
A60: EmployeeBenefits | AJ60: 20266000 | AN60: 17604000 | AR60: 18404000
A61: RestrictedCommonStock | AT61: 5601000 | AU61: 5644000 | AV61: 6087000 | AW61: 7309000 | AX61: 9271000 | AY61: 9267000 | AZ61: 9153000 | BA61: 14783000 | BB61: 14927000 | BC61: 16624000 | BD61: 18486000 | BE61: 15131000 | BF61: 15281000 | BG61: 14350000 | BH61: 13924000 | BI61: 13150000 | BJ61: 11157000 | BK61: 9112000 | BL61: 9122000
A62: OtherNonCurrentLiabilities | B62: 240408000 | C62: 227969000 | D62: 220761000 | E62: 237456000 | F62: 216105000 | G62: 229187000 | H62: 197997000 | I62: 277831000 | J62: 271631000 | K62: 271793000 | L62: 263691000 | M62: 178418000 | N62: 176396000 | O62: 171553000 | P62: 172676000 | Q62: 173003000 | R62: 173980000 | S62: 173985000 | T62: 298361000 | U62: 297446000 | V62: 302962000 | W62: 303933000 | X62: 305944000 | Y62: 282432000 | Z62: 284025000 | AA62: 280858000 | AB62: 279782000 | AC62: 285140000 | AD62: 280767000 | AE62: 279118000 | AF62: 275283000 | AG62: 279547000 | AH62: 281620000 | AI62: 285500000 | AJ62: 285309000 | AK62: 287812000 | AL62: 296283000 | AM62: 299696000 | AN62: 296546000 | AO62: 230798000 | AP62: 235046000 | AQ62: 232631000 | AR62: 46161000 | AS62: 225699000 | AT62: 222008000 | AU62: 231427000 | AV62: 229149000 | AW62: 233950000 | AX62: 215875000 | AY62: 230043000 | AZ62: 231582000 | BA62: 254669000 | BB62: 279423000 | BC62: 277989000 | BD62: 302348000 | BE62: 298622000 | BF62: 280726000 | BG62: 283916000 | BH62: 289288000 | BI62: 256103000 | BJ62: 305636000 | BK62: 302384000 | BL62: 319714000 | BM62: 266886000 | BN62: 158341000
A63: TotalEquityGrossMinorityInterest | B63: 6297705000 | C63: 5935251000 | D63: 5541772000 | E63: 6093806000 | F63: 6188491000 | G63: 5961624000 | H63: 6261986000 | I63: 6189801000 | J63: 6137135000 | K63: 6249925000 | L63: 6661238000 | M63: 6985519000 | N63: 7356071000 | O63: 7209454000 | P63: 6702500000 | Q63: 6648295000 | R63: 6749160000 | S63: 6572669000 | T63: 6417393000 | U63: 6355888000 | V63: 6378942000 | W63: 6236318000 | X63: 6125774000 | Y63: 5744155000 | Z63: 5687095000 | AA63: 5528881000 | AB63: 5406294000 | AC63: 5361852000 | AD63: 5413361000 | AE63: 5388383000 | AF63: 5377876000 | AG63: 5343593000 | AH63: 5418934000 | AI63: 5385858000 | AJ63: 5710038000 | AK63: 5343637000 | AL63: 5095993000 | AM63: 4832227000 | AN63: 5402193000 | AO63: 5274954000 | AP63: 5231476000 | AQ63: 5178899000 | AR63: 4985330000 | AS63: 4734862000 | AT63: 4810410000 | AU63: 4591432000 | AV63: 4668495000 | AW63: 4554012000 | AX63: 4373564000 | AY63: 4219656000 | AZ63: 4054479000 | BA63: 3817390000 | BB63: 3682844000 | BC63: 3536526000 | BD63: 3390298000 | BE63: 2855414000 | BF63: 3016538000 | BG63: 2916585000 | BH63: 2831695000 | BI63: 2763464000 | BJ63: 2766803000 | BK63: 2730607000 | BL63: 2703873000 | BM63: 1796777000 | BN63: 1745747000 | BO63: 1702941000 | BP63: 1721477000 | BQ63: 1686814000 | BR63: 1720795000 | BS63: 1614287000 | BT63: 1647817000 | BU63: 1727966000 | BV63: 1684465000 | BW63: 1577490000 | BX63: 1538876000 | BY63: 1488083000 | BZ63: 1576920000 | CA63: 1501660000 | CB63: 1402145000 | CC63: 1337747000 | CD63: 1288068000 | CE63: 1190351000 | CF63: 1131354000 | CG63: 1088660000 | CH63: 1041718000 | CI63: 953160000 | CJ63: 916030000 | CK63: 895620000 | CL63: 861763000 | CM63: 1005389000 | CN63: 946359000 | CO63: 907506000 | CP63: 925921000 | CQ63: 862100000 | CR63: 837200000 | CS63: 787500000 | CT63: 725761000 | CU63: 652000000 | CV63: 643800000 | CW63: 596700000 | CX63: 583896000 | CY63: 516900000 | CZ63: 559500000 | DA63: 519400000 | DB63: 485529000 | DC63: 434400000 | DD63: 449600000 | DE63: 435400000 | DF63: 420011000 | DG63: 383100000 | DH63: 363900000 | DI63: 334600000 | DJ63: 323756000 | DK63: 286400000 | DL63: 269500000 | DM63: 256500000 | DN63: 240700000 | DO63: 219400000 | DP63: 206500000 | DQ63: 194600000 | DR63: 189800000 | DS63: 168900000 | DT63: 160300000 | DU63: 153700000 | DV63: 151000000 | DW63: 138100000 | DX63: 134400000 | DY63: 131900000 | DZ63: 131700000 | EA63: 123600000 | EB63: 121800000 | EC63: 120100000 | ED63: 120600000 | EE63: 114300000 | EF63: 112300000 | EG63: 111600000 | EH63: 109500000 | EI63: 108800000 | EJ63: 108000000
A64: StockholdersEquity | B64: 6297705000 | C64: 5935251000 | D64: 5541772000 | E64: 6093806000 | F64: 6188491000 | G64: 5961624000 | H64: 6261986000 | I64: 6189801000 | J64: 6137135000 | K64: 6249925000 | L64: 6661238000 | M64: 6985519000 | N64: 7356071000 | O64: 7209454000 | P64: 6702500000 | Q64: 6648295000 | R64: 6749160000 | S64: 6572669000 | T64: 6417393000 | U64: 6355888000 | V64: 6378942000 | W64: 6236318000 | X64: 6125774000 | Y64: 5744155000 | Z64: 5687095000 | AA64: 5528881000 | AB64: 5406294000 | AC64: 5361852000 | AD64: 5413361000 | AE64: 5388383000 | AF64: 5377876000 | AG64: 5343593000 | AH64: 5418934000 | AI64: 5385858000 | AJ64: 5710038000 | AK64: 5343637000 | AL64: 5095993000 | AM64: 4832227000 | AN64: 5402193000 | AO64: 5274954000 | AP64: 5231476000 | AQ64: 5178899000 | AR64: 4985330000 | AS64: 4734862000 | AT64: 4810410000 | AU64: 4591432000 | AV64: 4668495000 | AW64: 4554012000 | AX64: 4373564000 | AY64: 4219656000 | AZ64: 4054479000 | BA64: 3817390000 | BB64: 3682844000 | BC64: 3536526000 | BD64: 3390298000 | BE64: 2855414000 | BF64: 3016538000 | BG64: 2916585000 | BH64: 2831695000 | BI64: 2763464000 | BJ64: 2766803000 | BK64: 2730607000 | BL64: 2703873000 | BM64: 1796777000 | BN64: 1745747000 | BO64: 1702941000 | BP64: 1721477000 | BQ64: 1686814000 | BR64: 1720795000 | BS64: 1614287000 | BT64: 1647817000 | BU64: 1727966000 | BV64: 1684465000 | BW64: 1577490000 | BX64: 1538876000 | BY64: 1488083000 | BZ64: 1576920000 | CA64: 1501660000 | CB64: 1402145000 | CC64: 1337747000 | CD64: 1288068000 | CE64: 1190351000 | CF64: 1131354000 | CG64: 1088660000 | CH64: 1041718000 | CI64: 953160000 | CJ64: 916030000 | CK64: 895620000 | CL64: 861763000 | CM64: 1005389000 | CN64: 946359000 | CO64: 907506000 | CP64: 925921000 | CQ64: 862100000 | CR64: 837200000 | CS64: 787500000 | CT64: 725761000 | CU64: 652000000 | CV64: 643800000 | CW64: 596700000 | CX64: 583896000 | CY64: 516900000 | CZ64: 559500000 | DA64: 519400000 | DB64: 485529000 | DC64: 434400000 | DD64: 449600000 | DE64: 435400000 | DF64: 420011000 | DG64: 383100000 | DH64: 363900000 | DI64: 334600000 | DJ64: 323756000 | DK64: 286400000 | DL64: 269500000 | DM64: 256500000 | DN64: 240700000 | DO64: 219400000 | DP64: 206500000 | DQ64: 194600000 | DR64: 189800000 | DS64: 168900000 | DT64: 160300000 | DU64: 153700000 | DV64: 151000000 | DW64: 138100000 | DX64: 134400000 | DY64: 131900000 | DZ64: 131700000 | EA64: 123600000 | EB64: 121800000 | EC64: 120100000 | ED64: 120600000 | EE64: 114300000 | EF64: 112300000 | EG64: 111600000 | EH64: 109500000 | EI64: 108800000 | EJ64: 108000000
A65: CapitalStock | B65: 192039000 | C65: 191921000 | D65: 191718000 | E65: 195629000 | F65: 197372000 | G65: 198623000 | H65: 201265000 | I65: 202743000 | J65: 204142000 | K65: 206680000 | L65: 210687000 | M65: 214375000 | N65: 217906000 | O65: 220259000 | P65: 220444000 | Q65: 222775000 | R65: 224935000 | S65: 226032000 | T65: 227072000 | U65: 230022000 | V65: 232340000 | W65: 234109000 | X65: 235141000 | Y65: 237598000 | Z65: 239101000 | AA65: 239947000 | AB65: 240811000 | AC65: 244457000 | AD65: 246983000 | AE65: 249096000 | AF65: 250855000 | AG65: 254697000 | AH65: 257968000 | AI65: 260111000 | AJ65: 265514000 | AK65: 265495000 | AL65: 265458000 | AM65: 265379000 | AN65: 277424000 | AO65: 280215000 | AP65: 283120000 | AQ65: 286464000 | AR65: 286185000 | AS65: 287613000 | AT65: 291983000 | AU65: 290782000 | AV65: 295828000 | AW65: 299514000 | AX65: 298842000 | AY65: 298844000 | AZ65: 298819000 | BA65: 298459000 | BB65: 298399000 | BC65: 298371000 | BD65: 298013000 | BE65: 278202000 | BF65: 278217000 | BG65: 278159000 | BH65: 278114000 | BI65: 277938000 | BJ65: 277712000 | BK65: 277740000 | BL65: 277741000 | BM65: 157298000 | BN65: 156218000 | BO65: 156024000 | BP65: 156000000 | BQ65: 155859000 | BR65: 157840000 | BS65: 158437000 | BT65: 160630000 | BU65: 164071000 | BV65: 164086000 | BW65: 163785000 | BX65: 164191000 | BY65: 164354000 | BZ65: 168095000 | CA65: 168415000 | CB65: 167345000 | CC65: 166762000 | CD65: 166670000 | CE65: 166691000 | CF65: 166670000 | CG65: 166462000 | CH65: 166359000 | CI65: 166302000 | CJ65: 166232000 | CK65: 166052000 | CL65: 165646000 | CM65: 165281000 | CN65: 164548000 | CO65: 164155000 | CP65: 132346000 | CQ65: 132700000 | CR65: 133100000 | CT65: 105979000 | CX65: 84384000 | DB65: 53963000 | DF65: 43620000 | DJ65: 34829000
A66: PreferredStock | B66: 0 | C66: 0 | D66: 0 | E66: 0 | F66: 0 | G66: 0 | H66: 0 | I66: 0 | J66: 0 | K66: 0 | L66: 0 | M66: 0 | N66: 0 | O66: 0 | P66: 0 | Q66: 0 | R66: 0 | S66: 0 | T66: 0 | U66: 0 | V66: 0 | W66: 0 | X66: 0 | Y66: 0 | Z66: 0 | AA66: 0 | AB66: 0 | AC66: 0 | AD66: 0 | AE66: 0 | AG66: 0 | AH66: 0 | AI66: 0 | AJ66: 0 | AK66: 0 | AL66: 0 | AM66: 0 | AN66: 0 | AO66: 0 | AP66: 0 | AQ66: 0 | AR66: 0 | AS66: 0 | AT66: 0 | AU66: 0 | AV66: 0 | AW66: 0 | AX66: 0 | AY66: 0 | AZ66: 0 | BA66: 0 | BB66: 0 | BC66: 0 | BE66: 0 | BF66: 0 | BG66: 0 | BH66: 0 | BI66: 0 | BJ66: 0 | BK66: 0 | BL66: 0 | BM66: 0 | BN66: 0 | BO66: 0 | BP66: 0 | BQ66: 0 | BR66: 0 | BS66: 0 | BT66: 0 | BU66: 0 | BV66: 0 | BW66: 0 | BX66: 0 | BY66: 0 | BZ66: 0 | CA66: 0 | CB66: 0 | CC66: 0 | CD66: 0 | CE66: 0 | CF66: 0 | CG66: 0 | CH66: 0 | CI66: 0 | CJ66: 0 | CK66: 0 | CL66: 0 | CM66: 0 | CN66: 0 | CO66: 0 | CP66: 0 | CT66: 858000 | CX66: 858000 | DB66: 858000 | DF66: 858000 | DJ66: 858000
A67: CommonStock | B67: 192039000 | C67: 191921000 | D67: 191718000 | E67: 195629000 | F67: 197372000 | G67: 198623000 | H67: 201265000 | I67: 202743000 | J67: 204142000 | K67: 206680000 | L67: 210687000 | M67: 214375000 | N67: 217906000 | O67: 220259000 | P67: 220444000 | Q67: 222775000 | R67: 224935000 | S67: 226032000 | T67: 227072000 | U67: 230022000 | V67: 232340000 | W67: 234109000 | X67: 235141000 | Y67: 237598000 | Z67: 239101000 | AA67: 239947000 | AB67: 240811000 | AC67: 244457000 | AD67: 246983000 | AE67: 249096000 | AF67: 250855000 | AG67: 254697000 | AH67: 257968000 | AI67: 260111000 | AJ67: 265514000 | AK67: 265495000 | AL67: 265458000 | AM67: 265379000 | AN67: 277424000 | AO67: 280215000 | AP67: 283120000 | AQ67: 286464000 | AR67: 286185000 | AS67: 287613000 | AT67: 291983000 | AU67: 290782000 | AV67: 295828000 | AW67: 299514000 | AX67: 298842000 | AY67: 298844000 | AZ67: 298819000 | BA67: 298459000 | BB67: 298399000 | BC67: 298371000 | BD67: 298013000 | BE67: 278202000 | BF67: 278217000 | BG67: 278159000 | BH67: 278114000 | BI67: 277938000 | BJ67: 277712000 | BK67: 277740000 | BL67: 277741000 | BM67: 157298000 | BN67: 156218000 | BO67: 156024000 | BP67: 156000000 | BQ67: 155859000 | BR67: 157840000 | BS67: 158437000 | BT67: 160630000 | BU67: 164071000 | BV67: 164086000 | BW67: 163785000 | BX67: 164191000 | BY67: 164354000 | BZ67: 168095000 | CA67: 168415000 | CB67: 167345000 | CC67: 166762000 | CD67: 166670000 | CE67: 166691000 | CF67: 166670000 | CG67: 166462000 | CH67: 166359000 | CI67: 166302000 | CJ67: 166232000 | CK67: 166052000 | CL67: 165646000 | CM67: 165281000 | CN67: 164548000 | CO67: 164155000 | CP67: 132346000 | CQ67: 132700000 | CR67: 133100000 | CT67: 105121000 | CX67: 83526000 | DB67: 53105000 | DF67: 42762000 | DJ67: 33971000
A68: AdditionalPaidInCapital | B68: 3724200000 | C68: 3701564000 | D68: 3693871000 | E68: 3676077000 | F68: 3627987000 | G68: 3606414000 | H68: 3587914000 | I68: 3527285000 | J68: 3504850000 | K68: 3457160000 | L68: 3446612000 | M68: 3426729000 | N68: 3381819000 | O68: 3332283000 | P68: 3322531000 | Q68: 3308160000 | R68: 3292902000 | S68: 3275917000 | T68: 3252421000 | U68: 3239170000 | V68: 3222233000 | W68: 3210527000 | X68: 3196462000 | Y68: 3176406000 | Z68: 3166518000 | AA68: 3157322000 | AB68: 3154606000 | AC68: 3144632000 | AD68: 3136683000 | AE68: 3124110000 | AF68: 3107283000 | AG68: 3095790000 | AH68: 3085637000 | AI68: 3070518000 | AJ68: 3048806000 | AK68: 3038621000 | AL68: 3027985000 | AM68: 3016262000 | AN68: 3009226000 | AO68: 3004582000 | AP68: 2998785000 | AQ68: 2992981000 | AR68: 2991351000 | AS68: 2983323000 | AT68: 2973160000 | AU68: 2967014000 | AV68: 2960940000 | AW68: 2957267000 | AX68: 2951761000 | AY68: 2948506000 | AZ68: 2945024000 | BA68: 2937300000 | BB68: 2933846000 | BC68: 2928855000 | BD68: 2923377000 | BE68: 2497939000 | BF68: 2494984000 | BG68: 2492482000 | BH68: 2489647000 | BI68: 2487071000 | BJ68: 2484606000 | BK68: 2482409000 | BL68: 2480062000 | BM68: 525830000 | BN68: 486145000 | BO68: 477687000 | BP68: 475462000 | BQ68: 470878000 | BR68: 462383000 | BS68: 451180000 | BT68: 447617000 | BU68: 441119000 | BV68: 421600000 | BW68: 405003000 | BX68: 395205000 | BY68: 386158000 | BZ68: 376930000 | CA68: 363767000 | CB68: 331185000 | CC68: 314973000 | CD68: 313269000 | CE68: 313023000 | CF68: 312589000 | CG68: 302200000 | CH68: 301848000 | CI68: 300622000 | CJ68: 299149000 | CK68: 294957000 | CL68: 283925000 | CM68: 263233000 | CN68: 245341000 | CO68: 235619000 | CP68: 255581000 | CQ68: 250300000 | CR68: 440500000 | CT68: 418039000 | CX68: 379954000 | DB68: 329948000 | DF68: 303609000 | DJ68: 283323000
A69: RetainedEarnings | B69: 2380451000 | C69: 2041118000 | D69: 1656140000 | E69: 2222823000 | F69: 2364098000 | G69: 2157589000 | H69: 2473999000 | I69: 2461208000 | J69: 2429821000 | K69: 2588006000 | L69: 3006102000 | M69: 3346821000 | N69: 3758995000 | O69: 3659804000 | P69: 3162660000 | Q69: 3120738000 | R69: 3234944000 | S69: 3074584000 | T69: 2941107000 | U69: 2890147000 | V69: 2928064000 | W69: 2795620000 | X69: 2698352000 | Y69: 2334534000 | Z69: 2286060000 | AA69: 2136401000 | AB69: 2015867000 | AC69: 1977969000 | AD69: 2035101000 | AE69: 2020784000 | AF69: 2025545000 | AG69: 1999119000 | AH69: 2081543000 | AI69: 2061798000 | AJ69: 2403045000 | AK69: 2047674000 | AL69: 1811358000 | AM69: 1560098000 | AN69: 2125453000 | AO69: 2000488000 | AP69: 1960068000 | AQ69: 1911160000 | AR69: 1710732000 | AS69: 1468534000 | AT69: 1550438000 | AU69: 1336298000 | AV69: 1416918000 | AW69: 1305107000 | AX69: 1133943000 | AY69: 987901000 | AZ69: 830932000 | BA69: 608386000 | BB69: 480266000 | BC69: 339071000 | BD69: 203075000 | BE69: 115878000 | BF69: 279960000 | BG69: 186370000 | BH69: 103364000 | BI69: 21510000 | BJ69: 28816000 | BK69: 1097000 | BL69: -4818000 | BM69: 1114170000 | BN69: 1103951000 | BO69: 1069472000 | BP69: 1090298000 | BQ69: 1060427000 | BR69: 1106165000 | BS69: 1011019000 | BT69: 1046650000 | BU69: 1129626000 | BV69: 1102457000 | BW69: 1014969000 | BX69: 985243000 | BY69: 943404000 | BZ69: 1037409000 | CA69: 975255000 | CB69: 909114000 | CC69: 860879000 | CD69: 812220000 | CE69: 714800000 | CF69: 656894000 | CG69: 625193000 | CH69: 579265000 | CI69: 492473000 | CJ69: 456383000 | CK69: 439919000 | CL69: 414318000 | CM69: 576875000 | CN69: 536470000 | CO69: 507732000 | CP69: 537994000 | CQ69: 479100000 | CR69: 463200000 | CS69: 430300000 | CT69: 402270000 | CU69: 366400000 | CV69: 332200000 | CW69: 316700000 | CX69: 320085000 | CY69: 276700000 | CZ69: 322600000 | DA69: 315000000 | DB69: 302145000 | DC69: 265400000 | DD69: 288900000 | DE69: 284100000 | DF69: 273309000 | DG69: 246600000 | DH69: 229900000 | DI69: 225200000 | DJ69: 207436000 | DK69: 184000000 | DL69: 271900000 | DM69: 158000000 | DN69: 156400000 | DO69: 136500000 | DP69: 127700000 | DQ69: 123800000 | DR69: 119600000 | DS69: 107800000 | DT69: 100800000 | DU69: 95400000 | DV69: 95400000 | DW69: 84100000 | DX69: 80800000 | DY69: 105700000 | DZ69: 105400000 | EA69: 97400000 | EB69: 95600000 | EC69: 94000000 | ED69: 94500000 | EE69: 88200000 | EF69: 86400000 | EG69: 85800000 | EH69: 82100000 | EI69: 79400000 | EJ69: 78800000
A70: TreasuryStock | BZ70: 2739000 | CD70: 2742000 | CH70: 2395000 | CI70: 2685000 | CJ70: 2690000 | CK70: 2469000 | CL70: 2126000 | CN70: 0 | CO70: 0 | CP70: 0 | CR70: 200500000 | CT70: 200527000 | CX70: 200527000 | DB70: 200527000 | DF70: 200527000 | DJ70: 201832000
A71: GainsLossesNotAffectingRetainedEarnings | B71: 1015000 | C71: 648000 | D71: 43000 | E71: -723000 | F71: -966000 | G71: -1002000 | H71: -1192000 | I71: -1435000 | J71: -1678000 | K71: -1921000 | L71: -2163000 | M71: -2406000 | N71: -2649000 | O71: -2892000 | P71: -3135000 | Q71: -3378000 | R71: -3621000 | S71: -3864000 | T71: -3207000 | U71: -3451000 | V71: -3695000 | W71: -3938000 | X71: -4181000 | Y71: -4383000 | Z71: -4584000 | AA71: -4789000 | AB71: -4990000 | AC71: -5206000 | AD71: -5406000 | AE71: -5607000 | AF71: -5807000 | AG71: -6013000 | AH71: -6214000 | AI71: -6569000 | AJ71: -7327000 | AK71: -8153000 | AL71: -8808000 | AM71: -9512000 | AN71: -9910000 | AO71: -10331000 | AP71: -10497000 | AQ71: -11706000 | AR71: -2938000 | AS71: -4608000 | AT71: -5171000 | AU71: -2662000 | AV71: -5191000 | AW71: -7876000 | AX71: -10982000 | AY71: -15595000 | AZ71: -20296000 | BA71: -26755000 | BB71: -29667000 | BC71: -29771000 | BD71: -34167000 | BE71: -36605000 | BF71: -36623000 | BG71: -40426000 | BH71: -39430000 | BI71: -23055000 | BJ71: -24331000 | BK71: -30639000 | BL71: -49112000 | BM71: -941000 | BN71: -987000 | BO71: -659000 | BP71: -696000 | BQ71: -740000 | BR71: -794000 | BS71: -839000 | BT71: -883000 | BU71: -928000 | BV71: -973000 | BW71: -1009000 | BX71: -1054000 | BY71: -1108000 | BZ71: -1161000 | CA71: -1206000 | CB71: -1266000 | CC71: -1311000 | CD71: -1349000 | CE71: -1382000 | CF71: -2012000 | CG71: -2677000 | CH71: -3228000 | CI71: -3552000 | CJ71: -3044000 | CK71: -2839000
A72: OtherEquityAdjustments | B72: 1015000 | C72: 648000 | D72: 43000 | E72: -723000 | F72: -966000 | G72: -1002000 | H72: -1192000 | I72: -1435000 | J72: -1678000 | K72: -1921000 | L72: -2163000 | M72: -2406000 | N72: -2649000 | O72: -2892000 | P72: -3135000 | Q72: -3378000 | R72: -3621000 | S72: -3864000 | T72: -3207000 | U72: -3451000 | V72: -3695000 | W72: -3938000 | X72: -4181000 | Y72: -4383000 | Z72: -4584000 | AA72: -4789000 | AB72: -4990000 | AC72: -5206000 | AD72: -5406000 | AE72: -5607000 | AF72: -5807000 | AG72: -6013000 | AH72: -6214000 | AI72: -6569000 | AJ72: -7327000 | AK72: -8153000 | AL72: -8808000 | AM72: -9512000 | AN72: -9910000 | AO72: -10331000 | AP72: -10497000 | AQ72: -11706000 | AR72: -2938000
A73: OtherEquityInterest | BM73: 420000 | BN73: 420000 | BO73: 417000 | BP73: 413000 | BQ73: 390000 | BR73: -4799000 | BS73: -5510000 | BT73: -6197000 | BU73: -5922000 | BV73: -2705000 | BW73: -5258000 | BX73: -4709000 | BY73: -4725000 | BZ73: -1614000 | CA73: -4571000 | CB73: -4233000 | CC73: -3556000 | CE73: -2781000 | CF73: -2787000 | CG73: -2518000 | CH73: -131000 | CR73: 900000 | CS73: 357200000 | CU73: 285600000 | CV73: 311600000 | CW73: 280000000 | CY73: 240200000 | CZ73: 236900000 | DA73: 204400000 | DC73: 169000000 | DD73: 160700000 | DE73: 151300000 | DG73: 136500000 | DH73: 134000000 | DI73: 109400000 | DK73: 102400000 | DL73: -2400000 | DM73: 98500000 | DN73: 84300000 | DO73: 82900000 | DP73: 78800000 | DQ73: 70800000 | DR73: 70200000 | DS73: 61100000 | DT73: 59500000 | DU73: 58300000 | DV73: 55600000 | DW73: 54000000 | DX73: 53600000 | DY73: 26200000 | DZ73: 26300000 | EA73: 26200000 | EB73: 26200000 | EC73: 26100000 | ED73: 26100000 | EE73: 26100000 | EF73: 25900000 | EG73: 25800000 | EH73: 27400000 | EI73: 29400000 | EJ73: 29200000
A74: TotalCapitalization | B74: 13592920000 | C74: 12964018000 | D74: 12551171000 | E74: 12079534000 | F74: 10479191000 | G74: 9909086000 | H74: 10434054000 | I74: 10317227000 | J74: 10293900000 | K74: 10380635000 | L74: 10792213000 | M74: 11117092000 | N74: 11445072000 | O74: 11176675000 | P74: 9613938000 | Q74: 9410785000 | R74: 9322643000 | S74: 9304774000 | T74: 9280133000 | U74: 9258327000 | V74: 9155753000 | W74: 9098815000 | X74: 8730387000 | Y74: 8463723000 | Z74: 8370200000 | AA74: 8160971000 | AB74: 8116870000 | AC74: 8035062000 | AD74: 7969825000 | AE74: 8378046000 | AF74: 8347051000 | AG74: 8448925000 | AH74: 8180728000 | AI74: 7999863000 | AJ74: 8349465000 | AK74: 8009659000 | AL74: 7977210000 | AM74: 7838631000 | AN74: 8144981000 | AO74: 8148921000 | AP74: 8076614000 | AQ74: 8014202000 | AR74: 7756666000 | AS74: 7758229000 | AT74: 7697661000 | AU74: 7472352000 | AV74: 7286386000 | AW74: 7275073000 | AX74: 7152972000 | AY74: 7482253000 | AZ74: 7341549000 | BA74: 7104297000 | BB74: 7033651000 | BC74: 6936413000 | BD74: 6790013000 | BE74: 6960666000 | BF74: 7127561000 | BG74: 7033775000 | BH74: 6954651000 | BI74: 6935931000 | BJ74: 6944413000 | BK74: 6906728000 | BL74: 6982629000 | BM74: 2057150000 | BN74: 2007705000 | BO74: 2198280000 | BP74: 2238014000 | BQ74: 2020285000 | BR74: 1990757000 | BS74: 1958723000 | BT74: 1903262000 | BU74: 1984418000 | BV74: 1942927000 | BW74: 1898684000 | BX74: 1797885000 | BY74: 1749704000 | BZ74: 1842257000 | CA74: 1770017000 | CB74: 1674565000 | CC74: 1663775000 | CD74: 1618405000 | CE74: 1692849000 | CF74: 1638061000 | CG74: 1424743000 | CH74: 1381188000 | CI74: 1300334000 | CJ74: 1651465000 | CK74: 1629146000 | CL74: 1582527000 | CM74: 1216296000 | CN74: 1151728000 | CO74: 909746000 | CP74: 927121000 | CQ74: 863600000 | CR74: 838700000 | CS74: 788100000 | CT74: 726547000 | CU74: 652200000 | CV74: 644000000 | CW74: 597100000 | CX74: 585190000 | CY74: 518300000 | CZ74: 561100000 | DA74: 521200000 | DB74: 488111000 | DC74: 437100000 | DD74: 451700000 | DE74: 437700000 | DF74: 423289000 | DG74: 386500000 | DH74: 367500000 | DI74: 338500000 | DJ74: 328523000 | DK74: 290900000 | DL74: 274200000 | DM74: 261300000 | DN74: 246400000 | DO74: 225200000 | DP74: 212500000 | DQ74: 200700000 | DR74: 196800000 | DS74: 176000000 | DT74: 197600000 | DU74: 177200000 | DV74: 172200000 | DW74: 183800000 | DX74: 172700000 | DY74: 156000000 | DZ74: 150800000 | EA74: 183800000 | EB74: 179400000 | EC74: 166800000 | ED74: 147400000 | EE74: 175200000 | EF74: 174800000 | EG74: 157200000 | EH74: 158400000 | EI74: 161100000 | EJ74: 172300000
A75: PreferredStockEquity | CT75: 858000 | CX75: 858000 | DB75: 858000 | DF75: 858000 | DJ75: 858000
A76: CommonStockEquity | B76: 6297705000 | C76: 5935251000 | D76: 5541772000 | E76: 6093806000 | F76: 6188491000 | G76: 5961624000 | H76: 6261986000 | I76: 6189801000 | J76: 6137135000 | K76: 6249925000 | L76: 6661238000 | M76: 6985519000 | N76: 7356071000 | O76: 7209454000 | P76: 6702500000 | Q76: 6648295000 | R76: 6749160000 | S76: 6572669000 | T76: 6417393000 | U76: 6355888000 | V76: 6378942000 | W76: 6236318000 | X76: 6125774000 | Y76: 5744155000 | Z76: 5687095000 | AA76: 5528881000 | AB76: 5406294000 | AC76: 5361852000 | AD76: 5413361000 | AE76: 5388383000 | AF76: 5377876000 | AG76: 5343593000 | AH76: 5418934000 | AI76: 5385858000 | AJ76: 5710038000 | AK76: 5343637000 | AL76: 5095993000 | AM76: 4832227000 | AN76: 5402193000 | AO76: 5274954000 | AP76: 5231476000 | AQ76: 5178899000 | AR76: 4985330000 | AS76: 4734862000 | AT76: 4810410000 | AU76: 4591432000 | AV76: 4668495000 | AW76: 4554012000 | AX76: 4373564000 | AY76: 4219656000 | AZ76: 4054479000 | BA76: 3817390000 | BB76: 3682844000 | BC76: 3536526000 | BD76: 3390298000 | BE76: 2855414000 | BF76: 3016538000 | BG76: 2916585000 | BH76: 2831695000 | BI76: 2763464000 | BJ76: 2766803000 | BK76: 2730607000 | BL76: 2703873000 | BM76: 1796777000 | BN76: 1745747000 | BO76: 1702941000 | BP76: 1721477000 | BQ76: 1686814000 | BR76: 1720795000 | BS76: 1614287000 | BT76: 1647817000 | BU76: 1727966000 | BV76: 1684465000 | BW76: 1577490000 | BX76: 1538876000 | BY76: 1488083000 | BZ76: 1576920000 | CA76: 1501660000 | CB76: 1402145000 | CC76: 1337747000 | CD76: 1288068000 | CE76: 1190351000 | CF76: 1131354000 | CG76: 1088660000 | CH76: 1041718000 | CI76: 953160000 | CJ76: 916030000 | CK76: 895620000 | CL76: 861763000 | CM76: 1005389000 | CN76: 946359000 | CO76: 907506000 | CP76: 925921000 | CQ76: 862100000 | CR76: 837200000 | CS76: 787500000 | CT76: 724903000 | CU76: 652000000 | CV76: 643800000 | CW76: 596700000 | CX76: 583038000 | CY76: 516900000 | CZ76: 559500000 | DA76: 519400000 | DB76: 484671000 | DC76: 434400000 | DD76: 449600000 | DE76: 435400000 | DF76: 419153000 | DG76: 383100000 | DH76: 363900000 | DI76: 334600000 | DJ76: 322898000 | DK76: 286400000 | DL76: 269500000 | DM76: 256500000 | DN76: 240700000 | DO76: 219400000 | DP76: 206500000 | DQ76: 194600000 | DR76: 189800000 | DS76: 168900000 | DT76: 160300000 | DU76: 153700000 | DV76: 151000000 | DW76: 138100000 | DX76: 134400000 | DY76: 131900000 | DZ76: 131700000 | EA76: 123600000 | EB76: 121800000 | EC76: 120100000 | ED76: 120600000 | EE76: 114300000 | EF76: 112300000 | EG76: 111600000 | EH76: 109500000 | EI76: 108800000 | EJ76: 108000000
A77: CapitalLeaseObligations | B77: 10740626000 | C77: 10711586000 | D77: 10651700000 | E77: 10452102000 | F77: 10301392000 | G77: 10164217000 | H77: 10074268000 | I77: 9965759000 | J77: 9789557000 | K77: 9600811000 | L77: 9459467000 | M77: 9329395000 | N77: 9140617000 | O77: 8947813000 | P77: 8784488000 | Q77: 8629427000 | R77: 8395946000 | S77: 8133414000
A78: NetTangibleAssets | B78: 759416000 | C78: 396962000 | D78: 3483000 | E78: 555517000 | F78: 650202000 | G78: 423315000 | H78: 723647000 | I78: 651432000 | J78: 598736000 | K78: 711496000 | L78: 1122779000 | M78: 1447030000 | N78: 1817551000 | O78: 1670904000 | P78: 1163905000 | Q78: 1109647000 | R78: 1210460000 | S78: 1033916000 | T78: 878587000 | U78: 817029000 | V78: 840031000 | W78: 697354000 | X78: 586757000 | Y78: 205085000 | Z78: 147969000 | AA78: -10305000 | AB78: -132954000 | AC78: -177471000 | AD78: -126044000 | AE78: -151110000 | AF78: -161707000 | AG78: -196106000 | AH78: -120896000 | AI78: -154159000 | AJ78: 169579000 | AK78: -197603000 | AL78: -446500000 | AM78: -711960000 | AN78: -144041000 | AO78: -273712000 | AP78: -319934000 | AQ78: -375689000 | AR78: -572802000 | AS78: -827134000 | AT78: -755678000 | AU78: -979023000 | AV78: -906048000 | AW78: -1025310000 | AX78: -1210798000 | AY78: -1370222000 | AZ78: -1541032000 | BA78: -1784033000 | BB78: -1924735000 | BC78: -2078236000 | BD78: -2232574000 | BE78: -2776455000 | BF78: -2625247000 | BG78: -2736429000 | BH78: -2832452000 | BI78: -2910462000 | BJ78: -2926075000 | BK78: -2973413000 | BL78: -3011614000 | BM78: 1796777000 | BN78: 1745747000 | BO78: 1702941000 | BP78: 1721477000 | BQ78: 1686814000 | BR78: 1720795000 | BS78: 1614287000 | BT78: 1647817000 | BU78: 1727966000 | BV78: 1684465000 | BW78: 1577490000 | BX78: 1538876000 | BY78: 1488083000 | BZ78: 1576920000 | CA78: 1501660000 | CB78: 1402145000 | CC78: 1337747000 | CD78: 1288068000 | CE78: 1190351000 | CF78: 1131354000 | CG78: 1088660000 | CH78: 1041718000 | CI78: 953160000 | CJ78: 916030000 | CK78: 895620000 | CL78: 861763000 | CM78: 1005389000 | CN78: 946359000 | CO78: 907506000 | CP78: 925921000 | CQ78: 862100000 | CR78: 837200000 | CS78: 787500000 | CT78: 725761000 | CU78: 652000000 | CV78: 643800000 | CW78: 596700000 | CX78: 583896000 | CY78: 516900000 | CZ78: 559500000 | DA78: 519400000 | DB78: 485529000 | DC78: 434400000 | DD78: 449600000 | DE78: 435400000 | DF78: 420011000 | DG78: 383100000 | DH78: 363900000 | DI78: 334600000 | DJ78: 323756000 | DK78: 286400000 | DL78: 269500000 | DM78: 256500000 | DN78: 240700000 | DO78: 219400000 | DP78: 206500000 | DQ78: 194600000 | DR78: 189800000 | DS78: 168900000 | DT78: 160300000 | DU78: 153700000 | DV78: 151000000 | DW78: 138100000 | DX78: 134400000 | DY78: 131900000 | DZ78: 131700000 | EA78: 123600000 | EB78: 121800000 | EC78: 120100000 | ED78: 120600000 | EE78: 114300000 | EF78: 112300000 | EG78: 111600000 | EH78: 109500000 | EI78: 108800000 | EJ78: 108000000
A79: WorkingCapital | B79: 2380057000 | C79: 1954781000 | D79: 1693241000 | E79: 1514369000 | F79: 116106000 | G79: -214971000 | H79: 324486000 | I79: 441335000 | J79: 513634000 | K79: 726347000 | L79: 1203436000 | M79: 1647221000 | N79: 2186220000 | O79: 2149255000 | P79: 634308000 | Q79: 562504000 | R79: 606868000 | S79: 627053000 | T79: 1647163000 | U79: 1648162000 | V79: 1602282000 | W79: 1640704000 | X79: 1282974000 | Y79: 1215528000 | Z79: 1173236000 | AA79: 1056908000 | AB79: 1054966000 | AC79: 1008773000 | AD79: 988645000 | AE79: 1465752000 | AF79: 1436814000 | AG79: 1497192000 | AH79: 1270084000 | AI79: 1171961000 | AJ79: 1544869000 | AK79: 1168286000 | AL79: 1171213000 | AM79: 1080028000 | AN79: 1393636000 | AO79: 1151253000 | AP79: 1124553000 | AQ79: 1124074000 | AR79: 938566000 | AS79: 984353000 | AT79: 987761000 | AU79: 862482000 | AV79: 765172000 | AW79: 820634000 | AX79: 745830000 | AY79: 1119667000 | AZ79: 1002452000 | BA79: 862443000 | BB79: 815524000 | BC79: 732538000 | BD79: 638949000 | BE79: 806381000 | BF79: 979954000 | BG79: 869486000 | BH79: 794890000 | BI79: 693640000 | BJ79: 688084000 | BK79: 640400000 | BL79: 659503000 | BM79: 1035884000 | BN79: 909877000 | BO79: 969488000 | BP79: 1009228000 | BQ79: 829263000 | BR79: 829128000 | BS79: 834710000 | BT79: 829295000 | BU79: 935417000 | BV79: 905210000 | BW79: 873575000 | BX79: 805773000 | BY79: 776241000 | BZ79: 908413000 | CA79: 838623000 | CB79: 733425000 | CC79: 714783000 | CD79: 659407000 | CE79: 717118000 | CF79: 662967000 | CG79: 477665000 | CH79: 422496000 | CI79: 178009000 | CJ79: 623820000 | CK79: 615788000 | CL79: 586992000 | CM79: 756211000 | CN79: 740795000 | CO79: 583966000 | CP79: 623238000 | CQ79: 540200000 | CR79: 543500000 | CS79: 486400000 | CT79: 423783000 | CU79: 368900000 | CV79: 388700000 | CW79: 358800000 | CX79: 358998000 | CY79: 280000000 | CZ79: 340200000 | DA79: 329800000 | DB79: 280134000 | DC79: 256200000 | DD79: 287600000 | DE79: 279100000 | DF79: 262529000 | DG79: 230300000 | DH79: 225500000 | DI79: 206700000 | DJ79: 201190000 | DK79: 180900000 | DL79: 178900000 | DM79: 177700000 | DN79: 166800000 | DO79: 150500000 | DP79: 143900000 | DQ79: 139000000 | DR79: 138700000 | DS79: 122600000 | DT79: 149100000 | DU79: 132000000 | DV79: 130000000 | DW79: 142900000 | DX79: 133300000 | DY79: 117800000 | DZ79: 113100000 | EA79: 145000000 | EB79: 141600000 | EC79: 129300000 | ED79: 110100000 | EE79: 138800000 | EF79: 142000000 | EG79: 130200000 | EH79: 129000000 | EI79: 129000000 | EJ79: 139200000
A80: InvestedCapital | B80: 13592920000 | C80: 13214018000 | D80: 12551171000 | E80: 12079534000 | F80: 11379826000 | G80: 10809721000 | H80: 10434054000 | I80: 10317227000 | J80: 10293900000 | K80: 10380635000 | L80: 10792213000 | M80: 11117092000 | N80: 11445072000 | O80: 11177255000 | P80: 9614493000 | Q80: 9411340000 | R80: 9323198000 | S80: 9305329000 | T80: 9282083000 | U80: 9260256000 | V80: 9157662000 | W80: 9100704000 | X80: 9131732000 | Y80: 8865255000 | Z80: 8771602000 | AA80: 8562159000 | AB80: 8617820000 | AC80: 8536542000 | AD80: 8471373000 | AE80: 8379572000 | AF80: 8348430000 | AG80: 8450283000 | AH80: 8282063000 | AI80: 8101172000 | AJ80: 8450623000 | AK80: 8110700000 | AL80: 8078223000 | AM80: 7939620000 | AN80: 8220947000 | AO80: 8199866000 | AP80: 8102541000 | AQ80: 8015111000 | AR80: 7757558000 | AS80: 7759120000 | AT80: 7698005000 | AU80: 7472811000 | AV80: 7286976000 | AW80: 7275836000 | AX80: 7153935000 | AY80: 7483292000 | AZ80: 7342706000 | BA80: 7105655000 | BB80: 7035246000 | BC80: 6939960000 | BD80: 6793684000 | BE80: 6987428000 | BF80: 7154358000 | BG80: 7053301000 | BH80: 6968809000 | BI80: 6944386000 | BJ80: 6947412000 | BK80: 6909558000 | BL80: 6985875000 | BM80: 2064336000 | BN80: 2015785000 | BO80: 2206753000 | BP80: 2247181000 | BQ80: 2029085000 | BR80: 1999542000 | BS80: 1967587000 | BT80: 1912823000 | BU80: 1995155000 | BV80: 1955787000 | BW80: 1913388000 | BX80: 1813841000 | BY80: 1766584000 | BZ80: 1858927000 | CA80: 1787312000 | CB80: 1691522000 | CC80: 1680335000 | CD80: 1634614000 | CE80: 1708683000 | CF80: 1653193000 | CG80: 1820620000 | CH80: 1776863000 | CI80: 1691423000 | CJ80: 1659407000 | CK80: 1636229000 | CL80: 1591562000 | CM80: 1281287000 | CN80: 1176054000 | CO80: 1092700000 | CP80: 928354000 | CQ80: 1044900000 | CR80: 988600000 | CS80: 902400000 | CT80: 726414000 | CU80: 912500000 | CV80: 805600000 | CW80: 717500000 | CX80: 607715000 | CY80: 713500000 | CZ80: 620700000 | DA80: 573100000 | DB80: 527752000 | DC80: 623900000 | DD80: 528300000 | DE80: 544200000 | DF80: 496113000 | DG80: 588100000 | DH80: 493500000 | DI80: 436400000 | DJ80: 358706000 | DK80: 404900000 | DL80: 337500000 | DM80: 289600000 | DN80: 265700000 | DO80: 294300000 | DP80: 247800000 | DQ80: 227000000 | DR80: 208100000 | DS80: 234300000 | DT80: 198900000 | DU80: 178500000 | DV80: 173500000 | DW80: 194100000 | DX80: 174000000 | DY80: 157600000 | DZ80: 152400000 | EA80: 194200000 | EB80: 187200000 | EC80: 174600000 | ED80: 155200000 | EE80: 183000000 | EF80: 178600000 | EG80: 158000000 | EH80: 174700000 | EI80: 167600000 | EJ80: 178800000
A81: TangibleBookValue | B81: 759416000 | C81: 396962000 | D81: 3483000 | E81: 555517000 | F81: 650202000 | G81: 423315000 | H81: 723647000 | I81: 651432000 | J81: 598736000 | K81: 711496000 | L81: 1122779000 | M81: 1447030000 | N81: 1817551000 | O81: 1670904000 | P81: 1163905000 | Q81: 1109647000 | R81: 1210460000 | S81: 1033916000 | T81: 878587000 | U81: 817029000 | V81: 840031000 | W81: 697354000 | X81: 586757000 | Y81: 205085000 | Z81: 147969000 | AA81: -10305000 | AB81: -132954000 | AC81: -177471000 | AD81: -126044000 | AE81: -151110000 | AF81: -161707000 | AG81: -196106000 | AH81: -120896000 | AI81: -154159000 | AJ81: 169579000 | AK81: -197603000 | AL81: -446500000 | AM81: -711960000 | AN81: -144041000 | AO81: -273712000 | AP81: -319934000 | AQ81: -375689000 | AR81: -572802000 | AS81: -827134000 | AT81: -755678000 | AU81: -979023000 | AV81: -906048000 | AW81: -1025310000 | AX81: -1210798000 | AY81: -1370222000 | AZ81: -1541032000 | BA81: -1784033000 | BB81: -1924735000 | BC81: -2078236000 | BD81: -2232574000 | BE81: -2776455000 | BF81: -2625247000 | BG81: -2736429000 | BH81: -2832452000 | BI81: -2910462000 | BJ81: -2926075000 | BK81: -2973413000 | BL81: -3011614000 | BM81: 1796777000 | BN81: 1745747000 | BO81: 1702941000 | BP81: 1721477000 | BQ81: 1686814000 | BR81: 1720795000 | BS81: 1614287000 | BT81: 1647817000 | BU81: 1727966000 | BV81: 1684465000 | BW81: 1577490000 | BX81: 1538876000 | BY81: 1488083000 | BZ81: 1576920000 | CA81: 1501660000 | CB81: 1402145000 | CC81: 1337747000 | CD81: 1288068000 | CE81: 1190351000 | CF81: 1131354000 | CG81: 1088660000 | CH81: 1041718000 | CI81: 953160000 | CJ81: 916030000 | CK81: 895620000 | CL81: 861763000 | CM81: 1005389000 | CN81: 946359000 | CO81: 907506000 | CP81: 925921000 | CQ81: 862100000 | CR81: 837200000 | CS81: 787500000 | CT81: 724903000 | CU81: 652000000 | CV81: 643800000 | CW81: 596700000 | CX81: 583038000 | CY81: 516900000 | CZ81: 559500000 | DA81: 519400000 | DB81: 484671000 | DC81: 434400000 | DD81: 449600000 | DE81: 435400000 | DF81: 419153000 | DG81: 383100000 | DH81: 363900000 | DI81: 334600000 | DJ81: 322898000 | DK81: 286400000 | DL81: 269500000 | DM81: 256500000 | DN81: 240700000 | DO81: 219400000 | DP81: 206500000 | DQ81: 194600000 | DR81: 189800000 | DS81: 168900000 | DT81: 160300000 | DU81: 153700000 | DV81: 151000000 | DW81: 138100000 | DX81: 134400000 | DY81: 131900000 | DZ81: 131700000 | EA81: 123600000 | EB81: 121800000 | EC81: 120100000 | ED81: 120600000 | EE81: 114300000 | EF81: 112300000 | EG81: 111600000 | EH81: 109500000 | EI81: 108800000 | EJ81: 108000000
A82: TotalDebt | B82: 18035841000 | C82: 17990353000 | D82: 17661099000 | E82: 16437830000 | F82: 15492727000 | G82: 15012314000 | H82: 14246336000 | I82: 14093185000 | J82: 13946322000 | K82: 13731521000 | L82: 13590442000 | M82: 13460968000 | N82: 13229618000 | O82: 12915614000 | P82: 11696481000 | Q82: 11392472000 | R82: 10969984000 | S82: 10866074000 | T82: 2864690000 | U82: 2904368000 | V82: 2778720000 | W82: 2864386000 | X82: 3005958000 | Y82: 3121100000 | Z82: 3084507000 | AA82: 3033278000 | AB82: 3211526000 | AC82: 3174690000 | AD82: 3058012000 | AE82: 2991189000 | AF82: 2970554000 | AG82: 3106690000 | AH82: 2863129000 | AI82: 2715314000 | AJ82: 2740585000 | AK82: 2767063000 | AL82: 2982230000 | AM82: 3107393000 | AN82: 2818754000 | AO82: 2924912000 | AP82: 2871065000 | AQ82: 2836212000 | AR82: 2772228000 | AS82: 3024258000 | AT82: 2887595000 | AU82: 2881379000 | AV82: 2618481000 | AW82: 2721824000 | AX82: 2780371000 | AY82: 3263636000 | AZ82: 3288227000 | BA82: 3288265000 | BB82: 3352402000 | BC82: 3403434000 | BD82: 3403386000 | BE82: 4132014000 | BF82: 4137820000 | BG82: 4136716000 | BH82: 4137114000 | BI82: 4180922000 | BJ82: 4180609000 | BK82: 4178951000 | BL82: 4282002000 | BM82: 267559000 | BN82: 270038000 | BO82: 503812000 | BP82: 525704000 | BQ82: 342271000 | BR82: 278747000 | BS82: 353300000 | BT82: 265006000 | BU82: 267189000 | BV82: 271322000 | BW82: 335898000 | BX82: 274965000 | BY82: 278501000 | BZ82: 282007000 | CA82: 285652000 | CB82: 289377000 | CC82: 342588000 | CD82: 346546000 | CE82: 518332000 | CF82: 521839000 | CG82: 731960000 | CH82: 735145000 | CI82: 738263000 | CJ82: 743377000 | CK82: 740609000 | CL82: 729799000 | CM82: 275898000 | CN82: 229695000 | CO82: 185194000 | CP82: 2433000 | CQ82: 182800000 | CR82: 151400000 | CS82: 114900000 | CT82: 1511000 | CU82: 260500000 | CV82: 161800000 | CW82: 120800000 | CX82: 24677000 | CY82: 196600000 | CZ82: 61200000 | DA82: 53700000 | DB82: 43081000 | DC82: 189500000 | DD82: 78700000 | DE82: 108800000 | DF82: 76960000 | DG82: 205000000 | DH82: 129600000 | DI82: 101800000 | DJ82: 35808000 | DK82: 118500000 | DL82: 68000000 | DM82: 33100000 | DN82: 25000000 | DO82: 74900000 | DP82: 41300000 | DQ82: 32400000 | DR82: 18300000 | DS82: 65400000 | DT82: 38600000 | DU82: 24800000 | DV82: 22500000 | DW82: 56000000 | DX82: 39600000 | DY82: 25700000 | DZ82: 20700000 | EA82: 70600000 | EB82: 65400000 | EC82: 54500000 | ED82: 34600000 | EE82: 68700000 | EF82: 66300000 | EG82: 46400000 | EH82: 65200000 | EI82: 58800000 | EJ82: 70800000
A83: NetDebt | B83: 6942197000 | C83: 6965703000 | D83: 6627823000 | E83: 5622997000 | F83: 4865072000 | G83: 4512484000 | H83: 3827239000 | I83: 3638764000 | J83: 3843099000 | K83: 3442655000 | L83: 2754398000 | M83: 1932130000 | N83: 1129397000 | O83: 1293889000 | P83: 2671673000 | Q83: 2486969000 | R83: 2314470000 | S83: 2461549000 | T83: 2629203000 | U83: 2643680000 | V83: 2513432000 | W83: 2580416000 | X83: 2738517000 | Y83: 2894908000 | Z83: 2870334000 | AA83: 2827301000 | AB83: 3023611000 | AC83: 2974454000 | AD83: 2872979000 | AE83: 2803502000 | AF83: 2812607000 | AG83: 2924176000 | AH83: 2682604000 | AI83: 2490198000 | AJ83: 2160762000 | AK83: 2550908000 | AL83: 2809756000 | AM83: 2941063000 | AN83: 2313188000 | AO83: 2759195000 | AP83: 2701845000 | AQ83: 2680686000 | AR83: 2631419000 | AS83: 2881678000 | AT83: 2753438000 | AU83: 2748849000 | AV83: 2492355000 | AW83: 2603244000 | AX83: 2667321000 | AY83: 2661173000 | AZ83: 2790781000 | BA83: 3050359000 | BB83: 3070981000 | BC83: 3180725000 | BD83: 3181310000 | BE83: 3794995000 | BF83: 3622445000 | BG83: 3702132000 | BH83: 3759119000 | BI83: 4030332000 | BJ83: 3918979000 | BK83: 4063047000 | BL83: 4181793000 | BM83: 63142000 | BN83: 80750000 | BO83: 412898000 | BP83: 439352000 | BQ83: 270395000 | BR83: 78138000 | BS83: 260531000 | BT83: 119056000 | BU83: 30666000 | BV83: 38492000 | BW83: 290066000 | BX83: 173500000 | BY83: 21618000 | CA83: 147182000 | CB83: 187101000 | CC83: 266642000 | CD83: 225228000 | CE83: 481231000 | CF83: 482322000 | CG83: 444536000 | CH83: 473620000 | CI83: 663444000 | CJ83: 661747000 | CK83: 579715000 | CL83: 567489000 | CM83: 262818000 | CN83: 215655000 | CO83: 156797000 | CQ83: 147100000 | CR83: 126100000 | CS83: 89300000 | CU83: 242200000 | CV83: 128600000 | CW83: 83600000 | CX83: 17549000 | CY83: 183400000 | CZ83: 36300000 | DA83: 20300000 | DB83: 36518000 | DC83: 180700000 | DD83: 65700000 | DE83: 89400000 | DF83: 72616000 | DG83: 200900000 | DH83: 115600000 | DI83: 60700000 | DJ83: 2763000 | DK83: 92900000 | DL83: 41200000 | DM83: 2800000 | DO83: 41700000 | DP83: 18700000 | DQ83: 15000000 | DS83: 36100000 | DT83: 20500000 | DU83: 10900000 | DV83: 14600000 | DW83: 48400000 | DX83: 30800000 | DY83: 19800000 | DZ83: 16800000 | EA83: 58000000 | EB83: 58100000 | EC83: 46100000 | ED83: 28100000 | EE83: 66000000 | EF83: 62800000 | EG83: 40700000 | EH83: 57900000 | EI83: 53600000 | EJ83: 64000000
A84: ShareIssued | B84: 219470000 | C84: 219336000 | D84: 219105000 | E84: 223575000 | F84: 225567000 | G84: 226997000 | H84: 230016000 | I84: 231706000 | J84: 233305000 | K84: 236205000 | L84: 240785000 | M84: 245000000 | N84: 249033000 | O84: 251722000 | P84: 251936000 | Q84: 254600000 | R84: 257068000 | S84: 258322000 | T84: 259511000 | U84: 262884331 | V84: 265534401 | W84: 267557504 | X84: 268733000 | Y84: 271563597 | Z84: 273259005 | AA84: 274225125 | AB84: 275212000 | AC84: 276264260 | AD84: 281744265 | AE84: 283778285 | AF84: 286694000 | AG84: 290934510 | AH84: 294659578 | AI84: 297108500 | AJ84: 303447000 | AK84: 303425920 | AL84: 303397106 | AM84: 303303655 | AN84: 317058000 | AO84: 320255172 | AP84: 323608057 | AQ84: 327395122 | AR84: 327069000 | AS84: 328712549 | AT84: 333695858 | AU84: 332326972 | AV84: 338089000 | AW84: 342263844 | AX84: 341532297 | AY84: 341535481 | AZ84: 341507000 | BA84: 341101600 | BB84: 341038564 | BC84: 341004089 | BD84: 340586000 | BE84: 340644825 | BF84: 340644825 | BG84: 340644825 | BH84: 340644825 | BI84: 340644825 | BJ84: 340644825 | BK84: 340644825 | BL84: 340644825 | BM84: 340644825 | BN84: 340644825 | BO84: 340644825 | BP84: 340644825 | BQ84: 340644825 | BR84: 340644825 | BS84: 340644825 | BT84: 340644825 | BU84: 340644825 | BV84: 340644825 | BW84: 340644825 | BX84: 340644825 | BY84: 340644825 | BZ84: 340644825 | CA84: 340644825 | CB84: 340644825 | CC84: 340644825 | CD84: 340644825 | CE84: 340644825 | CF84: 340644825 | CG84: 340644825 | CH84: 340644825 | CI84: 340644825 | CJ84: 340644825 | CK84: 340644825 | CL84: 340644825 | CM84: 340644825 | CN84: 340644825 | CO84: 340644825 | CP84: 340644825 | CQ84: 340644825 | CR84: 340644825 | CS84: 340644825 | CT84: 340644825 | CU84: 340644825 | CV84: 340644825 | CW84: 340644825 | CX84: 340644825 | CY84: 340644825 | CZ84: 340644825 | DA84: 340644825 | DB84: 340644825 | DC84: 340644825 | DD84: 340644825 | DE84: 340644825 | DF84: 340644825 | DG84: 340644825 | DH84: 340644825 | DI84: 340644825 | DJ84: 340644825 | DK84: 340644825 | DL84: 340644825 | DM84: 340644825 | DN84: 340644825 | DO84: 340644825 | DP84: 340644825 | DQ84: 340644825 | DR84: 340644825 | DS84: 340644825 | DT84: 340644825 | DU84: 340644825 | DV84: 340644825 | DW84: 340644825 | DX84: 340644825 | DY84: 340644825 | DZ84: 340644825 | EA84: 340644825 | EB84: 340644825 | EC84: 340644825 | ED84: 340644825 | EE84: 340644825 | EF84: 340644825 | EG84: 340644825 | EH84: 340644825 | EI84: 340644825 | EJ84: 340644825
A85: OrdinarySharesNumber | B85: 219470000 | C85: 219336000 | D85: 219105000 | E85: 223575000 | F85: 225567000 | G85: 226997000 | H85: 230016000 | I85: 231706000 | J85: 233305000 | K85: 236205000 | L85: 240785000 | M85: 245000000 | N85: 249033000 | O85: 251722000 | P85: 251936000 | Q85: 254600000 | R85: 257068000 | S85: 258322000 | T85: 259511000 | U85: 262884331 | V85: 265534401 | W85: 267557504 | X85: 268733000 | Y85: 271563597 | Z85: 273259005 | AA85: 274225125 | AB85: 275212000 | AC85: 276264260 | AD85: 281744265 | AE85: 283778285 | AF85: 286694000 | AG85: 290934510 | AH85: 294659578 | AI85: 297108500 | AJ85: 303447000 | AK85: 303425920 | AL85: 303397106 | AM85: 303303655 | AN85: 317058000 | AO85: 320255172 | AP85: 323608057 | AQ85: 327395122 | AR85: 327069000 | AS85: 328712549 | AT85: 333695858 | AU85: 332326972 | AV85: 338089000 | AW85: 342263844 | AX85: 341532297 | AY85: 341535481 | AZ85: 341507000 | BA85: 341101600 | BB85: 341038564 | BC85: 341004089 | BD85: 340586000 | BE85: 340644825 | BF85: 340644825 | BG85: 340644825 | BH85: 340644825 | BI85: 340644825 | BJ85: 340644825 | BK85: 340644825 | BL85: 340644825 | BM85: 340644825 | BN85: 340644825 | BO85: 340644825 | BP85: 340644825 | BQ85: 340644825 | BR85: 340644825 | BS85: 340644825 | BT85: 340644825 | BU85: 340644825 | BV85: 340644825 | BW85: 340644825 | BX85: 340644825 | BY85: 340644825 | BZ85: 340644825 | CA85: 340644825 | CB85: 340644825 | CC85: 340644825 | CD85: 340644825 | CE85: 340644825 | CF85: 340644825 | CG85: 340644825 | CH85: 340644825 | CI85: 340644825 | CJ85: 340644825 | CK85: 340644825 | CL85: 340644825 | CM85: 340644825 | CN85: 340644825 | CO85: 340644825 | CP85: 340644825 | CQ85: 340644825 | CR85: 340644825 | CS85: 340644825 | CT85: 340644825 | CU85: 340644825 | CV85: 340644825 | CW85: 340644825 | CX85: 340644825 | CY85: 340644825 | CZ85: 340644825 | DA85: 340644825 | DB85: 340644825 | DC85: 340644825 | DD85: 340644825 | DE85: 340644825 | DF85: 340644825 | DG85: 340644825 | DH85: 340644825 | DI85: 340644825 | DJ85: 340644825 | DK85: 340644825 | DL85: 340644825 | DM85: 340644825 | DN85: 340644825 | DO85: 340644825 | DP85: 340644825 | DQ85: 340644825 | DR85: 340644825 | DS85: 340644825 | DT85: 340644825 | DU85: 340644825 | DV85: 340644825 | DW85: 340644825 | DX85: 340644825 | DY85: 340644825 | DZ85: 340644825 | EA85: 340644825 | EB85: 340644825 | EC85: 340644825 | ED85: 340644825 | EE85: 340644825 | EF85: 340644825 | EG85: 340644825 | EH85: 340644825 | EI85: 340644825 | EJ85: 340644825

Sheet DG_quarterly_pl
A1: name | B1: ttm | C1: 45138 | D1: 45046 | E1: 44957 | F1: 44865 | G1: 44773 | H1: 44681 | I1: 44592 | J1: 44500 | K1: 44408 | L1: 44316 | M1: 44227 | N1: 44135 | O1: 44043 | P1: 43951 | Q1: 43861 | R1: 43769 | S1: 43677 | T1: 43585 | U1: 43496 | V1: 43404 | W1: 43312 | X1: 43220 | Y1: 43131 | Z1: 43039 | AA1: 42947 | AB1: 42855 | AC1: 42766 | AD1: 42674 | AE1: 42582 | AF1: 42490 | AG1: 42400 | AH1: 42308 | AI1: 42216 | AJ1: 42124 | AK1: 42035 | AL1: 41943 | AM1: 41851 | AN1: 41759 | AO1: 41670 | AP1: 41578 | AQ1: 41486 | AR1: 41394 | AS1: 41305 | AT1: 41213 | AU1: 41121 | AV1: 41029 | AW1: 40939 | AX1: 40847 | AY1: 40755 | AZ1: 40663 | BA1: 40574 | BB1: 40482 | BC1: 40390 | BD1: 40298 | BE1: 40209 | BF1: 40117 | BG1: 40025 | BH1: 39933 | BI1: 39844 | BJ1: 39752 | BK1: 39660 | BL1: 39568 | BM1: 39478 | BN1: 39386 | BO1: 39294 | BP1: 39202 | BQ1: 39113 | BR1: 39021 | BS1: 38929 | BT1: 38837 | BU1: 38748 | BV1: 38656 | BW1: 38564 | BX1: 38472 | BY1: 38383 | BZ1: 38291 | CA1: 38199 | CB1: 38107 | CC1: 38017 | CD1: 37925 | CE1: 37833 | CF1: 37741 | CG1: 37652 | CH1: 37560 | CI1: 37468 | CJ1: 37376 | CK1: 37287 | CL1: 37195 | CM1: 37103 | CN1: 37011 | CO1: 36922 | CP1: 36830 | CQ1: 36738 | CR1: 36646 | CS1: 36556 | CT1: 36464 | CU1: 36372 | CV1: 36280 | CW1: 36191 | CX1: 36099 | CY1: 36007 | CZ1: 35915 | DA1: 35826 | DB1: 35734 | DC1: 35642 | DD1: 35550 | DE1: 35461 | DF1: 35369 | DG1: 35277 | DH1: 35185 | DI1: 35095 | DJ1: 35003 | DK1: 34911 | DL1: 34819 | DM1: 34730 | DN1: 34638 | DO1: 34546 | DP1: 34454 | DQ1: 34365 | DR1: 34273 | DS1: 34181 | DT1: 34089 | DU1: 34000 | DV1: 33908 | DW1: 33816 | DX1: 33724 | DY1: 33634 | DZ1: 33542 | EA1: 33450 | EB1: 33358 | EC1: 33269 | ED1: 33177 | EE1: 33085 | EF1: 32993 | EG1: 32904 | EH1: 32812 | EI1: 32720 | EJ1: 32628 | EK1: 32539 | EL1: 32447 | EM1: 32355 | EN1: 32263 | EO1: 32142 | EP1: 32050 | EQ1: 31958 | ER1: 31867 | ES1: 31777 | ET1: 31685 | EU1: 31593 | EV1: 31502 | EW1: 31412 | EX1: 31320
A2: TotalRevenue | B2: 38806811000 | C2: 9796181000 | D2: 9342832000 | E2: 10202907000 | F2: 9464891000 | G2: 9425713000 | H2: 8751352000 | I2: 8651448000 | J2: 8517839000 | K2: 8650198000 | L2: 8400964000 | M2: 8414524000 | N2: 8199625000 | O2: 8684241000 | P2: 8448449000 | Q2: 7157642000 | R2: 6991393000 | S2: 6981753000 | T2: 6623185000 | U2: 6649809000 | V2: 6417462000 | W2: 6443309000 | X2: 6114463000 | Y2: 6129431000 | Z2: 5903606000 | AA2: 5828305000 | AB2: 5609625000 | AC2: 6009246000 | AD2: 5320029000 | AE2: 5391891000 | AF2: 5265432000 | AG2: 5286938000 | AH2: 5067048000 | AI2: 5095904000 | AJ2: 4918672000 | AK2: 4939059000 | AL2: 4724409000 | AM2: 4724039000 | AN2: 4522081000 | AO2: 4493945000 | AP2: 4381838000 | AQ2: 4394651000 | AR2: 4233733000 | AS2: 4207621000 | AT2: 3964647000 | AU2: 3948655000 | AV2: 3901205000 | AW2: 4185073000 | AX2: 3595224000 | AY2: 3575194000 | AZ2: 3451697000 | BA2: 3486104000 | BB2: 3223427000 | BC2: 3214155000 | BD2: 3111314000 | BE2: 3185785000 | BF2: 2928751000 | BG2: 2901907000 | BH2: 2779937000 | BI2: 2845848000 | BJ2: 2598938000 | BK2: 2609384000 | BL2: 2403498000 | BM2: 2559573000 | BN2: 2312842000 | BO2: 2347564000 | BP2: 2275267000 | BQ2: 2553986000 | BR2: 2213396000 | BS2: 2251053000 | BT2: 2151387000 | BU2: 2480504000 | BV2: 2057888000 | BW2: 2066016000 | BX2: 1977829000 | BY2: 2197538000 | BZ2: 1879187000 | CA2: 1836243000 | CB2: 1747959000 | CC2: 1966488000 | CD2: 1685346000 | CE2: 1651094000 | CF2: 1569064000 | CG2: 1759563000 | CH2: 1497702000 | CI2: 1453727000 | CJ2: 1389412000 | CK2: 1586012000 | CL2: 1309125000 | CM2: 1225254000 | CN2: 1202504000 | CO2: 1441714000 | CP2: 1094360000 | CQ2: 1017418000 | CR2: 997079000 | CS2: 1177764000 | CT2: 950400000 | CU2: 915200000 | CV2: 844600000 | CW2: 992989000 | CX2: 781400000 | CY2: 741400000 | CZ2: 705300000 | DA2: 861125000 | DB2: 649400000 | DC2: 596800000 | DD2: 520000000 | DE2: 675198000 | DF2: 509000000 | DG2: 494400000 | DH2: 455900000 | DI2: 575388000 | DJ2: 437200000 | DK2: 408200000 | DL2: 343400000 | DM2: 484809000 | DN2: 359400000 | DO2: 317300000 | DP2: 287100000 | DQ2: 383100000 | DR2: 272600000 | DS2: 255600000 | DT2: 221800000 | DU2: 291700000 | DV2: 223500000 | DW2: 216900000 | DX2: 188600000 | DY2: 243000000 | DZ2: 189700000 | EA2: 173300000 | EB2: 148300000 | EC2: 201900000 | ED2: 164600000 | EE2: 153000000 | EF2: 133800000 | EG2: 192000000 | EH2: 145600000 | EI2: 147600000 | EJ2: 129900000 | EK2: 190100000 | EL2: 153100000 | EM2: 145600000 | EN2: 124200000 | EO2: 189500000 | EP2: 136900000 | EQ2: 146000000 | ER2: 116000000 | ES2: 186200000 | ET2: 134000000 | EU2: 135900000 | EV2: 108700000 | EW2: 182000000 | EX2: 138700000
A3: OperatingRevenue | B3: 38806811000 | C3: 9796181000 | D3: 9342832000 | E3: 10202907000 | F3: 9464891000 | G3: 9425713000 | H3: 8751352000 | I3: 8651448000 | J3: 8517839000 | K3: 8650198000 | L3: 8400964000 | M3: 8414524000 | N3: 8199625000 | O3: 8684241000 | P3: 8448449000 | Q3: 7157642000 | R3: 6991393000 | S3: 6981753000 | T3: 6623185000 | U3: 6649809000 | V3: 6417462000 | W3: 6443309000 | X3: 6114463000 | Y3: 6129431000 | Z3: 5903606000 | AA3: 5828305000 | AB3: 5609625000 | AC3: 6009246000 | AD3: 5320029000 | AE3: 5391891000 | AF3: 5265432000 | AG3: 5286938000 | AH3: 5067048000 | AI3: 5095904000 | AJ3: 4918672000 | AK3: 4939059000 | AL3: 4724409000 | AM3: 4724039000 | AN3: 4522081000 | AO3: 4493945000 | AP3: 4381838000 | AQ3: 4394651000 | AR3: 4233733000 | AS3: 4207621000 | AT3: 3964647000 | AU3: 3948655000 | AV3: 3901205000 | AW3: 4185073000 | AX3: 3595224000 | AY3: 3575194000 | AZ3: 3451697000 | BA3: 3486104000 | BB3: 3223427000 | BC3: 3214155000 | BD3: 3111314000 | BE3: 3185785000 | BF3: 2928751000 | BG3: 2901907000 | BH3: 2779937000 | BI3: 2845848000 | BJ3: 2598938000 | BK3: 2609384000 | BL3: 2403498000 | BM3: 2559573000 | BN3: 2312842000 | BO3: 2347564000 | BP3: 2275267000 | BQ3: 2553986000 | BR3: 2213396000 | BS3: 2251053000 | BT3: 2151387000 | BU3: 2480504000 | BV3: 2057888000 | BW3: 2066016000 | BX3: 1977829000 | BY3: 2197538000 | BZ3: 1879187000 | CA3: 1836243000 | CB3: 1747959000 | CC3: 1966488000 | CD3: 1685346000 | CE3: 1651094000 | CF3: 1569064000 | CG3: 1759563000 | CH3: 1497702000 | CI3: 1453727000 | CJ3: 1389412000 | CK3: 1586012000 | CL3: 1309125000 | CM3: 1225254000 | CN3: 1202504000 | CO3: 1441714000 | CP3: 1094360000 | CQ3: 1017418000 | CR3: 997079000 | CS3: 1177764000 | CT3: 950400000 | CU3: 915200000 | CV3: 844600000 | CW3: 992989000 | CX3: 781400000 | CY3: 741400000 | CZ3: 705300000 | DA3: 861125000 | DB3: 649400000 | DC3: 596800000 | DD3: 520000000 | DE3: 675198000 | DF3: 509000000 | DG3: 494400000 | DH3: 455900000 | DI3: 575388000 | DJ3: 437200000 | DK3: 408200000 | DL3: 343400000 | DM3: 484809000 | DN3: 359400000 | DO3: 317300000 | DP3: 287100000 | DQ3: 383100000 | DR3: 272600000 | DS3: 255600000 | DT3: 221800000 | DU3: 291700000 | DV3: 223500000 | DW3: 216900000 | DX3: 188600000 | DY3: 243000000 | DZ3: 189700000 | EA3: 173300000 | EB3: 148300000 | EC3: 201900000 | ED3: 164600000 | EE3: 153000000 | EF3: 133800000 | EG3: 192000000 | EH3: 145600000 | EI3: 147600000 | EJ3: 129900000 | EK3: 190100000 | EL3: 153100000 | EM3: 145600000 | EN3: 124200000 | EO3: 189500000 | EP3: 136900000 | EQ3: 146000000 | ER3: 116000000 | ES3: 186200000 | ET3: 134000000 | EU3: 135900000 | EV3: 108700000 | EW3: 182000000 | EX3: 138700000
A4: CostOfRevenue | B4: 26773139000 | C4: 6751495000 | D4: 6387358000 | E4: 7054590000 | F4: 6579696000 | G4: 6377490000 | H4: 6012989000 | I4: 5951208000 | J4: 5898400000 | K4: 5912539000 | L4: 5645296000 | M4: 5677829000 | N4: 5631385000 | O4: 5866006000 | P4: 5852757000 | Q4: 4884879000 | R4: 4926307000 | S4: 4832817000 | T4: 4620909000 | U4: 4578120000 | V4: 4522403000 | W4: 4468436000 | X4: 4252214000 | Y4: 4164033000 | Z4: 4137150000 | AA4: 4037783000 | AB4: 3910642000 | AC4: 4108499000 | AD4: 3732519000 | AE4: 3710124000 | AF4: 3652818000 | AG4: 3604669000 | AH4: 3530086000 | AI4: 3507749000 | AJ4: 3419967000 | AK4: 3373620000 | AL4: 3300661000 | AM4: 3268465000 | AN4: 3164335000 | AO4: 3059134000 | AP4: 3053345000 | AQ4: 3017361000 | AR4: 2938585000 | AS4: 2839822000 | AT4: 2738524000 | AU4: 2685432000 | AV4: 2672949000 | AW4: 2838704000 | AX4: 2479422000 | AY4: 2426852000 | AZ4: 2364300000 | BA4: 2355951000 | BB4: 2212759000 | BC4: 2178176000 | BD4: 2111558000 | BE4: 2160396000 | BF4: 2025669000 | BG4: 1995865000 | BH4: 1924579000 | BI4: 2008150000 | BJ4: 1826651000 | BK4: 1851349000 | BL4: 1710421000 | BM4: 1819202000 | BN4: 1666042000 | BO4: 1724326000 | BP4: 1642207000 | BQ4: 1908036000 | BR4: 1686949000 | BS4: 1639519000 | BT4: 1567113000 | BU4: 1749575000 | BV4: 1478872000 | BW4: 1474486000 | BX4: 1414480000 | BY4: 1537561000 | BZ4: 1325202000 | CA4: 1299263000 | CB4: 1235709000 | CC4: 1389992000 | CD4: 1168449000 | CE4: 1178264000 | CF4: 1117158000 | CG4: 1231599000 | CH4: 1069119000 | CI4: 1066300000 | CJ4: 1009120000 | CK4: 1110489000 | CL4: 927944000 | CM4: 893971000 | CN4: 881079000 | CO4: 1066857000 | CP4: 772996000 | CQ4: 735445000 | CR4: 724370000 | CS4: 880073000 | CT4: 656100000 | CU4: 650100000 | CV4: 603800000 | CW4: 746412000 | CX4: 543200000 | CY4: 523000000 | CZ4: 502600000 | DA4: 632590000 | DB4: 455600000 | DC4: 427500000 | DD4: 369600000 | DE4: 499103000 | DF4: 352200000 | DG4: 353100000 | DH4: 325200000 | DI4: 428269000 | DJ4: 302400000 | DK4: 288300000 | DL4: 241700000 | DM4: 341730000 | DN4: 251700000 | DO4: 225700000 | DP4: 203400000 | DQ4: 277100000 | DR4: 187300000 | DS4: 179900000 | DT4: 156800000 | DU4: 200300000 | DV4: 157000000 | DW4: 153900000 | DX4: 134200000 | DY4: 171800000 | DZ4: 133200000 | EA4: 122200000 | EB4: 105000000 | EC4: 141400000 | ED4: 115200000 | EE4: 107800000 | EF4: 94800000 | EG4: 129800000 | EH4: 101800000 | EI4: 103800000
A5: GrossProfit | B5: 12033672000 | C5: 3044686000 | D5: 2955474000 | E5: 3148317000 | F5: 2885195000 | G5: 3048223000 | H5: 2738363000 | I5: 2700240000 | J5: 2619439000 | K5: 2737659000 | L5: 2755668000 | M5: 2736695000 | N5: 2568240000 | O5: 2818235000 | P5: 2595692000 | Q5: 2272763000 | R5: 2065086000 | S5: 2148936000 | T5: 2002276000 | U5: 2071689000 | V5: 1895059000 | W5: 1974873000 | X5: 1862249000 | Y5: 1965398000 | Z5: 1766456000 | AA5: 1790522000 | AB5: 1698983000 | AC5: 1900747000 | AD5: 1587510000 | AE5: 1681767000 | AF5: 1612614000 | AG5: 1682269000 | AH5: 1536962000 | AI5: 1588155000 | AJ5: 1498705000 | AK5: 1565439000 | AL5: 1423748000 | AM5: 1455574000 | AN5: 1357746000 | AO5: 1434811000 | AP5: 1328493000 | AQ5: 1377290000 | AR5: 1295148000 | AS5: 1367799000 | AT5: 1226123000 | AU5: 1263223000 | AV5: 1228256000 | AW5: 1346369000 | AX5: 1115802000 | AY5: 1148342000 | AZ5: 1087397000 | BA5: 1130153000 | BB5: 1010668000 | BC5: 1035979000 | BD5: 999756000 | BE5: 1025389000 | BF5: 903082000 | BG5: 906042000 | BH5: 855358000 | BI5: 837698000 | BJ5: 772287000 | BK5: 758035000 | BL5: 693077000 | BM5: 740371000 | BN5: 646800000 | BO5: 623238000 | BP5: 633060000 | BQ5: 645950000 | BR5: 526447000 | BS5: 611534000 | BT5: 584274000 | BU5: 730929000 | BV5: 579016000 | BW5: 591530000 | BX5: 563349000 | BY5: 659977000 | BZ5: 553985000 | CA5: 536980000 | CB5: 512250000 | CC5: 576496000 | CD5: 516897000 | CE5: 472830000 | CF5: 451906000 | CG5: 527964000 | CH5: 428583000 | CI5: 387427000 | CJ5: 380292000 | CK5: 475523000 | CL5: 381181000 | CM5: 331283000 | CN5: 321425000 | CO5: 374857000 | CP5: 321364000 | CQ5: 281973000 | CR5: 272709000 | CS5: 297691000 | CT5: 294300000 | CU5: 265100000 | CV5: 240800000 | CW5: 246577000 | CX5: 238200000 | CY5: 218400000 | CZ5: 202700000 | DA5: 228535000 | DB5: 193800000 | DC5: 169300000 | DD5: 150400000 | DE5: 176095000 | DF5: 156800000 | DG5: 141300000 | DH5: 130700000 | DI5: 147119000 | DJ5: 134800000 | DK5: 119900000 | DL5: 101700000 | DM5: 143079000 | DN5: 107700000 | DO5: 91600000 | DP5: 83700000 | DQ5: 106000000 | DR5: 85300000 | DS5: 75700000 | DT5: 65000000 | DU5: 91400000 | DV5: 66500000 | DW5: 63000000 | DX5: 54400000 | DY5: 71200000 | DZ5: 56500000 | EA5: 51100000 | EB5: 43300000 | EC5: 60500000 | ED5: 49400000 | EE5: 45200000 | EF5: 39000000 | EG5: 62200000 | EH5: 43800000 | EI5: 43800000
A6: OperatingExpense | B6: 8931781000 | C6: 2352372000 | D6: 2214616000 | E6: 2215143000 | F6: 2149650000 | G6: 2134797000 | H6: 1992206000 | I6: 1903571000 | J6: 1953851000 | K6: 1888091000 | L6: 1846818000 | M6: 1864471000 | N6: 1795110000 | O6: 1775608000 | P6: 1728908000 | Q6: 1551888000 | R6: 1573669000 | S6: 1571161000 | T6: 1490039000 | U6: 1433186000 | V6: 1452916000 | W6: 1429397000 | X6: 1372065000 | Y6: 1341952000 | Z6: 1349025000 | AA6: 1297376000 | AB6: 1225188000 | AC6: 1220129000 | AD6: 1194519000 | AE6: 1172670000 | AF6: 1131871000 | AG6: 1069840000 | AH6: 1113103000 | AI6: 1112343000 | AJ6: 1070511000 | AK6: 998723000 | AL6: 1029605000 | AM6: 1027048000 | AN6: 978038000 | AO6: 896689000 | AP6: 938252000 | AQ6: 964468000 | AR6: 900148000 | AS6: 845450000 | AT6: 864734000 | AU6: 876009000 | AV6: 843932000 | AW6: 838129000 | AX6: 804885000 | AY6: 798313000 | AZ6: 765779000 | BA6: 721902000 | BB6: 736334000 | BC6: 735222000 | BD6: 709033000 | BE6: 746456000 | BF6: 686843000 | BG6: 672825000 | BH6: 630489000 | BI6: 617370000 | BJ6: 634055000 | BK6: 614980000 | BL6: 582504000 | BM6: 553905000 | BN6: 581097000 | BO6: 675378000 | BP6: 577692000 | BQ6: 562875000 | BR6: 523108000 | BS6: 530957000 | BT6: 502989000 | BU6: 498665000 | BV6: 477404000 | BW6: 470460000 | BX6: 456428000 | BY6: 439633000 | BZ6: 440029000 | CA6: 428854000 | CB6: 397700000 | CC6: 391373000 | CD6: 385551000 | CE6: 370987000 | CF6: 348955000 | CG6: 350419000 | CH6: 335152000 | CI6: 313667000 | CJ6: 297304000 | CK6: 312639000 | CL6: 295103000 | CM6: 276069000 | CN6: 251990000 | CO6: 280512000 | CP6: 236524000 | CQ6: 215985000 | CR6: 201878000 | CS6: 155489000 | CT6: 212300000 | CU6: 197900000 | CV6: 182900000 | CW6: 128013000 | CX6: 171900000 | CY6: 163300000 | CZ6: 153300000 | DA6: 123492000 | DB6: 138200000 | DC6: 125900000 | DD6: 118900000 | DE6: 92719000 | DF6: 112300000 | DG6: 104900000 | DH6: 105200000 | DI6: 83812000 | DJ6: 99800000 | DK6: 89400000 | DL6: 81700000 | DM6: 89592000 | DN6: 78800000 | DO6: 68500000 | DP6: 68000000 | DQ6: 70000000 | DR6: 67600000 | DS6: 59400000 | DT6: 54900000 | DU6: 63200000 | DV6: 52100000 | DW6: 51600000 | DX6: 47500000 | DY6: 51000000 | DZ6: 48400000 | EA6: 44300000 | EB6: 40700000 | EC6: 45700000 | ED6: 43300000 | EE6: 39500000 | EF6: 37300000 | EG6: 49100000 | EH6: 37800000 | EI6: 37800000
A7: SellingGeneralAndAdministration | B7: 8931781000 | C7: 2352372000 | D7: 2214616000 | E7: 2215143000 | F7: 2149650000 | G7: 2134797000 | H7: 1992206000 | I7: 1903571000 | J7: 1953851000 | K7: 1888091000 | L7: 1846818000 | M7: 1864471000 | N7: 1795110000 | O7: 1775608000 | P7: 1728908000 | Q7: 1551888000 | R7: 1573669000 | S7: 1571161000 | T7: 1490039000 | U7: 1433186000 | V7: 1452916000 | W7: 1429397000 | X7: 1372065000 | Y7: 1341952000 | Z7: 1349025000 | AA7: 1297376000 | AB7: 1225188000 | AC7: 1220129000 | AD7: 1194519000 | AE7: 1172670000 | AF7: 1131871000 | AG7: 1069840000 | AH7: 1113103000 | AI7: 1112343000 | AJ7: 1070511000 | AK7: 998723000 | AL7: 1029605000 | AM7: 1027048000 | AN7: 978038000 | AO7: 896689000 | AP7: 938252000 | AQ7: 964468000 | AR7: 900148000 | AS7: 845450000 | AT7: 864734000 | AU7: 876009000 | AV7: 843932000 | AW7: 838129000 | AX7: 804885000 | AY7: 798313000 | AZ7: 765779000 | BA7: 721902000 | BB7: 736334000 | BC7: 735222000 | BD7: 709033000 | BE7: 746456000 | BF7: 686843000 | BG7: 672825000 | BH7: 630489000 | BI7: 617370000 | BJ7: 634055000 | BK7: 614980000 | BL7: 582504000 | BM7: 553905000 | BN7: 581097000 | BO7: 675378000 | BP7: 577692000 | BQ7: 562875000 | BR7: 523108000 | BS7: 530957000 | BT7: 502989000 | BU7: 498665000 | BV7: 477404000 | BW7: 470460000 | BX7: 456428000 | BY7: 439633000 | BZ7: 440029000 | CA7: 428854000 | CB7: 397700000 | CC7: 391373000 | CD7: 385551000 | CE7: 370987000 | CF7: 348955000 | CG7: 350419000 | CH7: 335152000 | CI7: 313667000 | CJ7: 297304000 | CK7: 312639000 | CL7: 295103000 | CM7: 276069000 | CN7: 251990000 | CO7: 280512000 | CP7: 236524000 | CQ7: 215985000 | CR7: 201878000 | CS7: 202289000 | CT7: 195800000 | CU7: 182400000 | CV7: 168100000 | CW7: 166813000 | CX7: 158400000 | CY7: 150400000 | CZ7: 140900000 | DA7: 151292000 | DB7: 128200000 | DC7: 116700000 | DD7: 110300000 | DE7: 115719000 | DF7: 104200000 | DG7: 97300000 | DH7: 97900000 | DI7: 101712000 | DJ7: 93300000 | DK7: 83400000 | DL7: 76300000 | DM7: 93992000 | DN7: 76600000 | DO7: 64600000 | DP7: 64300000 | DQ7: 74800000 | DR7: 62000000 | DS7: 56700000 | DT7: 52400000 | DU7: 61000000 | DV7: 49900000 | DW7: 49700000 | DX7: 45600000 | DY7: 49100000 | DZ7: 46700000 | EA7: 42700000 | EB7: 39200000 | EC7: 44000000 | ED7: 41600000 | EE7: 37900000 | EF7: 35800000 | EG7: 47200000 | EH7: 36400000 | EI7: 36400000
A8: DepreciationAmortizationDepletionIncomeStatement | CT8: 16500000 | CU8: 15500000 | CV8: 14800000 | CX8: 13500000 | CY8: 12900000 | CZ8: 12400000 | DB8: 10000000 | DC8: 9200000 | DD8: 8600000 | DF8: 8100000 | DG8: 7600000 | DH8: 7300000 | DJ8: 6500000 | DK8: 6000000 | DL8: 5400000 | DN8: 2200000 | DO8: 3900000 | DP8: 3700000 | DQ8: -4800000 | DR8: 5600000 | DS8: 2700000 | DT8: 2500000 | DU8: 2200000 | DV8: 2200000 | DW8: 1900000 | DX8: 1900000 | DY8: 1900000 | DZ8: 1700000 | EA8: 1600000 | EB8: 1500000 | EC8: 1700000 | ED8: 1700000 | EE8: 1600000 | EF8: 1500000 | EG8: 1900000 | EH8: 1400000 | EI8: 1400000
A9: DepreciationAndAmortizationInIncomeStatement | CT9: 16500000 | CU9: 15500000 | CV9: 14800000 | CX9: 13500000 | CY9: 12900000 | CZ9: 12400000 | DB9: 10000000 | DC9: 9200000 | DD9: 8600000 | DF9: 8100000 | DG9: 7600000 | DH9: 7300000 | DJ9: 6500000 | DK9: 6000000 | DL9: 5400000 | DN9: 2200000 | DO9: 3900000 | DP9: 3700000 | DQ9: -4800000 | DR9: 5600000 | DS9: 2700000 | DT9: 2500000 | DU9: 2200000 | DV9: 2200000 | DW9: 1900000 | DX9: 1900000 | DY9: 1900000 | DZ9: 1700000 | EA9: 1600000 | EB9: 1500000 | EC9: 1700000 | ED9: 1700000 | EE9: 1600000 | EF9: 1500000 | EG9: 1900000 | EH9: 1400000 | EI9: 1400000
A10: DepreciationIncomeStatement | CT10: 16500000 | CU10: 15500000 | CV10: 14800000 | CX10: 13500000 | CY10: 12900000 | CZ10: 12400000 | DB10: 10000000 | DC10: 9200000 | DD10: 8600000 | DF10: 8100000 | DG10: 7600000 | DH10: 7300000 | DJ10: 6500000 | DK10: 6000000 | DL10: 5400000 | DN10: 2200000 | DO10: 3900000 | DP10: 3700000 | DQ10: -4800000 | DR10: 5600000 | DS10: 2700000 | DT10: 2500000 | DU10: 2200000 | DV10: 2200000 | DW10: 1900000 | DX10: 1900000 | DY10: 1900000 | DZ10: 1700000 | EA10: 1600000 | EB10: 1500000 | EC10: 1700000 | ED10: 1700000 | EE10: 1600000 | EF10: 1500000 | EG10: 1900000 | EH10: 1400000 | EI10: 1400000
A11: OperatingIncome | B11: 3101891000 | C11: 692314000 | D11: 740858000 | E11: 933174000 | F11: 735545000 | G11: 913426000 | H11: 746157000 | I11: 796669000 | J11: 665588000 | K11: 849568000 | L11: 908850000 | M11: 872224000 | N11: 773130000 | O11: 1042627000 | P11: 866784000 | Q11: 720875000 | R11: 491417000 | S11: 577775000 | T11: 512237000 | U11: 638503000 | V11: 442143000 | W11: 545476000 | X11: 490184000 | Y11: 623446000 | Z11: 417431000 | AA11: 493146000 | AB11: 473795000 | AC11: 680618000 | AD11: 392991000 | AE11: 509097000 | AF11: 480743000 | AG11: 612429000 | AH11: 423859000 | AI11: 475812000 | AJ11: 428194000 | AK11: 566716000 | AL11: 394143000 | AM11: 428526000 | AN11: 379708000 | AO11: 538122000 | AP11: 390241000 | AQ11: 412822000 | AR11: 395000000 | AS11: 522349000 | AT11: 361389000 | AU11: 387214000 | AV11: 384324000 | AW11: 508240000 | AX11: 310917000 | AY11: 350029000 | AZ11: 321618000 | BA11: 408251000 | BB11: 274334000 | BC11: 300757000 | BD11: 290723000 | BE11: 278933000 | BF11: 216239000 | BG11: 233217000 | BH11: 224869000 | BI11: 220328000 | BJ11: 138232000 | BK11: 143055000 | BL11: 110573000 | BM11: 186466000 | BN11: 65703000 | BO11: -52140000 | BP11: 55368000 | BQ11: 83075000 | BR11: 3339000 | BS11: 80577000 | BT11: 81285000 | BU11: 232264000 | BV11: 101612000 | BW11: 121070000 | BX11: 106921000 | BY11: 220344000 | BZ11: 113956000 | CA11: 108126000 | CB11: 114550000 | CC11: 185123000 | CD11: 131346000 | CE11: 101843000 | CF11: 102951000 | CG11: 177545000 | CH11: 93431000 | CI11: 73760000 | CJ11: 82988000 | CK11: 162884000 | CL11: 86078000 | CM11: 55214000 | CN11: 69435000 | CO11: 94345000 | CP11: 84840000 | CQ11: 65988000 | CR11: 70831000 | CS11: 142202000 | CT11: 82000000 | CU11: 67200000 | CV11: 57900000 | CW11: 118564000 | CX11: 66300000 | CY11: 55100000 | CZ11: 49400000 | DA11: 105043000 | DB11: 55600000 | DC11: 43400000 | DD11: 31500000 | DE11: 83376000 | DF11: 44500000 | DG11: 36400000 | DH11: 25500000 | DI11: 63307000 | DJ11: 35000000 | DK11: 30500000 | DL11: 20000000 | DM11: 53487000 | DN11: 28900000 | DO11: 23100000 | DP11: 15700000 | DQ11: 36000000 | DR11: 17700000 | DS11: 16300000 | DT11: 10100000 | DU11: 28200000 | DV11: 14400000 | DW11: 11400000 | DX11: 6900000 | DY11: 20200000 | DZ11: 8100000 | EA11: 6800000 | EB11: 2600000 | EC11: 14800000 | ED11: 6100000 | EE11: 5700000 | EF11: 1700000 | EG11: 13100000 | EH11: 6000000 | EI11: 6000000 | EJ11: 129900000 | EK11: -400400000 | EL11: 153100000 | EM11: 145600000 | EN11: 124200000 | EO11: -380600000 | EP11: 136900000 | EQ11: 146000000 | ER11: 116000000 | ES11: -364100000 | ET11: 134000000 | EU11: 135900000 | EV11: 108700000 | EW11: -360300000 | EX11: 138700000
A12: NetNonOperatingInterestIncomeExpense | B12: -295874000 | C12: -84337000 | D12: -83038000 | E12: -74818000 | F12: -53681000 | G12: -43098000 | H12: -39676000 | I12: -38506000 | J12: -39198000 | K12: -39430000 | L12: -40392000 | M12: -40268000 | N12: -40298000 | O12: -39326000 | P12: -30493000 | Q12: -25567000 | R12: -24264000 | S12: -24810000 | T12: -25933000 | U12: -25061000 | V12: -24586000 | W12: -25451000 | X12: -24773000 | Y12: -24289000 | Z12: -23995000 | AA12: -23748000 | AB12: -25004000 | AC12: -25511000 | AD12: -23877000 | AE12: -24352000 | AF12: -24081000 | AG12: -23275000 | AH12: -21394000 | AI12: -20699000 | AJ12: -21576000 | AK12: -21532000 | AL12: -21835000 | AM12: -22598000 | AN12: -22267000 | AO12: -22313000 | AP12: -21524000 | AQ12: -20631000 | AR12: -24516000 | AS12: -27460000 | AT12: -27726000 | AU12: -35666000 | AV12: -37074000 | AW12: -40069000 | AX12: -38632000 | AY12: -60627000 | AZ12: -65572000 | BA12: -65537000 | BB12: -67145000 | BC12: -69298000 | BD12: -72012000 | BE12: -78943000 | BF12: -87586000 | BG12: -89930000 | BH12: -89141000 | BI12: -92966000 | BJ12: -97774000 | BK12: -98217000 | BL12: -99914000 | BM12: -103042000 | BN12: -110569000 | BO12: -37146000 | BP12: -3594000 | BQ12: -5681000 | BR12: -10019000 | BS12: -7416000 | BT12: -4797000 | BU12: -5034000 | BV12: -3651000 | BW12: -5188000 | BX12: -3352000 | BY12: -5372000 | BZ12: -6364000 | CA12: -4041000 | CB12: -6442000 | CC12: -6217000 | CD12: -7976000 | CE12: -7899000 | CF12: -9411000 | CG12: -9333000 | CH12: -11537000 | CI12: -11337000 | CJ12: -10432000 | CK12: -10752000 | CL12: -11480000 | CM12: -11957000 | CN12: -11600000
A13: InterestIncomeNonOperating | AW13: 36000 | AX13: 10000 | AY13: 26000 | AZ13: 19000 | BA13: 92000 | BB13: 90000 | BC13: 32000 | BD13: 6000 | BE13: 9000 | BF13: 26000 | BG13: 15000 | BH13: 94000 | BI13: 268000 | BJ13: 619000 | BK13: 1217000 | BL13: 957000 | BM13: 1378000 | BN13: 1388000 | BO13: 3506000 | BP13: 2573000 | BQ13: 2210000 | BR13: 885000 | BS13: 1457000 | BT13: 2450000 | BU13: 2559000 | BV13: 1670000 | BW13: 2156000 | BX13: 2616000
A14: InterestExpenseNonOperating | B14: 295874000 | C14: 84337000 | D14: 83038000 | E14: 74818000 | F14: 53681000 | G14: 43098000 | H14: 39676000 | I14: 38506000 | J14: 39198000 | K14: 39430000 | L14: 40392000 | M14: 40268000 | N14: 40298000 | O14: 39326000 | P14: 30493000 | Q14: 25567000 | R14: 24264000 | S14: 24810000 | T14: 25933000 | U14: 25061000 | V14: 24586000 | W14: 25451000 | X14: 24773000 | Y14: 24289000 | Z14: 23995000 | AA14: 23748000 | AB14: 25004000 | AC14: 25511000 | AD14: 23877000 | AE14: 24352000 | AF14: 24081000 | AG14: 23275000 | AH14: 21394000 | AI14: 20699000 | AJ14: 21576000 | AK14: 21532000 | AL14: 21835000 | AM14: 22598000 | AN14: 22267000 | AO14: 22313000 | AP14: 21524000 | AQ14: 20631000 | AR14: 24516000 | AS14: 27460000 | AT14: 27726000 | AU14: 35666000 | AV14: 37074000 | AW14: 40105000 | AX14: 38642000 | AY14: 60653000 | AZ14: 65591000 | BA14: 65629000 | BB14: 67235000 | BC14: 69330000 | BD14: 72018000 | BE14: 78952000 | BF14: 87612000 | BG14: 89945000 | BH14: 89235000 | BI14: 93234000 | BJ14: 98393000 | BK14: 99434000 | BL14: 100871000 | BM14: 104420000 | BN14: 111957000 | BO14: 40652000 | BP14: 6167000 | BQ14: 7891000 | BR14: 10904000 | BS14: 8873000 | BT14: 7247000 | BU14: 7593000 | BV14: 5321000 | BW14: 7344000 | BX14: 5968000 | CI14: 11337000 | CJ14: 10432000 | CK14: 10752000 | CL14: 11480000 | CM14: 11957000 | CN14: 11600000
A15: TotalOtherFinanceCost | BZ15: 6364000 | CA15: 4041000 | CB15: 6442000 | CC15: 6217000 | CD15: 7976000 | CE15: 7899000 | CF15: 9411000 | CH15: 11537000
A16: OtherIncomeExpense | E16: 0 | F16: -415000 | U16: 0 | W16: -1019000 | Y16: 0 | AB16: -3502000 | AG16: 0 | AH16: -326000 | AO16: 0 | AR16: -18871000 | AS16: 0 | AT16: -1728000 | AU16: -26557000 | AV16: -1671000 | AW16: -51000 | AX16: -53000 | AY16: -58239000 | AZ16: -2272000 | BA16: -118000 | BB16: -8312000 | BC16: -6526000 | BD16: -145000 | BE16: -55757000 | BF16: -513000 | BG16: 2395000 | BH16: -1667000 | BI16: 6144000 | BJ16: -34766000 | BK16: -292000 | BM16: 4593000 | BN16: -6784000 | BO16: 567000 | CG16: 0 | CH16: 25041000 | CI16: 4500000
A17: SpecialIncomeCharges | AT17: -1728000 | AU17: -26557000 | AV17: -1671000 | AW17: -51000 | AX17: -53000 | AY17: -58239000 | AZ17: -2272000 | BA17: -118000 | BB17: -8312000 | BC17: -6526000 | BD17: -145000 | BE17: -55757000 | BF17: -513000 | BG17: 2395000 | BH17: -1667000 | BI17: 6144000 | BJ17: -34766000 | BK17: -292000 | BM17: 4593000 | BN17: -6784000 | BO17: 567000 | CC17: -10000000 | CD17: 0 | CE17: 0 | CG17: 0 | CH17: 25041000 | CI17: 4500000
A18: OtherSpecialCharges | AT18: 1728000 | AU18: 26557000 | AV18: 1671000 | AW18: 51000 | AX18: 53000 | AY18: 58239000 | AZ18: 2272000 | BE18: 55757000 | BF18: 513000 | BG18: -2395000 | BH18: 1667000 | BI18: -6144000 | BJ18: 34766000 | BM18: -4593000 | BN18: 6784000
A19: OtherNonOperatingIncomeExpenses | E19: 0 | F19: -415000 | U19: 0 | W19: -1019000 | Y19: 0 | AB19: -3502000 | AG19: 0 | AH19: -326000 | AO19: 0 | AR19: -18871000
A20: PretaxIncome | B20: 2805602000 | C20: 607977000 | D20: 657820000 | E20: 858356000 | F20: 681449000 | G20: 870328000 | H20: 706481000 | I20: 758163000 | J20: 626390000 | K20: 810138000 | L20: 868458000 | M20: 831956000 | N20: 732832000 | O20: 1003301000 | P20: 836291000 | Q20: 695308000 | R20: 467153000 | S20: 552965000 | T20: 486304000 | U20: 613442000 | V20: 417557000 | W20: 519006000 | X20: 465411000 | Y20: 599157000 | Z20: 393436000 | AA20: 469398000 | AB20: 445289000 | AC20: 655107000 | AD20: 369114000 | AE20: 484745000 | AF20: 456662000 | AG20: 589154000 | AH20: 402139000 | AI20: 455113000 | AJ20: 406618000 | AK20: 545184000 | AL20: 372308000 | AM20: 405928000 | AN20: 357441000 | AO20: 515809000 | AP20: 368717000 | AQ20: 392191000 | AR20: 351613000 | AS20: 494889000 | AT20: 331935000 | AU20: 324991000 | AV20: 345579000 | AW20: 468120000 | AX20: 272232000 | AY20: 231163000 | AZ20: 253774000 | BA20: 342596000 | BB20: 198877000 | BC20: 224933000 | BD20: 218566000 | BE20: 144233000 | BF20: 128140000 | BG20: 145682000 | BH20: 134061000 | BI20: 133506000 | BJ20: 5692000 | BK20: 44546000 | BL20: 10659000 | BM20: 88017000 | BN20: -51650000 | BO20: -88719000 | BP20: 51774000 | BQ20: 77394000 | BR20: -6680000 | BS20: 73161000 | BT20: 76488000 | BU20: 227230000 | BV20: 97961000 | BW20: 115882000 | BX20: 103569000 | BY20: 214972000 | BZ20: 107592000 | CA20: 104085000 | CB20: 108108000 | CC20: 168906000 | CD20: 123370000 | CE20: 93944000 | CF20: 93540000 | CG20: 168212000 | CH20: 106935000 | CI20: 66923000 | CJ20: 72556000 | CK20: 152132000 | CL20: 74598000 | CM20: 43257000 | CN20: 57835000 | CO20: -102553000 | CP20: 79985000 | CQ20: 61662000 | CR20: 69553000 | CS20: 142045000 | CT20: 79800000 | CU20: 65300000 | CV20: 57000000 | CW20: 116515000 | CX20: 62900000 | CY20: 53100000 | CZ20: 48400000 | DA20: 103879000 | DB20: 54000000 | DC20: 42900000 | DD20: 31000000 | DE20: 82417000 | DF20: 42900000 | DG20: 35300000 | DH20: 24200000 | DI20: 61446000 | DJ20: 32500000 | DK20: 28800000 | DL20: 12700000 | DM20: 52788000 | DN20: 27800000 | DO20: 22500000 | DP20: 15300000 | DQ20: 35500000 | DR20: 17200000 | DS20: 15600000 | DT20: 9600000 | DU20: 27900000 | DV20: 13400000 | DW20: 10800000 | DX20: 6300000 | DY20: 19600000 | DZ20: 7000000 | EA20: 6200000 | EB20: 1900000 | EC20: 13800000 | ED20: 4600000 | EE20: 4100000 | EF20: 600000 | EG20: 11800000 | EH20: 4700000 | EI20: 4600000
A21: TaxProvision | B21: 637085000 | C21: 139142000 | D21: 143440000 | E21: 199221000 | F21: 155282000 | G21: 192298000 | H21: 153824000 | I21: 160730000 | J21: 139359000 | K21: 173119000 | L21: 190709000 | M21: 189213000 | N21: 158572000 | O21: 215700000 | P21: 185845000 | Q21: 159871000 | R21: 101603000 | S21: 126410000 | T21: 101291000 | U21: 130201000 | V21: 83415000 | W21: 111769000 | X21: 100559000 | Y21: -112998000 | Z21: 140903000 | AA21: 174615000 | AB21: 165800000 | AC21: 240931000 | AD21: 133799000 | AE21: 178227000 | AF21: 161538000 | AG21: 212979000 | AH21: 148818000 | AI21: 172764000 | AJ21: 153383000 | AK21: 189813000 | AL21: 135992000 | AM21: 154668000 | AN21: 135043000 | AO21: 193636000 | AP21: 131332000 | AQ21: 146716000 | AR21: 131530000 | AS21: 177467000 | AT21: 124250000 | AU21: 110851000 | AV21: 132164000 | AW21: 175610000 | AX21: 101068000 | AY21: 85121000 | AZ21: 96805000 | BA21: 120050000 | BB21: 70757000 | BC21: 83738000 | BD21: 82570000 | BE21: 57036000 | BF21: 52491000 | BG21: 52092000 | BH21: 51055000 | BI21: 51652000 | BJ21: 12998000 | BK21: 16828000 | BL21: 4743000 | BM21: 32628000 | BN21: -18618000 | BO21: -19901000 | BP21: 16899000 | BQ21: 27304000 | BR21: -1395000 | BS21: 27693000 | BT21: 28818000 | BU21: 81958000 | BV21: 33536000 | BW21: 40324000 | BX21: 38669000 | BY21: 81079000 | BZ21: 36466000 | CA21: 32763000 | CB21: 40259000 | CC21: 66077000 | CD21: 45467000 | CE21: 34008000 | CF21: 33208000 | CG21: 60126000 | CH21: 38365000 | CI21: 24561000 | CJ21: 26628000 | CK21: 54689000 | CL21: 27861000 | CM21: 16157000 | CN21: 21602000 | CO21: -38555000 | CP21: 28995000 | CQ21: 22352000 | CR21: 25213000 | CS21: 51418000 | CT21: 28900000 | CU21: 23700000 | CV21: 20700000 | CW21: 38482000 | CX21: 22600000 | CY21: 19800000 | CZ21: 18000000 | DA21: 38851000 | DB21: 20400000 | DC21: 16200000 | DD21: 11700000 | DE21: 30917000 | DF21: 16300000 | DG21: 13400000 | DH21: 9200000 | DI21: 22928000 | DJ21: 12500000 | DK21: 11100000 | DL21: 1100000 | DM21: 19954000 | DN21: 10500000 | DO21: 8500000 | DP21: 5800000 | DQ21: 13400000 | DR21: 6200000 | DS21: 6000000 | DT21: 3700000 | DU21: 11100000 | DV21: 5100000 | DW21: 4100000 | DX21: 2400000 | DY21: 7300000 | DZ21: 2700000 | EA21: 2400000 | EB21: 700000 | EC21: 4900000 | ED21: 1800000 | EE21: 1600000 | EF21: 200000 | EG21: 4500000 | EH21: 1900000 | EI21: 1800000
A22: NetIncomeCommonStockholders | B22: 2168517000 | C22: 468835000 | D22: 514380000 | E22: 659135000 | F22: 526167000 | G22: 678030000 | H22: 552657000 | I22: 597433000 | J22: 487031000 | K22: 637019000 | L22: 677749000 | M22: 642743000 | N22: 574260000 | O22: 787601000 | P22: 650446000 | Q22: 535437000 | R22: 365550000 | S22: 426555000 | T22: 385013000 | U22: 483241000 | V22: 334142000 | W22: 407237000 | X22: 364852000 | Y22: 712155000 | Z22: 252533000 | AA22: 294783000 | AB22: 279489000 | AC22: 414176000 | AD22: 235315000 | AE22: 306518000 | AF22: 295124000 | AG22: 376175000 | AH22: 253321000 | AI22: 282349000 | AJ22: 253235000 | AK22: 355371000 | AL22: 236316000 | AM22: 251260000 | AN22: 222398000 | AO22: 322173000 | AP22: 237385000 | AQ22: 245475000 | AR22: 220083000 | AS22: 317422000 | AT22: 207685000 | AU22: 214140000 | AV22: 213415000 | AW22: 292510000 | AX22: 171164000 | AY22: 146042000 | AZ22: 156969000 | BA22: 222546000 | BB22: 128120000 | BC22: 141195000 | BD22: 135996000 | BE22: 87197000 | BF22: 75649000 | BG22: 93590000 | BH22: 83006000 | BI22: 81854000 | BJ22: -7306000 | BK22: 27718000 | BL22: 5916000 | BM22: 55389000 | BN22: -33032000 | BO22: -68818000 | BP22: 34875000 | BQ22: 50090000 | BR22: -5285000 | BS22: 45468000 | BT22: 47670000 | BU22: 145272000 | BV22: 64425000 | BW22: 75558000 | BX22: 64900000 | BY22: 133893000 | BZ22: 71126000 | CA22: 71322000 | CB22: 67849000 | CC22: 102829000 | CD22: 77903000 | CE22: 59936000 | CF22: 60332000 | CG22: 108086000 | CH22: 68570000 | CI22: 42362000 | CJ22: 45928000 | CK22: 97443000 | CL22: 46737000 | CM22: 27100000 | CN22: 36233000 | CO22: -63998000 | CP22: 50990000 | CQ22: 39310000 | CR22: 44340000 | CS22: 91805000 | CT22: 50900000 | CU22: 41600000 | CV22: 35122000 | CW22: 80633000 | CX22: 39400000 | CY22: 32300000 | CZ22: 29400000 | DA22: 67428000 | DB22: 33600000 | DC22: 25900000 | DD22: 18500000 | DE22: 51500000 | DF22: 26600000 | DG22: 21900000 | DH22: 14400000 | DI22: 38518000 | DJ22: 20000000 | DK22: 17700000 | DL22: 11600000 | DM22: 32834000 | DN22: 17300000 | DO22: 14000000 | DP22: 9500000 | DQ22: 22100000 | DR22: 11000000 | DS22: 9600000 | DT22: 5900000 | DU22: 16800000 | DV22: 8300000 | DW22: 6700000 | DX22: 3900000 | DY22: 12300000 | DZ22: 4300000 | EA22: 3800000 | EB22: 1200000 | EC22: 8900000 | ED22: 2800000 | EE22: 2500000 | EF22: 400000 | EG22: 7300000 | EH22: 2800000 | EI22: 2800000 | EJ22: -400000 | EK22: 6200000 | EL22: 2500000 | EM22: 2400000 | EN22: -800000 | EO22: 5300000 | EP22: 700000 | EQ22: 2000000 | ER22: -1500000 | ES22: 2500000 | ET22: 1100000 | EU22: 2400000 | EV22: -1700000 | EW22: 7600000 | EX22: 4100000
A23: NetIncome | B23: 2168517000 | C23: 468835000 | D23: 514380000 | E23: 659135000 | F23: 526167000 | G23: 678030000 | H23: 552657000 | I23: 597433000 | J23: 487031000 | K23: 637019000 | L23: 677749000 | M23: 642743000 | N23: 574260000 | O23: 787601000 | P23: 650446000 | Q23: 535437000 | R23: 365550000 | S23: 426555000 | T23: 385013000 | U23: 483241000 | V23: 334142000 | W23: 407237000 | X23: 364852000 | Y23: 712155000 | Z23: 252533000 | AA23: 294783000 | AB23: 279489000 | AC23: 414176000 | AD23: 235315000 | AE23: 306518000 | AF23: 295124000 | AG23: 376175000 | AH23: 253321000 | AI23: 282349000 | AJ23: 253235000 | AK23: 355371000 | AL23: 236316000 | AM23: 251260000 | AN23: 222398000 | AO23: 322173000 | AP23: 237385000 | AQ23: 245475000 | AR23: 220083000 | AS23: 317422000 | AT23: 207685000 | AU23: 214140000 | AV23: 213415000 | AW23: 292510000 | AX23: 171164000 | AY23: 146042000 | AZ23: 156969000 | BA23: 222546000 | BB23: 128120000 | BC23: 141195000 | BD23: 135996000 | BE23: 87197000 | BF23: 75649000 | BG23: 93590000 | BH23: 83006000 | BI23: 81854000 | BJ23: -7306000 | BK23: 27718000 | BL23: 5916000 | BM23: 55389000 | BN23: -33032000 | BO23: -68818000 | BP23: 34875000 | BQ23: 50090000 | BR23: -5285000 | BS23: 45468000 | BT23: 47670000 | BU23: 145272000 | BV23: 64425000 | BW23: 75558000 | BX23: 64900000 | BY23: 133893000 | BZ23: 71126000 | CA23: 71322000 | CB23: 67849000 | CC23: 102829000 | CD23: 77903000 | CE23: 59936000 | CF23: 60332000 | CG23: 108086000 | CH23: 68570000 | CI23: 42362000 | CJ23: 45928000 | CK23: 97443000 | CL23: 46737000 | CM23: 27100000 | CN23: 36233000 | CO23: -63998000 | CP23: 50990000 | CQ23: 39310000 | CR23: 44340000 | CS23: 90627000 | CT23: 50900000 | CU23: 41600000 | CV23: 36300000 | CW23: 78033000 | CX23: 40300000 | CY23: 33300000 | CZ23: 30400000 | DA23: 65028000 | DB23: 33600000 | DC23: 26700000 | DD23: 19300000 | DE23: 51500000 | DF23: 26600000 | DG23: 21900000 | DH23: 15000000 | DI23: 38518000 | DJ23: 20000000 | DK23: 17700000 | DL23: 11600000 | DM23: 32834000 | DN23: 17300000 | DO23: 14000000 | DP23: 9500000 | DQ23: 22100000 | DR23: 11000000 | DS23: 9600000 | DT23: 5900000 | DU23: 16800000 | DV23: 8300000 | DW23: 6700000 | DX23: 3900000 | DY23: 12300000 | DZ23: 4300000 | EA23: 3800000 | EB23: 1200000 | EC23: 8900000 | ED23: 2800000 | EE23: 2500000 | EF23: 400000 | EG23: 7300000 | EH23: 2800000 | EI23: 2800000 | EJ23: -400000 | EK23: 6200000 | EL23: 2500000 | EM23: 2400000 | EN23: -800000 | EO23: 5300000 | EP23: 700000 | EQ23: 2000000 | ER23: -1500000 | ES23: 2500000 | ET23: 1100000 | EU23: 2400000 | EV23: -1700000 | EW23: 7600000 | EX23: 4100000
A24: NetIncomeIncludingNoncontrollingInterests | B24: 2168517000 | C24: 468835000 | D24: 514380000 | E24: 659135000 | F24: 526167000 | G24: 678030000 | H24: 552657000 | I24: 597433000 | J24: 487031000 | K24: 637019000 | L24: 677749000 | M24: 642743000 | N24: 574260000 | O24: 787601000 | P24: 650446000 | Q24: 535437000 | R24: 365550000 | S24: 426555000 | T24: 385013000 | U24: 483241000 | V24: 334142000 | W24: 407237000 | X24: 364852000 | Y24: 712155000 | Z24: 252533000 | AA24: 294783000 | AB24: 279489000 | AC24: 414176000 | AD24: 235315000 | AE24: 306518000 | AF24: 295124000 | AG24: 376175000 | AH24: 253321000 | AI24: 282349000 | AJ24: 253235000 | AK24: 355371000 | AL24: 236316000 | AM24: 251260000 | AN24: 222398000 | AO24: 322173000 | AP24: 237385000 | AQ24: 245475000 | AR24: 220083000 | AS24: 317422000 | AT24: 207685000 | AU24: 214140000 | AV24: 213415000 | AW24: 292510000 | AX24: 171164000 | AY24: 146042000 | AZ24: 156969000 | BA24: 222546000 | BB24: 128120000 | BC24: 141195000 | BD24: 135996000 | BE24: 87197000 | BF24: 75649000 | BG24: 93590000 | BH24: 83006000 | BI24: 81854000 | BJ24: -7306000 | BK24: 27718000 | BL24: 5916000 | BM24: 55389000 | BN24: -33032000 | BO24: -68818000 | BP24: 34875000 | BQ24: 50090000 | BR24: -5285000 | BS24: 45468000 | BT24: 47670000 | BU24: 145272000 | BV24: 64425000 | BW24: 75558000 | BX24: 64900000 | BY24: 133893000 | BZ24: 71126000 | CA24: 71322000 | CB24: 67849000 | CC24: 102829000 | CD24: 77903000 | CE24: 59936000 | CF24: 60332000 | CG24: 108086000 | CH24: 68570000 | CI24: 42362000 | CJ24: 45928000 | CK24: 97443000 | CL24: 46737000 | CM24: 27100000 | CN24: 36233000 | CO24: -63998000 | CP24: 50990000 | CQ24: 39310000 | CR24: 44340000 | CS24: 90627000 | CT24: 50900000 | CU24: 41600000 | CV24: 36300000 | CW24: 78033000 | CX24: 40300000 | CY24: 33300000 | CZ24: 30400000 | DA24: 65028000 | DB24: 33600000 | DC24: 26700000 | DD24: 19300000 | DE24: 51500000 | DF24: 26600000 | DG24: 21900000 | DH24: 15000000 | DI24: 38518000 | DJ24: 20000000 | DK24: 17700000 | DL24: 11600000 | DM24: 32834000 | DN24: 17300000 | DO24: 14000000 | DP24: 9500000 | DQ24: 22100000 | DR24: 11000000 | DS24: 9600000 | DT24: 5900000 | DU24: 16800000 | DV24: 8300000 | DW24: 6700000 | DX24: 3900000 | DY24: 12300000 | DZ24: 4300000 | EA24: 3800000 | EB24: 1200000 | EC24: 8900000 | ED24: 2800000 | EE24: 2500000 | EF24: 400000 | EG24: 7300000 | EH24: 2800000 | EI24: 2800000 | EJ24: -400000 | EK24: 6200000 | EL24: 2500000 | EM24: 2400000 | EN24: -800000 | EO24: 5300000 | EP24: 700000 | EQ24: 2000000 | ER24: -1500000 | ES24: 2500000 | ET24: 1100000 | EU24: 2400000 | EV24: -1700000 | EW24: 7600000 | EX24: 4100000
A25: NetIncomeContinuousOperations | B25: 2168517000 | C25: 468835000 | D25: 514380000 | E25: 659135000 | F25: 526167000 | G25: 678030000 | H25: 552657000 | I25: 597433000 | J25: 487031000 | K25: 637019000 | L25: 677749000 | M25: 642743000 | N25: 574260000 | O25: 787601000 | P25: 650446000 | Q25: 535437000 | R25: 365550000 | S25: 426555000 | T25: 385013000 | U25: 483241000 | V25: 334142000 | W25: 407237000 | X25: 364852000 | Y25: 712155000 | Z25: 252533000 | AA25: 294783000 | AB25: 279489000 | AC25: 414176000 | AD25: 235315000 | AE25: 306518000 | AF25: 295124000 | AG25: 376175000 | AH25: 253321000 | AI25: 282349000 | AJ25: 253235000 | AK25: 355371000 | AL25: 236316000 | AM25: 251260000 | AN25: 222398000 | AO25: 322173000 | AP25: 237385000 | AQ25: 245475000 | AR25: 220083000 | AS25: 317422000 | AT25: 207685000 | AU25: 214140000 | AV25: 213415000 | AW25: 292510000 | AX25: 171164000 | AY25: 146042000 | AZ25: 156969000 | BA25: 222546000 | BB25: 128120000 | BC25: 141195000 | BD25: 135996000 | BE25: 87197000 | BF25: 75649000 | BG25: 93590000 | BH25: 83006000 | BI25: 81854000 | BJ25: -7306000 | BK25: 27718000 | BL25: 5916000 | BM25: 55389000 | BN25: -33032000 | BO25: -68818000 | BP25: 34875000 | BQ25: 50090000 | BR25: -5285000 | BS25: 45468000 | BT25: 47670000 | BU25: 145272000 | BV25: 64425000 | BW25: 75558000 | BX25: 64900000 | BY25: 133893000 | BZ25: 71126000 | CA25: 71322000 | CB25: 67849000 | CC25: 102829000 | CD25: 77903000 | CE25: 59936000 | CF25: 60332000 | CG25: 108086000 | CH25: 68570000 | CI25: 42362000 | CJ25: 45928000 | CK25: 97443000 | CL25: 46737000 | CM25: 27100000 | CN25: 36233000 | CO25: -63998000 | CP25: 50990000 | CQ25: 39310000 | CR25: 44340000 | CS25: 90627000 | CT25: 50900000 | CU25: 41600000 | CV25: 36300000 | CW25: 78033000 | CX25: 40300000 | CY25: 33300000 | CZ25: 30400000 | DA25: 65028000 | DB25: 33600000 | DC25: 26700000 | DD25: 19300000 | DE25: 51500000 | DF25: 26600000 | DG25: 21900000 | DH25: 15000000 | DI25: 38518000 | DJ25: 20000000 | DK25: 17700000 | DL25: 11600000 | DM25: 32834000 | DN25: 17300000 | DO25: 14000000 | DP25: 9500000 | DQ25: 22100000 | DR25: 11000000 | DS25: 9600000 | DT25: 5900000 | DU25: 16800000 | DV25: 8300000 | DW25: 6700000 | DX25: 3900000 | DY25: 12300000 | DZ25: 4300000 | EA25: 3800000 | EB25: 1200000 | EC25: 8900000 | ED25: 2800000 | EE25: 2500000 | EF25: 400000 | EG25: 7300000 | EH25: 2800000 | EI25: 2800000 | EJ25: -400000 | EK25: 6200000 | EL25: 2500000 | EM25: 2400000 | EN25: -800000 | EO25: 5300000 | EP25: 700000 | EQ25: 2000000 | ER25: -1500000 | ES25: 2500000 | ET25: 1100000 | EU25: 2400000 | EV25: -1700000 | EW25: 7600000 | EX25: 4100000
A26: PreferredStockDividends | CV26: 1178000 | CX26: 900000 | CY26: 1000000 | CZ26: 1000000 | DC26: 800000 | DD26: 800000 | DH26: 600000
A27: DilutedNIAvailtoComStockholders | B27: 2168517000 | C27: 468835000 | D27: 514380000 | E27: 659135000 | F27: 526167000 | G27: 678030000 | H27: 552657000 | I27: 597433000 | J27: 487031000 | K27: 637019000 | L27: 677749000 | M27: 642743000 | N27: 574260000 | O27: 787601000 | P27: 650446000 | Q27: 535437000 | R27: 365550000 | S27: 426555000 | T27: 385013000 | U27: 483241000 | V27: 334142000 | W27: 407237000 | X27: 364852000 | Y27: 712155000 | Z27: 252533000 | AA27: 294783000 | AB27: 279489000 | AC27: 414176000 | AD27: 235315000 | AE27: 306518000 | AF27: 295124000 | AG27: 376175000 | AH27: 253321000 | AI27: 282349000 | AJ27: 253235000 | AK27: 355371000 | AL27: 236316000 | AM27: 251260000 | AN27: 222398000 | AO27: 322173000 | AP27: 237385000 | AQ27: 245475000 | AR27: 220083000 | AS27: 317422000 | AT27: 207685000 | AU27: 214140000 | AV27: 213415000 | AW27: 292510000 | AX27: 171164000 | AY27: 146042000 | AZ27: 156969000 | BA27: 222546000 | BB27: 128120000 | BC27: 141195000 | BD27: 135996000 | BE27: 87197000 | BF27: 75649000 | BG27: 93590000 | BH27: 83006000 | BI27: 81854000 | BJ27: -7306000 | BK27: 27718000 | BL27: 5916000 | BM27: 55389000 | BN27: -33032000 | BO27: -68818000 | BP27: 34875000 | BQ27: 50090000 | BR27: -5285000 | BS27: 45468000 | BT27: 47670000 | BU27: 145272000 | BV27: 64425000 | BW27: 75558000 | BX27: 64900000 | BY27: 133893000 | BZ27: 71126000 | CA27: 71322000 | CB27: 67849000 | CC27: 102829000 | CD27: 77903000 | CE27: 59936000 | CF27: 60332000 | CG27: 108086000 | CH27: 68570000 | CI27: 42362000 | CJ27: 45928000 | CK27: 97443000 | CL27: 46737000 | CM27: 27100000 | CN27: 36233000 | CO27: -63998000 | CP27: 50990000 | CQ27: 39310000 | CR27: 44340000 | CS27: 91805000 | CT27: 50900000 | CU27: 41600000 | CV27: 35122000 | CW27: 80633000 | CX27: 39400000 | CY27: 32300000 | CZ27: 29400000 | DA27: 67428000 | DB27: 33600000 | DC27: 25900000 | DD27: 18500000 | DE27: 51500000 | DF27: 26600000 | DG27: 21900000 | DH27: 14400000 | DI27: 38518000 | DJ27: 20000000 | DK27: 17700000 | DL27: 11600000 | DM27: 32834000 | DN27: 17300000 | DO27: 14000000 | DP27: 9500000 | DQ27: 22100000 | DR27: 11000000 | DS27: 9600000 | DT27: 5900000 | DU27: 16800000 | DV27: 8300000 | DW27: 6700000 | DX27: 3900000 | DY27: 12300000 | DZ27: 4300000 | EA27: 3800000 | EB27: 1200000 | EC27: 8900000 | ED27: 2800000 | EE27: 2500000 | EF27: 400000 | EG27: 7300000 | EH27: 2800000 | EI27: 2800000 | EJ27: -400000 | EK27: 6200000 | EL27: 2500000 | EM27: 2400000 | EN27: -800000 | EO27: 5300000 | EP27: 700000 | EQ27: 2000000 | ER27: -1500000 | ES27: 2500000 | ET27: 1100000 | EU27: 2400000 | EV27: -1700000 | EW27: 7600000 | EX27: 4100000
A28: BasicEPS | C28: 2.14 | D28: 2.35 | E28: 2.97 | F28: 2.34 | G28: 3 | H28: 2.42 | I28: 2.59 | J28: 2.09 | K28: 2.71 | L28: 2.84 | M28: 2.64 | N28: 2.32 | O28: 3.15 | P28: 2.58 | Q28: 2.11 | R28: 1.43 | S28: 1.65 | T28: 1.49 | U28: 1.85 | V28: 1.26 | W28: 1.53 | X28: 1.36 | Y28: 2.63 | Z28: 0.93 | AA28: 1.08 | AB28: 1.02 | AC28: 1.5 | AD28: 0.84 | AE28: 1.08 | AF28: 1.03 | AG28: 1.3 | AH28: 0.87 | AI28: 0.95 | AJ28: 0.84 | AK28: 1.17 | AL28: 0.78 | AM28: 0.83 | AN28: 0.72 | AO28: 1.01 | AP28: 0.74 | AQ28: 0.76 | AR28: 0.67 | AS28: 0.97 | AT28: 0.62 | AU28: 0.64 | AV28: 0.64 | AW28: 0.86 | AX28: 0.5 | AY28: 0.43 | AZ28: 0.46 | BA28: 0.65 | BB28: 0.38 | BC28: 0.41 | BD28: 0.4 | BE28: 0.26 | BF28: 0.24 | BG28: 0.29 | BH28: 0.26 | BI28: 0.26 | BJ28: -0.02 | BK28: 0.106 | BL28: 0.023 | BM28: 0.177 | BN28: -0.105 | BO28: -0.219 | BP28: 0.133 | BQ28: 0.16 | BR28: -0.02 | BS28: 0.15 | BT28: 0.15 | BU28: 0.449 | BV28: 0.2 | BW28: 0.23 | BX28: 0.2 | BY28: 0.4 | BZ28: 0.22 | CA28: 0.22 | CB28: 0.2 | CC28: 0.3 | CD28: 0.23 | CE28: 0.18 | CF28: 0.18 | CG28: 0.32 | CH28: 0.21 | CI28: 0.13 | CJ28: 0.14 | CK28: 0.3 | CL28: 0.14 | CM28: 0.08 | CN28: 0.11 | CO28: -0.1 | CP28: 0.14 | CQ28: 0.08 | CR28: 0.09 | CS28: 0.226 | CT28: 0.15 | CU28: 0.14 | CV28: 0.13 | CW28: 0.189 | CX28: 0.14 | CY28: 0.11 | CZ28: 0.11 | DA28: 0.258 | DB28: 0.1 | DC28: 0.08 | DD28: 0.06 | DE28: 0.197 | DF28: 0.08 | DG28: 0.06 | DH28: 0.05 | DI28: 0.147 | DJ28: 0.06 | DK28: 0.05 | DL28: 0.04 | DM28: 0.126 | DN28: 0.05 | DO28: 0.04 | DP28: 0.02 | DQ28: 0.07 | DR28: 0.03 | DS28: 0.03 | DT28: 0.02 | DU28: 0.05 | DV28: 0.02 | DW28: 0.02 | DX28: 0.02 | DY28: 0.04 | DZ28: 0.02 | EA28: 0.02 | EB28: 0.02 | EC28: 0.03 | ED28: 0.02 | EE28: 0.02 | EF28: 0.01 | EG28: 0.03 | EH28: 0.02 | EI28: 0.02 | EJ28: -0.02 | EK28: 0.024 | EL28: 0.02 | EM28: 0.02 | EN28: -0.02 | EO28: 0.02 | EP28: 0.02 | EQ28: 0.02 | ER28: -0.02 | ES28: 0.01 | ET28: 0.02 | EU28: 0.02 | EV28: -0.02 | EW28: 0.02 | EX28: 0.02
A29: DilutedEPS | C29: 2.13 | D29: 2.34 | E29: 2.96 | F29: 2.33 | G29: 2.98 | H29: 2.41 | I29: 2.57 | J29: 2.08 | K29: 2.69 | L29: 2.82 | M29: 2.62 | N29: 2.31 | O29: 3.12 | P29: 2.56 | Q29: 2.1 | R29: 1.42 | S29: 1.65 | T29: 1.48 | U29: 1.84 | V29: 1.26 | W29: 1.52 | X29: 1.36 | Y29: 2.63 | Z29: 0.93 | AA29: 1.08 | AB29: 1.02 | AC29: 1.49 | AD29: 0.84 | AE29: 1.08 | AF29: 1.03 | AG29: 1.3 | AH29: 0.86 | AI29: 0.95 | AJ29: 0.84 | AK29: 1.17 | AL29: 0.78 | AM29: 0.83 | AN29: 0.72 | AO29: 1.01 | AP29: 0.74 | AQ29: 0.75 | AR29: 0.67 | AS29: 0.96 | AT29: 0.62 | AU29: 0.64 | AV29: 0.63 | AW29: 0.85 | AX29: 0.5 | AY29: 0.42 | AZ29: 0.45 | BA29: 0.64 | BB29: 0.37 | BC29: 0.41 | BD29: 0.39 | BE29: 0.25 | BF29: 0.24 | BG29: 0.29 | BH29: 0.26 | BI29: 0.26 | BJ29: -0.02 | BK29: 0.106 | BL29: 0.023 | BM29: 0.175 | BN29: -0.105 | BO29: -0.219 | BP29: 0.133 | BQ29: 0.16 | BR29: -0.02 | BS29: 0.15 | BT29: 0.15 | BU29: 0.445 | BV29: 0.2 | BW29: 0.23 | BX29: 0.2 | BY29: 0.4 | BZ29: 0.22 | CA29: 0.22 | CB29: 0.2 | CC29: 0.3 | CD29: 0.23 | CE29: 0.18 | CF29: 0.18 | CG29: 0.31 | CH29: 0.2 | CI29: 0.13 | CJ29: 0.14 | CK29: 0.29 | CL29: 0.14 | CM29: 0.08 | CN29: 0.11 | CO29: -0.1 | CP29: 0.14 | CQ29: 0.08 | CR29: 0.09 | CS29: 0.225 | CT29: 0.15 | CU29: 0.12 | CV29: 0.11 | CW29: 0.15 | CX29: 0.12 | CY29: 0.1 | CZ29: 0.09 | DA29: 0.257 | DB29: 0.1 | DC29: 0.08 | DD29: 0.06 | DE29: 0.197 | DF29: 0.08 | DG29: 0.06 | DH29: 0.05 | DI29: 0.147 | DJ29: 0.06 | DK29: 0.05 | DL29: 0.04 | DM29: 0.126 | DN29: 0.05 | DO29: 0.04 | DP29: 0.02 | DQ29: 0.07 | DR29: 0.03 | DS29: 0.03 | DT29: 0.02 | DU29: 0.05 | DV29: 0.02 | DW29: 0.02 | DX29: 0.02 | DY29: 0.04 | DZ29: 0.02 | EA29: 0.02 | EB29: 0.02 | EC29: 0.03 | ED29: 0.02 | EE29: 0.02 | EF29: 0.01 | EG29: 0.03 | EH29: 0.02 | EI29: 0.02 | EJ29: -0.02 | EK29: 0.024 | EL29: 0.02 | EM29: 0.02 | EN29: -0.02 | EO29: 0.02 | EP29: 0.02 | EQ29: 0.02 | ER29: -0.02 | ES29: 0.01 | ET29: 0.02 | EU29: 0.02 | EV29: -0.02 | EW29: 0.02 | EX29: 0.02
A30: BasicAverageShares | C30: 219403000 | D30: 219193000 | E30: 221289997 | F30: 224527001 | G30: 226299000 | H30: 228477000 | I30: 231080997 | J30: 232491001 | K30: 234924001 | L30: 238548001 | M30: 243490997 | N30: 247131001 | O30: 250281002 | P30: 251780002 | Q30: 253357002 | R30: 256041002 | S30: 257793002 | T30: 259021002 | U30: 261408002 | V30: 264490002 | W30: 266457002 | X30: 268267002 | Y30: 270305002 | Z30: 272319002 | AA30: 273690002 | AB30: 274692002 | AC30: 276204002 | AD30: 280441002 | AE30: 283130002 | AF30: 285886002 | AG30: 288401002 | AH30: 292037002 | AI30: 295679002 | AJ30: 301202002 | AK30: 303108002 | AL30: 303080002 | AM30: 303015002 | AN30: 309331002 | AO30: 318090002 | AP30: 321711002 | AQ30: 324770002 | AR30: 326975002 | AS30: 327598002 | AT30: 332337002 | AU30: 333001002 | AV30: 336080002 | AW30: 339926002 | AX30: 341955002 | AY30: 341534002 | AZ30: 341522002 | BA30: 341305002 | BB30: 341062002 | BC30: 341001002 | BD30: 340819002 | BE30: 337355002 | BF30: 317945002 | BG30: 317943002 | BH30: 317870002 | BI30: 315704002 | BJ30: 317570002 | BK30: 261408002 | BL30: 261408002 | BM30: 313567002 | BN30: 313567002 | BO30: 313567002 | BP30: 261408002 | BQ30: 312664002 | BR30: 312049002 | BS30: 311947002 | BT30: 313997002 | BU30: 323855002 | BV30: 319520002 | BW30: 323836002 | BX30: 328208002 | BY30: 327753002 | BZ30: 327844002 | CA30: 327799002 | CB30: 334109002 | CC30: 336263002 | CD30: 335411002 | CE30: 333871002 | CF30: 333243002 | CG30: 333262002 | CH30: 333227002 | CI30: 333067002 | CJ30: 332665002 | CK30: 332644002 | CL30: 332491002 | CM30: 332330002 | CN30: 331588002 | CO30: 331007002 | CP30: 329903002 | CQ30: 328578002 | CR30: 329476002 | CS30: 261408002 | CT30: 265466002 | CU30: 281161252 | CV30: 278511252 | CW30: 261408002 | CX30: 281428574 | CY30: 293636366 | CZ30: 267272729 | DA30: 261408002 | DB30: 336000003 | DC30: 323750003 | DD30: 308333336 | DE30: 261408002 | DF30: 332500003 | DG30: 365000003 | DH30: 288000002 | DI30: 261408002 | DJ30: 333333336 | DK30: 354000003 | DL30: 290000002 | DM30: 261408002 | DN30: 346000003 | DO30: 350000003 | DP30: 475000004 | DQ30: 302250002 | DR30: 366666670 | DS30: 320000003 | DT30: 295000002 | DU30: 354545457 | DV30: 415000003 | DW30: 335000003 | DX30: 195000002 | DY30: 308571431 | DZ30: 215000002 | EA30: 190000002 | EB30: 60000000 | EC30: 313000003 | ED30: 140000001 | EE30: 125000001 | EF30: 40000000 | EG30: 227000002 | EH30: 140000001 | EI30: 140000001 | EJ30: 20000000 | EK30: 261408002 | EL30: 125000001 | EM30: 120000001 | EN30: 40000000 | EO30: 261408002 | EP30: 35000000 | EQ30: 100000001 | ER30: 75000001 | ES30: 261408002 | ET30: 55000000 | EU30: 120000001 | EV30: 85000001 | EW30: 421666670 | EX30: 205000002
A31: DilutedAverageShares | C31: 219952000 | D31: 220107000 | E31: 222426997 | F31: 225697001 | G31: 227456000 | H31: 229609000 | I31: 232514997 | J31: 234026001 | K31: 236406001 | L31: 240301001 | M31: 245422994 | N31: 249063001 | O31: 252190002 | P31: 253627002 | Q31: 255146002 | R31: 257699002 | S31: 259102002 | T31: 260265002 | U31: 262536002 | V31: 265522002 | W31: 267226002 | X31: 269135002 | Y31: 271218002 | Z31: 272881002 | AA31: 274132002 | AB31: 275215002 | AC31: 277059002 | AD31: 281283002 | AE31: 284116002 | AF31: 286978002 | AG31: 289322002 | AH31: 292904002 | AI31: 296528002 | AJ31: 302089002 | AK31: 304435002 | AL31: 304108002 | AM31: 303888002 | AN31: 310295002 | AO31: 319104002 | AP31: 322543002 | AQ31: 325639002 | AR31: 328132002 | AS31: 328859002 | AT31: 334004002 | AU31: 335521002 | AV31: 339490002 | AW31: 343674002 | AX31: 345777002 | AY31: 345625002 | AZ31: 345393002 | BA31: 345316002 | BB31: 344739002 | BC31: 344746002 | BD31: 344397002 | BE31: 340982002 | BF31: 320558002 | BG31: 319505002 | BH31: 318298002 | BI31: 316324002 | BJ31: 317570002 | BK31: 262538002 | BL31: 262538002 | BM31: 315928002 | BN31: 315928002 | BO31: 315928002 | BP31: 262538002 | BQ31: 313588002 | BR31: 312049002 | BS31: 312594002 | BT31: 315233002 | BU31: 326334002 | BV31: 321443002 | BW31: 326340002 | BX31: 331218002 | BY31: 330403002 | BZ31: 330313002 | CA31: 330298002 | CB31: 337257002 | CC31: 339868002 | CD31: 339238002 | CE31: 336841002 | CF31: 334597002 | CG31: 334660002 | CH31: 334970002 | CI31: 335737002 | CJ31: 334834002 | CK31: 334624002 | CL31: 334857002 | CM31: 335402002 | CN31: 335184002 | CO31: 334005002 | CP31: 334097002 | CQ31: 333038002 | CR31: 334293002 | CS31: 262538002 | CT31: 270391002 | CU31: 338836252 | CV31: 336376252 | CW31: 327635558 | CX31: 328333336 | CY31: 323000003 | CZ31: 326666669 | DA31: 262538002 | DB31: 336000003 | DC31: 323750003 | DD31: 308333336 | DE31: 334736845 | DF31: 332500003 | DG31: 365000003 | DH31: 288000002 | DI31: 352142860 | DJ31: 333333336 | DK31: 354000003 | DL31: 290000002 | DM31: 340000003 | DN31: 346000003 | DO31: 350000003 | DP31: 475000004 | DQ31: 302250002 | DR31: 366666670 | DS31: 320000003 | DT31: 295000002 | DU31: 354545457 | DV31: 415000003 | DW31: 335000003 | DX31: 195000002 | DY31: 308571431 | DZ31: 215000002 | EA31: 190000002 | EB31: 60000000 | EC31: 313000003 | ED31: 140000001 | EE31: 125000001 | EF31: 40000000 | EG31: 227000002 | EH31: 140000001 | EI31: 140000001 | EJ31: 20000000 | EK31: 262538002 | EL31: 125000001 | EM31: 120000001 | EN31: 40000000 | EO31: 262538002 | EP31: 35000000 | EQ31: 100000001 | ER31: 75000001 | ES31: 262538002 | ET31: 55000000 | EU31: 120000001 | EV31: 85000001 | EW31: 421666670 | EX31: 205000002
A32: TotalOperatingIncomeAsReported | B32: 3101891000 | C32: 692314000 | D32: 740858000 | E32: 933174000 | F32: 735545000 | G32: 913426000 | H32: 746157000 | I32: 796669000 | J32: 665588000 | K32: 849568000 | L32: 908850000 | M32: 872224000 | N32: 773130000 | O32: 1042627000 | P32: 866784000 | Q32: 720875000 | R32: 491417000 | S32: 577775000 | T32: 512237000 | U32: 638503000 | V32: 442143000 | W32: 545476000 | X32: 490184000 | Y32: 623446000 | Z32: 417431000 | AA32: 493146000 | AB32: 473795000 | AC32: 680618000 | AD32: 392991000 | AE32: 509097000 | AF32: 480743000 | AG32: 612429000 | AH32: 423859000 | AI32: 475812000 | AJ32: 428194000 | AK32: 566716000 | AL32: 394143000 | AM32: 428526000 | AN32: 379708000 | AO32: 538122000 | AP32: 390241000 | AQ32: 412822000 | AR32: 395000000 | AS32: 522349000 | AT32: 361389000 | AU32: 387214000 | AV32: 384324000 | AW32: 508240000 | AX32: 310917000 | AY32: 350029000 | AZ32: 321618000 | BA32: 408251000 | BB32: 274334000 | BC32: 300757000 | BD32: 290723000 | BE32: 278933000 | BF32: 216239000 | BG32: 233217000 | BH32: 224869000 | BI32: 222828000 | BJ32: 103732000 | BK32: 143055000 | BL32: 110573000 | BM32: 186466000 | BN32: 65703000 | BO32: -52140000 | BP32: 55368000 | BQ32: 83075000 | BR32: 3339000 | BS32: 80577000 | BT32: 81285000 | BU32: 232264000 | BV32: 101612000 | BW32: 121070000 | BX32: 106921000 | BY32: 220344000 | BZ32: 113956000 | CA32: 108126000 | CB32: 114550000 | CC32: 175123000 | CD32: 131346000 | CE32: 101843000 | CF32: 102951000 | CG32: 177545000 | CH32: 118472000 | CI32: 78260000 | CJ32: 82988000 | CK32: 162884000 | CL32: 86078000 | CM32: 55214000 | CN32: 69435000 | CO32: -67655000 | CP32: 84840000 | CQ32: 65988000 | CR32: 70831000
A33: TotalExpenses | B33: 35704920000 | C33: 9103867000 | D33: 8601974000 | E33: 9269733000 | F33: 8729346000 | G33: 8512287000 | H33: 8005195000 | I33: 7854779000 | J33: 7852251000 | K33: 7800630000 | L33: 7492114000 | M33: 7542300000 | N33: 7426495000 | O33: 7641614000 | P33: 7581665000 | Q33: 6436767000 | R33: 6499976000 | S33: 6403978000 | T33: 6110948000 | U33: 6011306000 | V33: 5975319000 | W33: 5897833000 | X33: 5624279000 | Y33: 5505985000 | Z33: 5486175000 | AA33: 5335159000 | AB33: 5135830000 | AC33: 5328628000 | AD33: 4927038000 | AE33: 4882794000 | AF33: 4784689000 | AG33: 4674509000 | AH33: 4643189000 | AI33: 4620092000 | AJ33: 4490478000 | AK33: 4372343000 | AL33: 4330266000 | AM33: 4295513000 | AN33: 4142373000 | AO33: 3955823000 | AP33: 3991597000 | AQ33: 3981829000 | AR33: 3838733000 | AS33: 3685272000 | AT33: 3603258000 | AU33: 3561441000 | AV33: 3516881000 | AW33: 3676833000 | AX33: 3284307000 | AY33: 3225165000 | AZ33: 3130079000 | BA33: 3077853000 | BB33: 2949093000 | BC33: 2913398000 | BD33: 2820591000 | BE33: 2906852000 | BF33: 2712512000 | BG33: 2668690000 | BH33: 2555068000 | BI33: 2625520000 | BJ33: 2460706000 | BK33: 2466329000 | BL33: 2292925000 | BM33: 2373107000 | BN33: 2247139000 | BO33: 2399704000 | BP33: 2219899000 | BQ33: 2470911000 | BR33: 2210057000 | BS33: 2170476000 | BT33: 2070102000 | BU33: 2248240000 | BV33: 1956276000 | BW33: 1944946000 | BX33: 1870908000 | BY33: 1977194000 | BZ33: 1765231000 | CA33: 1728117000 | CB33: 1633409000 | CC33: 1781365000 | CD33: 1554000000 | CE33: 1549251000 | CF33: 1466113000 | CG33: 1582018000 | CH33: 1404271000 | CI33: 1379967000 | CJ33: 1306424000 | CK33: 1423128000 | CL33: 1223047000 | CM33: 1170040000 | CN33: 1133069000 | CO33: 1347369000 | CP33: 1009520000 | CQ33: 951430000 | CR33: 926248000 | CS33: 1035562000 | CT33: 868400000 | CU33: 848000000 | CV33: 786700000 | CW33: 874425000 | CX33: 715100000 | CY33: 686300000 | CZ33: 655900000 | DA33: 756082000 | DB33: 593800000 | DC33: 553400000 | DD33: 488500000 | DE33: 591822000 | DF33: 464500000 | DG33: 458000000 | DH33: 430400000 | DI33: 512081000 | DJ33: 402200000 | DK33: 377700000 | DL33: 323400000 | DM33: 431322000 | DN33: 330500000 | DO33: 294200000 | DP33: 271400000 | DQ33: 347100000 | DR33: 254900000 | DS33: 239300000 | DT33: 211700000 | DU33: 263500000 | DV33: 209100000 | DW33: 205500000 | DX33: 181700000 | DY33: 222800000 | DZ33: 181600000 | EA33: 166500000 | EB33: 145700000 | EC33: 187100000 | ED33: 158500000 | EE33: 147300000 | EF33: 132100000 | EG33: 178900000 | EH33: 139600000 | EI33: 141600000
A34: NetIncomeFromContinuingAndDiscontinuedOperation | B34: 2168517000 | C34: 468835000 | D34: 514380000 | E34: 659135000 | F34: 526167000 | G34: 678030000 | H34: 552657000 | I34: 597433000 | J34: 487031000 | K34: 637019000 | L34: 677749000 | M34: 642743000 | N34: 574260000 | O34: 787601000 | P34: 650446000 | Q34: 535437000 | R34: 365550000 | S34: 426555000 | T34: 385013000 | U34: 483241000 | V34: 334142000 | W34: 407237000 | X34: 364852000 | Y34: 712155000 | Z34: 252533000 | AA34: 294783000 | AB34: 279489000 | AC34: 414176000 | AD34: 235315000 | AE34: 306518000 | AF34: 295124000 | AG34: 376175000 | AH34: 253321000 | AI34: 282349000 | AJ34: 253235000 | AK34: 355371000 | AL34: 236316000 | AM34: 251260000 | AN34: 222398000 | AO34: 322173000 | AP34: 237385000 | AQ34: 245475000 | AR34: 220083000 | AS34: 317422000 | AT34: 207685000 | AU34: 214140000 | AV34: 213415000 | AW34: 292510000 | AX34: 171164000 | AY34: 146042000 | AZ34: 156969000 | BA34: 222546000 | BB34: 128120000 | BC34: 141195000 | BD34: 135996000 | BE34: 87197000 | BF34: 75649000 | BG34: 93590000 | BH34: 83006000 | BI34: 81854000 | BJ34: -7306000 | BK34: 27718000 | BL34: 5916000 | BM34: 55389000 | BN34: -33032000 | BO34: -68818000 | BP34: 34875000 | BQ34: 50090000 | BR34: -5285000 | BS34: 45468000 | BT34: 47670000 | BU34: 145272000 | BV34: 64425000 | BW34: 75558000 | BX34: 64900000 | BY34: 133893000 | BZ34: 71126000 | CA34: 71322000 | CB34: 67849000 | CC34: 102829000 | CD34: 77903000 | CE34: 59936000 | CF34: 60332000 | CG34: 108086000 | CH34: 68570000 | CI34: 42362000 | CJ34: 45928000 | CK34: 97443000 | CL34: 46737000 | CM34: 27100000 | CN34: 36233000 | CO34: -63998000 | CP34: 50990000 | CQ34: 39310000 | CR34: 44340000 | CS34: 90627000 | CT34: 50900000 | CU34: 41600000 | CV34: 36300000 | CW34: 78033000 | CX34: 40300000 | CY34: 33300000 | CZ34: 30400000 | DA34: 65028000 | DB34: 33600000 | DC34: 26700000 | DD34: 19300000 | DE34: 51500000 | DF34: 26600000 | DG34: 21900000 | DH34: 15000000 | DI34: 38518000 | DJ34: 20000000 | DK34: 17700000 | DL34: 11600000 | DM34: 32834000 | DN34: 17300000 | DO34: 14000000 | DP34: 9500000 | DQ34: 22100000 | DR34: 11000000 | DS34: 9600000 | DT34: 5900000 | DU34: 16800000 | DV34: 8300000 | DW34: 6700000 | DX34: 3900000 | DY34: 12300000 | DZ34: 4300000 | EA34: 3800000 | EB34: 1200000 | EC34: 8900000 | ED34: 2800000 | EE34: 2500000 | EF34: 400000 | EG34: 7300000 | EH34: 2800000 | EI34: 2800000 | EJ34: -400000 | EK34: 6200000 | EL34: 2500000 | EM34: 2400000 | EN34: -800000 | EO34: 5300000 | EP34: 700000 | EQ34: 2000000 | ER34: -1500000 | ES34: 2500000 | ET34: 1100000 | EU34: 2400000 | EV34: -1700000 | EW34: 7600000 | EX34: 4100000
A35: NormalizedIncome | B35: 2168517000 | C35: 468835000 | D35: 514380000 | E35: 659135000 | F35: 526167000 | G35: 678030000 | H35: 552657000 | I35: 597433000 | J35: 487031000 | K35: 637019000 | L35: 677749000 | M35: 642743000 | N35: 574260000 | O35: 787601000 | P35: 650446000 | Q35: 535437000 | R35: 365550000 | S35: 426555000 | T35: 385013000 | U35: 483241000 | V35: 334142000 | W35: 407237000 | X35: 364852000 | Y35: 712155000 | Z35: 252533000 | AA35: 294783000 | AB35: 279489000 | AC35: 414176000 | AD35: 235315000 | AE35: 306518000 | AF35: 295124000 | AG35: 376175000 | AH35: 253321000 | AI35: 282349000 | AJ35: 253235000 | AK35: 355371000 | AL35: 236316000 | AM35: 251260000 | AN35: 222398000 | AO35: 322173000 | AP35: 237385000 | AQ35: 245475000 | AR35: 220083000 | AS35: 317422000 | AT35: 2.0876617e+08 | AU35: 2.3163869e+08 | AV35: 2.1444694e+08 | AW35: 2.9254187e+08 | AX35: 1.7119732e+08 | AY35: 1.8283569e+08 | AZ35: 1.5837432e+08 | BA35: 2.2262265e+08 | BB35: 1.3347473e+08 | BC35: 1.452915e+08 | BD35: 1.3608622e+08 | BE35: 1.2090526e+08 | BF35: 75982450 | BG35: 92051388 | BH35: 84038150 | BI35: 78087046 | BJ35: 15291900 | BK35: 27899692 | BL35: 5916000 | BM35: 52498630 | BN35: -28693392 | BO35: -69257813 | BP35: 34875000 | BQ35: 50090000 | BR35: -5285000 | BS35: 45468000 | BT35: 47670000 | BU35: 145272000 | BV35: 64425000 | BW35: 75558000 | BX35: 64900000 | BY35: 133893000 | BZ35: 71126000 | CA35: 71322000 | CB35: 67849000 | CC35: 1.0891694e+08 | CD35: 77903000 | CE35: 59936000 | CF35: 60332000 | CG35: 108086000 | CH35: 52512943 | CI35: 39513517 | CJ35: 45928000 | CK35: 97443000 | CL35: 46737000 | CM35: 27100000 | CN35: 36233000 | CO35: -63998000 | CP35: 50990000 | CQ35: 39310000 | CR35: 44340000 | CS35: 90627000 | CT35: 50900000 | CU35: 41600000 | CV35: 36300000 | CW35: 78033000 | CX35: 40300000 | CY35: 33300000 | CZ35: 30400000 | DA35: 65028000 | DB35: 33600000 | DC35: 26700000 | DD35: 19300000 | DE35: 51500000 | DF35: 26600000 | DG35: 21900000 | DH35: 15000000 | DI35: 38518000 | DJ35: 20000000 | DK35: 17700000 | DL35: 11600000 | DM35: 32834000 | DN35: 17300000 | DO35: 14000000 | DP35: 9500000 | DQ35: 22100000 | DR35: 11000000 | DS35: 9600000 | DT35: 5900000 | DU35: 16800000 | DV35: 8300000 | DW35: 6700000 | DX35: 3900000 | DY35: 12300000 | DZ35: 4300000 | EA35: 3800000 | EB35: 1200000 | EC35: 8900000 | ED35: 2800000 | EE35: 2500000 | EF35: 400000 | EG35: 7300000 | EH35: 2800000 | EI35: 2800000 | EJ35: -400000 | EK35: 6200000 | EL35: 2500000 | EM35: 2400000 | EN35: -800000 | EO35: 5300000 | EP35: 700000 | EQ35: 2000000 | ER35: -1500000 | ES35: 2500000 | ET35: 1100000 | EU35: 2400000 | EV35: -1700000 | EW35: 7600000 | EX35: 4100000
A36: InterestIncome | AW36: 36000 | AX36: 10000 | AY36: 26000 | AZ36: 19000 | BA36: 92000 | BB36: 90000 | BC36: 32000 | BD36: 6000 | BE36: 9000 | BF36: 26000 | BG36: 15000 | BH36: 94000 | BI36: 268000 | BJ36: 619000 | BK36: 1217000 | BL36: 957000 | BM36: 1378000 | BN36: 1388000 | BO36: 3506000 | BP36: 2573000 | BQ36: 2210000 | BR36: 885000 | BS36: 1457000 | BT36: 2450000 | BU36: 2559000 | BV36: 1670000 | BW36: 2156000 | BX36: 2616000
A37: InterestExpense | B37: 295874000 | C37: 84337000 | D37: 83038000 | E37: 74818000 | F37: 53681000 | G37: 43098000 | H37: 39676000 | I37: 38506000 | J37: 39198000 | K37: 39430000 | L37: 40392000 | M37: 40268000 | N37: 40298000 | O37: 39326000 | P37: 30493000 | Q37: 25567000 | R37: 24264000 | S37: 24810000 | T37: 25933000 | U37: 25061000 | V37: 24586000 | W37: 25451000 | X37: 24773000 | Y37: 24289000 | Z37: 23995000 | AA37: 23748000 | AB37: 25004000 | AC37: 25511000 | AD37: 23877000 | AE37: 24352000 | AF37: 24081000 | AG37: 23275000 | AH37: 21394000 | AI37: 20699000 | AJ37: 21576000 | AK37: 21532000 | AL37: 21835000 | AM37: 22598000 | AN37: 22267000 | AO37: 22313000 | AP37: 21524000 | AQ37: 20631000 | AR37: 24516000 | AS37: 27460000 | AT37: 27726000 | AU37: 35666000 | AV37: 37074000 | AW37: 40105000 | AX37: 38642000 | AY37: 60653000 | AZ37: 65591000 | BA37: 65629000 | BB37: 67235000 | BC37: 69330000 | BD37: 72018000 | BE37: 78952000 | BF37: 87612000 | BG37: 89945000 | BH37: 89235000 | BI37: 93234000 | BJ37: 98393000 | BK37: 99434000 | BL37: 100871000 | BM37: 104420000 | BN37: 111957000 | BO37: 40652000 | BP37: 6167000 | BQ37: 7891000 | BR37: 10904000 | BS37: 8873000 | BT37: 7247000 | BU37: 7593000 | BV37: 5321000 | BW37: 7344000 | BX37: 5968000 | CI37: 11337000 | CJ37: 10432000 | CK37: 10752000 | CL37: 11480000 | CM37: 11957000 | CN37: 11600000
A38: NetInterestIncome | B38: -295874000 | C38: -84337000 | D38: -83038000 | E38: -74818000 | F38: -53681000 | G38: -43098000 | H38: -39676000 | I38: -38506000 | J38: -39198000 | K38: -39430000 | L38: -40392000 | M38: -40268000 | N38: -40298000 | O38: -39326000 | P38: -30493000 | Q38: -25567000 | R38: -24264000 | S38: -24810000 | T38: -25933000 | U38: -25061000 | V38: -24586000 | W38: -25451000 | X38: -24773000 | Y38: -24289000 | Z38: -23995000 | AA38: -23748000 | AB38: -25004000 | AC38: -25511000 | AD38: -23877000 | AE38: -24352000 | AF38: -24081000 | AG38: -23275000 | AH38: -21394000 | AI38: -20699000 | AJ38: -21576000 | AK38: -21532000 | AL38: -21835000 | AM38: -22598000 | AN38: -22267000 | AO38: -22313000 | AP38: -21524000 | AQ38: -20631000 | AR38: -24516000 | AS38: -27460000 | AT38: -27726000 | AU38: -35666000 | AV38: -37074000 | AW38: -40069000 | AX38: -38632000 | AY38: -60627000 | AZ38: -65572000 | BA38: -65537000 | BB38: -67145000 | BC38: -69298000 | BD38: -72012000 | BE38: -78943000 | BF38: -87586000 | BG38: -89930000 | BH38: -89141000 | BI38: -92966000 | BJ38: -97774000 | BK38: -98217000 | BL38: -99914000 | BM38: -103042000 | BN38: -110569000 | BO38: -37146000 | BP38: -3594000 | BQ38: -5681000 | BR38: -10019000 | BS38: -7416000 | BT38: -4797000 | BU38: -5034000 | BV38: -3651000 | BW38: -5188000 | BX38: -3352000 | BY38: -5372000 | BZ38: -6364000 | CA38: -4041000 | CB38: -6442000 | CC38: -6217000 | CD38: -7976000 | CE38: -7899000 | CF38: -9411000 | CG38: -9333000 | CH38: -11537000 | CI38: -11337000 | CJ38: -10432000 | CK38: -10752000 | CL38: -11480000 | CM38: -11957000 | CN38: -11600000
A39: EBIT | B39: 3101476000 | C39: 692314000 | D39: 740858000 | E39: 933174000 | F39: 735130000 | G39: 913426000 | H39: 746157000 | I39: 796669000 | J39: 665588000 | K39: 849568000 | L39: 908850000 | M39: 872224000 | N39: 773130000 | O39: 1042627000 | P39: 866784000 | Q39: 720875000 | R39: 491417000 | S39: 577775000 | T39: 512237000 | U39: 638503000 | V39: 442143000 | W39: 544457000 | X39: 490184000 | Y39: 623446000 | Z39: 417431000 | AA39: 493146000 | AB39: 470293000 | AC39: 680618000 | AD39: 392991000 | AE39: 509097000 | AF39: 480743000 | AG39: 612429000 | AH39: 423533000 | AI39: 475812000 | AJ39: 428194000 | AK39: 566716000 | AL39: 394143000 | AM39: 428526000 | AN39: 379708000 | AO39: 538122000 | AP39: 390241000 | AQ39: 412822000 | AR39: 376129000 | AS39: 522349000 | AT39: 359661000 | AU39: 360657000 | AV39: 382653000 | AW39: 508225000 | AX39: 310874000 | AY39: 291816000 | AZ39: 319365000 | BA39: 408225000 | BB39: 266112000 | BC39: 294263000 | BD39: 290584000 | BE39: 223185000 | BF39: 215752000 | BG39: 235627000 | BH39: 223296000 | BI39: 226740000 | BJ39: 104085000 | BK39: 143980000 | BL39: 111530000 | BM39: 192437000 | BN39: 60307000 | BO39: -48067000 | BP39: 57941000 | BQ39: 85285000 | BR39: 4224000 | BS39: 82034000 | BT39: 83735000 | BU39: 234823000 | BV39: 103282000 | BW39: 123226000 | BX39: 109537000 | BY39: 226919000 | BZ39: 113956000 | CA39: 108126000 | CB39: 114550000 | CC39: 185123000 | CD39: 131346000 | CE39: 101843000 | CF39: 102951000 | CG39: 207086000 | CH39: 93431000 | CI39: 78260000 | CJ39: 82988000 | CK39: 162884000 | CL39: 86078000 | CM39: 55214000 | CN39: 69435000 | CO39: -67655000 | CP39: 84840000 | CQ39: 65988000 | CR39: 70831000 | CS39: 142202000 | CT39: 82000000 | CU39: 67200000 | CV39: 57900000 | CW39: 118564000 | CX39: 66300000 | CY39: 55100000 | CZ39: 49400000 | DA39: 105043000 | DB39: 55600000 | DC39: 43400000 | DD39: 31500000 | DE39: 83376000 | DF39: 44500000 | DG39: 36400000 | DH39: 25500000 | DI39: 63307000 | DJ39: 35000000 | DK39: 30500000 | DL39: 20000000 | DM39: 53487000 | DN39: 28900000 | DO39: 23100000 | DP39: 15700000 | DQ39: 36000000 | DR39: 17700000 | DS39: 16300000 | DT39: 10100000 | DU39: 28200000 | DV39: 14400000 | DW39: 11400000 | DX39: 6900000 | DY39: 20200000 | DZ39: 8100000 | EA39: 6800000 | EB39: 2600000 | EC39: 14800000 | ED39: 6100000 | EE39: 5700000 | EF39: 1700000 | EG39: 13100000 | EH39: 6000000 | EI39: 6000000 | EJ39: 129900000 | EK39: -400400000 | EL39: 153100000 | EM39: 145600000 | EN39: 124200000 | EO39: -380600000 | EP39: 136900000 | EQ39: 146000000 | ER39: 116000000 | ES39: -364100000 | ET39: 134000000 | EU39: 135900000 | EV39: 108700000 | EW39: -360300000 | EX39: 138700000
A40: EBITDA | B40: 3886918000 | C40: 900694000 | D40: 942765000 | E40: 1125537000 | F40: 917922000 | G40: 913426000 | H40: 918720000 | I40: 796669000 | J40: 827851000 | K40: 1008104000 | L40: 1062996000 | M40: 1021995000 | N40: 773130000 | O40: 1183589000 | P40: 1004439000 | Q40: 720875000 | R40: 617887000 | S40: 701198000 | T40: 634722000 | U40: 638503000 | V40: 556995000 | W40: 656633000 | X40: 599519000 | Y40: 623446000 | Z40: 518386000 | AA40: 592176000 | AB40: 568879000 | AC40: 680618000 | AD40: 488435000 | AE40: 603715000 | AF40: 573067000 | AG40: 612429000 | AH40: 512086000 | AI40: 563394000 | AJ40: 515346000 | AK40: 566716000 | AL40: 480404000 | AM40: 513866000 | AN40: 463866000 | AO40: 538122000 | AP40: 474676000 | AQ40: 495566000 | AR40: 456622000 | AS40: 602862000 | AT40: 435799000 | AU40: 434646000 | AV40: 454924000 | AW40: 578862000 | AX40: 379774000 | AY40: 360201000 | AZ40: 386851000 | BA40: 473413000 | BB40: 329695000 | BC40: 357167000 | BD40: 353836000 | BE40: 285911000 | BF40: 278729000 | BG40: 302164000 | BH40: 287827000 | BI40: 290484000 | BJ40: 166217000 | BK40: 204597000 | BL40: 172936000 | BM40: 251743000 | BN40: 125639000 | BO40: 10974000 | BP40: 108392000 | BQ40: 136982000 | BR40: 55655000 | BS40: 130736000 | BT40: 132513000 | BU40: 283830000 | BV40: 150783000 | BW40: 169536000 | BX40: 153543000 | BY40: 268515000 | BZ40: 156141000 | CA40: 149187000 | CB40: 154186000 | CC40: 224408000 | CD40: 169577000 | CE40: 139970000 | CF40: 139707000 | CG40: 239743000 | CH40: 129714000 | CI40: 112275000 | CJ40: 114992000 | CK40: 193747000 | CL40: 117202000 | CM40: 86304000 | CN40: 99325000 | CO40: -14827000 | CP40: 105459000 | CQ40: 85333000 | CR40: 89438000 | CS40: 252946000 | CT40: 98500000 | CU40: 82700000 | CV40: 72700000 | CW40: 210476000 | CX40: 79800000 | CY40: 68000000 | CZ40: 61800000 | DA40: 171577000 | DB40: 65600000 | DC40: 52600000 | DD40: 40100000 | DE40: 137341000 | DF40: 52600000 | DG40: 44000000 | DH40: 32800000 | DI40: 106452000 | DJ40: 41500000 | DK40: 36500000 | DL40: 25400000 | DM40: 75150000 | DN40: 32300000 | DO40: 27000000 | DP40: 19400000 | DQ40: 40800000 | DR40: 23300000 | DS40: 19000000 | DT40: 12600000 | DU40: 30400000 | DV40: 16600000 | DW40: 13300000 | DX40: 8800000 | DY40: 22100000 | DZ40: 9800000 | EA40: 8400000 | EB40: 4100000 | EC40: 16500000 | ED40: 7800000 | EE40: 7300000 | EF40: 3200000 | EG40: 15000000 | EH40: 7400000 | EI40: 7400000 | EJ40: 129900000 | EK40: -400400000 | EL40: 153100000 | EM40: 145600000 | EN40: 124200000 | EO40: -380600000 | EP40: 136900000 | EQ40: 146000000 | ER40: 116000000 | ES40: -364100000 | ET40: 134000000 | EU40: 135900000 | EV40: 108700000 | EW40: -360300000 | EX40: 138700000
A41: ReconciledCostOfRevenue | B41: 26773139000 | C41: 6751495000 | D41: 6387358000 | E41: 7054590000 | F41: 6579696000 | G41: 6377490000 | H41: 6012989000 | I41: 5951208000 | J41: 5898400000 | K41: 5912539000 | L41: 5645296000 | M41: 5677829000 | N41: 5631385000 | O41: 5866006000 | P41: 5852757000 | Q41: 4884879000 | R41: 4926307000 | S41: 4832817000 | T41: 4620909000 | U41: 4578120000 | V41: 4522403000 | W41: 4468436000 | X41: 4252214000 | Y41: 4164033000 | Z41: 4137150000 | AA41: 4037783000 | AB41: 3910642000 | AC41: 4108499000 | AD41: 3732519000 | AE41: 3710124000 | AF41: 3652818000 | AG41: 3604669000 | AH41: 3530086000 | AI41: 3507749000 | AJ41: 3419967000 | AK41: 3373620000 | AL41: 3300661000 | AM41: 3268465000 | AN41: 3164335000 | AO41: 3059134000 | AP41: 3053345000 | AQ41: 3017361000 | AR41: 2938585000 | AS41: 2839822000 | AT41: 2738524000 | AU41: 2685432000 | AV41: 2672949000 | AW41: 2838704000 | AX41: 2479422000 | AY41: 2426852000 | AZ41: 2364300000 | BA41: 2355951000 | BB41: 2212759000 | BC41: 2178176000 | BD41: 2111558000 | BE41: 2160396000 | BF41: 2025669000 | BG41: 1995865000 | BH41: 1924579000 | BI41: 2008150000 | BJ41: 1826651000 | BK41: 1851349000 | BL41: 1710421000 | BM41: 1819202000 | BN41: 1666042000 | BO41: 1724326000 | BP41: 1642207000 | BQ41: 1908036000 | BR41: 1686949000 | BS41: 1639519000 | BT41: 1567113000 | BU41: 1749575000 | BV41: 1478872000 | BW41: 1474486000 | BX41: 1414480000 | BY41: 1537561000 | BZ41: 1325202000 | CA41: 1299263000 | CB41: 1235709000 | CC41: 1389992000 | CD41: 1168449000 | CE41: 1178264000 | CF41: 1117158000 | CG41: 1231599000 | CH41: 1069119000 | CI41: 1066300000 | CJ41: 1009120000 | CK41: 1110489000 | CL41: 927944000 | CM41: 893971000 | CN41: 881079000 | CO41: 1066857000 | CP41: 772996000 | CQ41: 735445000 | CR41: 724370000 | CS41: 880073000 | CT41: 689100000 | CU41: 681100000 | CV41: 633400000 | CW41: 746412000 | CX41: 570200000 | CY41: 548800000 | CZ41: 527400000 | DA41: 632590000 | DB41: 475600000 | DC41: 445900000 | DD41: 386800000 | DE41: 499103000 | DF41: 368400000 | DG41: 368300000 | DH41: 339800000 | DI41: 428269000 | DJ41: 315400000 | DK41: 300300000 | DL41: 252500000 | DM41: 341730000 | DN41: 250500000 | DO41: 233700000 | DP41: 210800000 | DQ41: 267500000 | DR41: 196000000 | DS41: 185300000 | DT41: 161800000 | DU41: 204700000 | DV41: 161400000 | DW41: 157700000 | DX41: 138000000 | DY41: 175600000 | DZ41: 136600000 | EA41: 125400000 | EB41: 108000000 | EC41: 144800000 | ED41: 118600000 | EE41: 111000000 | EF41: 97800000 | EG41: 133600000 | EH41: 104600000 | EI41: 103800000
A42: ReconciledDepreciation | B42: 785442000 | C42: 208380000 | D42: 201907000 | E42: 192363000 | F42: 182792000 | G42: 177159000 | H42: 172563000 | I42: 166371000 | J42: 162263000 | K42: 158536000 | L42: 154146000 | M42: 149771000 | N42: 145849000 | O42: 140962000 | P42: 137655000 | Q42: 132426000 | R42: 126470000 | S42: 123423000 | T42: 122485000 | U42: 117771000 | V42: 114852000 | W42: 112176000 | X42: 109335000 | Y42: 105660000 | Z42: 100955000 | AA42: 99030000 | AB42: 98586000 | AC42: 97545000 | AD42: 95444000 | AE42: 94618000 | AF42: 92324000 | AG42: 89144000 | AH42: 88553000 | AI42: 87582000 | AJ42: 87152000 | AK42: 86594000 | AL42: 86261000 | AM42: 85340000 | AN42: 84158000 | AO42: 85165000 | AP42: 84435000 | AQ42: 82744000 | AR42: 80493000 | AS42: 80513000 | AT42: 76138000 | AU42: 73989000 | AV42: 72271000 | AW42: 70637000 | AX42: 68900000 | AY42: 68385000 | AZ42: 67486000 | BA42: 65188000 | BB42: 63583000 | BC42: 62904000 | BD42: 63252000 | BE42: 62726000 | BF42: 62977000 | BG42: 66537000 | BH42: 64531000 | BI42: 63744000 | BJ42: 62132000 | BK42: 60617000 | BL42: 61406000 | BM42: 59306000 | BN42: 65332000 | BO42: 59041000 | BP42: 50451000 | BQ42: 51697000 | BR42: 51431000 | BS42: 48702000 | BT42: 48778000 | BU42: 49007000 | BV42: 47501000 | BW42: 46310000 | BX42: 44006000 | BY42: 41596000 | BZ42: 42185000 | CA42: 41061000 | CB42: 39636000 | CC42: 39285000 | CD42: 38231000 | CE42: 38127000 | CF42: 36756000 | CG42: 32657000 | CH42: 36283000 | CI42: 34015000 | CJ42: 32004000 | CK42: 30863000 | CL42: 31124000 | CM42: 31090000 | CN42: 29890000 | CO42: 52828000 | CP42: 20619000 | CQ42: 19345000 | CR42: 18607000 | CS42: 110744000 | CT42: -16500000 | CU42: -15500000 | CV42: -14800000 | CW42: 91912000 | CX42: -13500000 | CY42: -12900000 | CZ42: -12400000 | DA42: 66534000 | DB42: -10000000 | DC42: -9200000 | DD42: -8600000 | DE42: 53965000 | DF42: -8100000 | DG42: -7600000 | DH42: -7300000 | DI42: 43145000 | DJ42: -6500000 | DK42: -6000000 | DL42: -5400000 | DM42: 21663000 | DN42: 3400000 | DO42: -4100000 | DP42: -3700000 | DQ42: 4800000 | DR42: -3100000 | DS42: -2700000 | DT42: -2500000 | DU42: -2200000 | DV42: -2200000 | DW42: -1900000 | DX42: -1900000 | DY42: -1900000 | DZ42: -1700000 | EA42: -1600000 | EB42: -1500000 | EC42: -1700000 | ED42: -1700000 | EE42: -1600000 | EF42: -1500000 | EG42: -1900000 | EH42: -1400000 | EI42: 1400000
A43: NetIncomeFromContinuingOperationNetMinorityInterest | B43: 2168517000 | C43: 468835000 | D43: 514380000 | E43: 659135000 | F43: 526167000 | G43: 678030000 | H43: 552657000 | I43: 597433000 | J43: 487031000 | K43: 637019000 | L43: 677749000 | M43: 642743000 | N43: 574260000 | O43: 787601000 | P43: 650446000 | Q43: 535437000 | R43: 365550000 | S43: 426555000 | T43: 385013000 | U43: 483241000 | V43: 334142000 | W43: 407237000 | X43: 364852000 | Y43: 712155000 | Z43: 252533000 | AA43: 294783000 | AB43: 279489000 | AC43: 414176000 | AD43: 235315000 | AE43: 306518000 | AF43: 295124000 | AG43: 376175000 | AH43: 253321000 | AI43: 282349000 | AJ43: 253235000 | AK43: 355371000 | AL43: 236316000 | AM43: 251260000 | AN43: 222398000 | AO43: 322173000 | AP43: 237385000 | AQ43: 245475000 | AR43: 220083000 | AS43: 317422000 | AT43: 207685000 | AU43: 214140000 | AV43: 213415000 | AW43: 292510000 | AX43: 171164000 | AY43: 146042000 | AZ43: 156969000 | BA43: 222546000 | BB43: 128120000 | BC43: 141195000 | BD43: 135996000 | BE43: 87197000 | BF43: 75649000 | BG43: 93590000 | BH43: 83006000 | BI43: 81854000 | BJ43: -7306000 | BK43: 27718000 | BL43: 5916000 | BM43: 55389000 | BN43: -33032000 | BO43: -68818000 | BP43: 34875000 | BQ43: 50090000 | BR43: -5285000 | BS43: 45468000 | BT43: 47670000 | BU43: 145272000 | BV43: 64425000 | BW43: 75558000 | BX43: 64900000 | BY43: 133893000 | BZ43: 71126000 | CA43: 71322000 | CB43: 67849000 | CC43: 102829000 | CD43: 77903000 | CE43: 59936000 | CF43: 60332000 | CG43: 108086000 | CH43: 68570000 | CI43: 42362000 | CJ43: 45928000 | CK43: 97443000 | CL43: 46737000 | CM43: 27100000 | CN43: 36233000 | CO43: -63998000 | CP43: 50990000 | CQ43: 39310000 | CR43: 44340000 | CS43: 90627000 | CT43: 50900000 | CU43: 41600000 | CV43: 36300000 | CW43: 78033000 | CX43: 40300000 | CY43: 33300000 | CZ43: 30400000 | DA43: 65028000 | DB43: 33600000 | DC43: 26700000 | DD43: 19300000 | DE43: 51500000 | DF43: 26600000 | DG43: 21900000 | DH43: 15000000 | DI43: 38518000 | DJ43: 20000000 | DK43: 17700000 | DL43: 11600000 | DM43: 32834000 | DN43: 17300000 | DO43: 14000000 | DP43: 9500000 | DQ43: 22100000 | DR43: 11000000 | DS43: 9600000 | DT43: 5900000 | DU43: 16800000 | DV43: 8300000 | DW43: 6700000 | DX43: 3900000 | DY43: 12300000 | DZ43: 4300000 | EA43: 3800000 | EB43: 1200000 | EC43: 8900000 | ED43: 2800000 | EE43: 2500000 | EF43: 400000 | EG43: 7300000 | EH43: 2800000 | EI43: 2800000 | EJ43: -400000 | EK43: 6200000 | EL43: 2500000 | EM43: 2400000 | EN43: -800000 | EO43: 5300000 | EP43: 700000 | EQ43: 2000000 | ER43: -1500000 | ES43: 2500000 | ET43: 1100000 | EU43: 2400000 | EV43: -1700000 | EW43: 7600000 | EX43: 4100000
